Workbook
Name SegmentaciónDeDatos_DEPARTAMENTO: #N/A
Name SegmentaciónDeDatos_PROVINCIA: #N/A
Name SegmentaciónDeDatos_TIPO_DE_SUPERFICIE: #N/A

Sheet Tac_Moq
A1: IDENTIFICADOR | B1: N° CONVENIO | C1: DEPARTAMENTO | D1: PROVINCIA | E1: DISTRITO | F1: CÓDIGO DE RUTA | G1: DENOMINACION DE INTERVENCION | H1: LONGITUD TOTAL (km) | I1: TIPO DE SUPERFICIE | J1: COSTO (km/mes) | K1: PLAZO (dc) | L1: EJECUCIÓN S/ | M1: GG.OO S/ | N1: TOTAL S/ | O1: N° DE CONTRATO | P1: CONTRATISTA | Q1: PLAZO CONTRACTUAL (DC) | R1: F. INICIO MANTENIMIENTO | S1: F. TERMINO MANTENIMIENTO | T1: MONTO CONTRATADO | U1: GASTOS OPERATIVOS (S/) | V1: TOTAL (S/) | W1: PLAZO DE ADENDA (DC) | X1: F. INICIO MANTENIMIENTO | Y1: F. TERMINO MANTENIMIENTO | Z1: MONTO DE ADENDA | AA1: GASTOS OPERATIVOS (S/) | AB1: TOTAL (S/) | AC1: N° TRAMITE | AD1: 46112 | AE1: MANTENIMIENTO S/ | AF1: GASTOS OPERATIVOS S/ | AG1: TOTAL S/ | AH1: N° TRAMITE | AI1: 46142 | AJ1: MANTENIMIENTO S/ | AK1: GASTOS OPERATIVOS S/ | AL1: TOTAL S/ | AM1: N° TRAMITE | AN1: 46173 | AO1: MANTENIMIENTO S/ | AP1: GASTOS OPERATIVOS S/ | AQ1: TOTAL S/ | AR1: N° TRAMITE | AS1: 46203 | AT1: MANTENIMIENTO S/ | AU1: GASTOS OPERATIVOS S/ | AV1: TOTAL S/ | AW1: N° TRAMITE | AX1: 46234 | AY1: MANTENIMIENTO S/ | AZ1: GASTOS OPERATIVOS S/ | BA1: TOTAL S/ | BB1: N° TRAMITE | BC1: 46265 | BD1: MANTENIMIENTO S/ | BE1: GASTOS OPERATIVOS S/ | BF1: TOTAL S/ | BG1: N° TRAMITE | BH1: 46295 | BI1: MANTENIMIENTO S/ | BJ1: GASTOS OPERATIVOS S/ | BK1: TOTAL S/ | BL1: N° TRAMITE | BM1: 46326 | BN1: MANTENIMIENTO S/ | BO1: GASTOS OPERATIVOS S/ | BP1: TOTAL S/ | BQ1: N° TRAMITE | BR1: 46356 | BS1: MANTENIMIENTO S/ | BT1: GASTOS OPERATIVOS S/ | BU1: TOTAL S/ | BV1: N° TRAMITE | BW1: 46387 | BX1: MANTENIMIENTO S/ | BY1: GASTOS OPERATIVOS S/ | BZ1: TOTAL S/ | CA1: TOTAL DIAS EJECUTADOS | CB1: MANTENIMIENTO S/ | CC1: GASTOS OPERATIVOS S/ | CD1: TOTAL S/ | CE1: ERROR MANTENIMIENTO | CF1: ERROR GASTOS OPERATIVOS | CG1: AREA USUARIA | CH1: RESPONSABLE DE AREA USUARIA | CI1: CARGO | CJ1: TELEFONO AU | CK1: INSPECTOR | CL1: DOC. DESIGNACIÓN | CM1: FECHA DESIGNACIÓN | CN1: TELEFONO INSPECTOR | CO1: MONITOR | CP1: TELEFONO MONITOR
A2: 1 | B2: 236 | C2: MOQUEGUA | D2: ILO | E2: ALGARROBAL | F2: MO-609 | G2: LA PAMPA (KM 13+600) - EMP. PE-36 (KM 21+725) | H2: 8.125 | I2: AFIRMADO | J2: 735 | K2: 240 | L2: 47775 | M2: 4777 | N2: 52552 | Q2: =+$K2 -> 240 | S2: =IF(Q2+R2=0,"",Q2+R2-1) -> 239 | U2: =+ROUND(T2*0.1,2) -> 0 | V2: =+SUM(T2:U2) -> 0 | X2: =+$R2 -> 0 | Y2: =IF(W2>0,X2+W2-1,"") | AA2: =+ROUND(Z2*0.1,2) -> 0 | AB2: =+SUM(Z2:AA2) -> 0 | AD2: =MAX(0,MIN(IF($Y2<>"",$Y2,$S2),AD$1)-MAX($R2,EOMONTH(AD$1,-1)+1)+1) -> 0 | AE2: =ROUND(IF($Z2="",$T2,$Z2)*(AD2/IF($W2="",$Q2,$W2)),2) -> 0 | AF2: =+ROUND(AE2*0.1,2) -> 0 | AG2: =+SUM(AE2:AF2) -> 0 | AI2: =MAX(0,MIN(IF($Y2<>"",$Y2,$S2),AI$1)-MAX($R2,EOMONTH(AI$1,-1)+1)+1) -> 0 | AJ2: =ROUND(IF($Z2="",$T2,$Z2)*(AI2/IF($W2="",$Q2,$W2)),2) -> 0 | AK2: =+ROUND(AJ2*0.1,2) -> 0 | AL2: =+SUM(AJ2:AK2) -> 0 | AN2: =MAX(0,MIN(IF($Y2<>"",$Y2,$S2),AN$1)-MAX($R2,EOMONTH(AN$1,-1)+1)+1) -> 0 | AO2: =ROUND(IF($Z2="",$T2,$Z2)*(AN2/IF($W2="",$Q2,$W2)),2) -> 0 | AP2: =+ROUND(AO2*0.1,2) -> 0 | AQ2: =+SUM(AO2:AP2) -> 0 | AS2: =MAX(0,MIN(IF($Y2<>"",$Y2,$S2),AS$1)-MAX($R2,EOMONTH(AS$1,-1)+1)+1) -> 0 | AT2: =ROUND(IF($Z2="",$T2,$Z2)*(AS2/IF($W2="",$Q2,$W2)),2) -> 0 | AU2: =+ROUND(AT2*0.1,2) -> 0 | AV2: =+SUM(AT2:AU2) -> 0 | AX2: =MAX(0,MIN(IF($Y2<>"",$Y2,$S2),AX$1)-MAX($R2,EOMONTH(AX$1,-1)+1)+1) -> 0 | AY2: =ROUND(IF($Z2="",$T2,$Z2)*(AX2/IF($W2="",$Q2,$W2)),2) -> 0 | AZ2: =+ROUND(AY2*0.1,2) -> 0 | BA2: =+SUM(AY2:AZ2) -> 0 | BC2: =MAX(0,MIN(IF($Y2<>"",$Y2,$S2),BC$1)-MAX($R2,EOMONTH(BC$1,-1)+1)+1) -> 0 | BD2: =ROUND(IF($Z2="",$T2,$Z2)*(BC2/IF($W2="",$Q2,$W2)),2) -> 0 | BE2: =+ROUND(BD2*0.1,2) -> 0 | BF2: =+SUM(BD2:BE2) -> 0 | BH2: =MAX(0,MIN(IF($Y2<>"",$Y2,$S2),BH$1)-MAX($R2,EOMONTH(BH$1,-1)+1)+1) -> 0 | BI2: =ROUND(IF($Z2="",$T2,$Z2)*(BH2/IF($W2="",$Q2,$W2)),2) -> 0 | BJ2: =+ROUND(BI2*0.1,2) -> 0 | BK2: =+SUM(BI2:BJ2) -> 0 | BM2: =MAX(0,MIN(IF($Y2<>"",$Y2,$S2),BM$1)-MAX($R2,EOMONTH(BM$1,-1)+1)+1) -> 0 | BN2: =ROUND(IF($Z2="",$T2,$Z2)*(BM2/IF($W2="",$Q2,$W2)),2) -> 0 | BO2: =+ROUND(BN2*0.1,2) -> 0 | BP2: =+SUM(BN2:BO2) -> 0 | BR2: =MAX(0,MIN(IF($Y2<>"",$Y2,$S2),BR$1)-MAX($R2,EOMONTH(BR$1,-1)+1)+1) -> 0 | BS2: =ROUND(IF($Z2="",$T2,$Z2)*(BR2/IF($W2="",$Q2,$W2)),2) -> 0 | BT2: =+ROUND(BS2*0.1,2) -> 0 | BU2: =+SUM(BS2:BT2) -> 0 | BW2: =MAX(0,MIN(IF($Y2<>"",$Y2,$S2),BW$1)-MAX($R2,EOMONTH(BW$1,-1)+1)+1) -> 0 | BX2: =ROUND(IF($Z2="",$T2,$Z2)*(BW2/IF($W2="",$Q2,$W2)),2) -> 0 | BY2: =+ROUND(BX2*0.1,2) -> 0 | BZ2: =+SUM(BX2:BY2) -> 0 | CA2: =+AD2+AI2+AN2+AS2+AX2+BC2+BH2+BM2+BR2+BW2 -> 0 | CB2: =+AE2+AJ2+AO2+AT2+AY2+BD2+BI2+BN2+BS2+BX2 -> 0 | CC2: =+AF2+AK2+AP2+AU2+AZ2+BE2+BJ2+BO2+BT2+BY2 -> 0 | CD2: =+SUM(CB2:CC2) -> 0 | CE2: =ROUND(IF($Y2<>"",$Z2,$T2)-CB2,2) -> 0 | CF2: =ROUND(IF($Y2<>"",$AA2,$U2)-CC2,2) -> 0 | CG2: GERENCIA DE TRANSPORTE PUBLICO Y CIRCULACION VIAL | CH2: Pamela Aida Flores Laqui | CI2: Gerente | CJ2: 951 902 578
A3: 2 | B3: 236 | C3: MOQUEGUA | D3: ILO | E3: ALGARROBAL | F3: MO-610 | G3: LORETO (KM 0+280) - YARAL FLORIDA - PEDREGAL - BOCATOMA DE AGUA POTABLE (KM 06+593) | H3: 6.313 | I3: AFIRMADO | J3: 735 | K3: 240 | L3: 37120 | M3: 3712 | N3: 40832 | Q3: =+$K3 -> 240 | S3: =IF(Q3+R3=0,"",Q3+R3-1) -> 239 | U3: =+ROUND(T3*0.1,2) -> 0 | V3: =+SUM(T3:U3) -> 0 | X3: =+$R3 -> 0 | Y3: =IF(W3>0,X3+W3-1,"") | AA3: =+ROUND(Z3*0.1,2) -> 0 | AB3: =+SUM(Z3:AA3) -> 0 | AD3: =MAX(0,MIN(IF($Y3<>"",$Y3,$S3),AD$1)-MAX($R3,EOMONTH(AD$1,-1)+1)+1) -> 0 | AE3: =ROUND(IF($Z3="",$T3,$Z3)*(AD3/IF($W3="",$Q3,$W3)),2) -> 0 | AF3: =+ROUND(AE3*0.1,2) -> 0 | AG3: =+SUM(AE3:AF3) -> 0 | AI3: =MAX(0,MIN(IF($Y3<>"",$Y3,$S3),AI$1)-MAX($R3,EOMONTH(AI$1,-1)+1)+1) -> 0 | AJ3: =ROUND(IF($Z3="",$T3,$Z3)*(AI3/IF($W3="",$Q3,$W3)),2) -> 0 | AK3: =+ROUND(AJ3*0.1,2) -> 0 | AL3: =+SUM(AJ3:AK3) -> 0 | AN3: =MAX(0,MIN(IF($Y3<>"",$Y3,$S3),AN$1)-MAX($R3,EOMONTH(AN$1,-1)+1)+1) -> 0 | AO3: =ROUND(IF($Z3="",$T3,$Z3)*(AN3/IF($W3="",$Q3,$W3)),2) -> 0 | AP3: =+ROUND(AO3*0.1,2) -> 0 | AQ3: =+SUM(AO3:AP3) -> 0 | AS3: =MAX(0,MIN(IF($Y3<>"",$Y3,$S3),AS$1)-MAX($R3,EOMONTH(AS$1,-1)+1)+1) -> 0 | AT3: =ROUND(IF($Z3="",$T3,$Z3)*(AS3/IF($W3="",$Q3,$W3)),2) -> 0 | AU3: =+ROUND(AT3*0.1,2) -> 0 | AV3: =+SUM(AT3:AU3) -> 0 | AX3: =MAX(0,MIN(IF($Y3<>"",$Y3,$S3),AX$1)-MAX($R3,EOMONTH(AX$1,-1)+1)+1) -> 0 | AY3: =ROUND(IF($Z3="",$T3,$Z3)*(AX3/IF($W3="",$Q3,$W3)),2) -> 0 | AZ3: =+ROUND(AY3*0.1,2) -> 0 | BA3: =+SUM(AY3:AZ3) -> 0 | BC3: =MAX(0,MIN(IF($Y3<>"",$Y3,$S3),BC$1)-MAX($R3,EOMONTH(BC$1,-1)+1)+1) -> 0 | BD3: =ROUND(IF($Z3="",$T3,$Z3)*(BC3/IF($W3="",$Q3,$W3)),2) -> 0 | BE3: =+ROUND(BD3*0.1,2) -> 0 | BF3: =+SUM(BD3:BE3) -> 0 | BH3: =MAX(0,MIN(IF($Y3<>"",$Y3,$S3),BH$1)-MAX($R3,EOMONTH(BH$1,-1)+1)+1) -> 0 | BI3: =ROUND(IF($Z3="",$T3,$Z3)*(BH3/IF($W3="",$Q3,$W3)),2) -> 0 | BJ3: =+ROUND(BI3*0.1,2) -> 0 | BK3: =+SUM(BI3:BJ3) -> 0 | BM3: =MAX(0,MIN(IF($Y3<>"",$Y3,$S3),BM$1)-MAX($R3,EOMONTH(BM$1,-1)+1)+1) -> 0 | BN3: =ROUND(IF($Z3="",$T3,$Z3)*(BM3/IF($W3="",$Q3,$W3)),2) -> 0 | BO3: =+ROUND(BN3*0.1,2) -> 0 | BP3: =+SUM(BN3:BO3) -> 0 | BR3: =MAX(0,MIN(IF($Y3<>"",$Y3,$S3),BR$1)-MAX($R3,EOMONTH(BR$1,-1)+1)+1) -> 0 | BS3: =ROUND(IF($Z3="",$T3,$Z3)*(BR3/IF($W3="",$Q3,$W3)),2) -> 0 | BT3: =+ROUND(BS3*0.1,2) -> 0 | BU3: =+SUM(BS3:BT3) -> 0 | BW3: =MAX(0,MIN(IF($Y3<>"",$Y3,$S3),BW$1)-MAX($R3,EOMONTH(BW$1,-1)+1)+1) -> 0 | BX3: =ROUND(IF($Z3="",$T3,$Z3)*(BW3/IF($W3="",$Q3,$W3)),2) -> 0 | BY3: =+ROUND(BX3*0.1,2) -> 0 | BZ3: =+SUM(BX3:BY3) -> 0 | CA3: =+AD3+AI3+AN3+AS3+AX3+BC3+BH3+BM3+BR3+BW3 -> 0 | CB3: =+AE3+AJ3+AO3+AT3+AY3+BD3+BI3+BN3+BS3+BX3 -> 0 | CC3: =+AF3+AK3+AP3+AU3+AZ3+BE3+BJ3+BO3+BT3+BY3 -> 0 | CD3: =+SUM(CB3:CC3) -> 0 | CE3: =ROUND(IF($Y3<>"",$Z3,$T3)-CB3,2) -> 0 | CF3: =ROUND(IF($Y3<>"",$AA3,$U3)-CC3,2) -> 0 | CG3: GERENCIA DE TRANSPORTE PUBLICO Y CIRCULACION VIAL | CH3: Pamela Aida Flores Laqui | CI3: Gerente | CJ3: 951 902 578
A4: 3 | B4: 236 | C4: MOQUEGUA | D4: ILO | E4: ILO; ALGARROBAL | F4: MO-609 | G4: EMP. PE-1S D - EL ALGARROBAL - EL HUESITO - LA PAMPA (KM 13+600) | H4: 13.6 | I4: PAVIMENTADO | J4: 880 | K4: 240 | L4: 95744 | M4: 9574 | N4: 105318 | Q4: =+$K4 -> 240 | S4: =IF(Q4+R4=0,"",Q4+R4-1) -> 239 | U4: =+ROUND(T4*0.1,2) -> 0 | V4: =+SUM(T4:U4) -> 0 | X4: =+$R4 -> 0 | Y4: =IF(W4>0,X4+W4-1,"") | AA4: =+ROUND(Z4*0.1,2) -> 0 | AB4: =+SUM(Z4:AA4) -> 0 | AD4: =MAX(0,MIN(IF($Y4<>"",$Y4,$S4),AD$1)-MAX($R4,EOMONTH(AD$1,-1)+1)+1) -> 0 | AE4: =ROUND(IF($Z4="",$T4,$Z4)*(AD4/IF($W4="",$Q4,$W4)),2) -> 0 | AF4: =+ROUND(AE4*0.1,2) -> 0 | AG4: =+SUM(AE4:AF4) -> 0 | AI4: =MAX(0,MIN(IF($Y4<>"",$Y4,$S4),AI$1)-MAX($R4,EOMONTH(AI$1,-1)+1)+1) -> 0 | AJ4: =ROUND(IF($Z4="",$T4,$Z4)*(AI4/IF($W4="",$Q4,$W4)),2) -> 0 | AK4: =+ROUND(AJ4*0.1,2) -> 0 | AL4: =+SUM(AJ4:AK4) -> 0 | AN4: =MAX(0,MIN(IF($Y4<>"",$Y4,$S4),AN$1)-MAX($R4,EOMONTH(AN$1,-1)+1)+1) -> 0 | AO4: =ROUND(IF($Z4="",$T4,$Z4)*(AN4/IF($W4="",$Q4,$W4)),2) -> 0 | AP4: =+ROUND(AO4*0.1,2) -> 0 | AQ4: =+SUM(AO4:AP4) -> 0 | AS4: =MAX(0,MIN(IF($Y4<>"",$Y4,$S4),AS$1)-MAX($R4,EOMONTH(AS$1,-1)+1)+1) -> 0 | AT4: =ROUND(IF($Z4="",$T4,$Z4)*(AS4/IF($W4="",$Q4,$W4)),2) -> 0 | AU4: =+ROUND(AT4*0.1,2) -> 0 | AV4: =+SUM(AT4:AU4) -> 0 | AX4: =MAX(0,MIN(IF($Y4<>"",$Y4,$S4),AX$1)-MAX($R4,EOMONTH(AX$1,-1)+1)+1) -> 0 | AY4: =ROUND(IF($Z4="",$T4,$Z4)*(AX4/IF($W4="",$Q4,$W4)),2) -> 0 | AZ4: =+ROUND(AY4*0.1,2) -> 0 | BA4: =+SUM(AY4:AZ4) -> 0 | BC4: =MAX(0,MIN(IF($Y4<>"",$Y4,$S4),BC$1)-MAX($R4,EOMONTH(BC$1,-1)+1)+1) -> 0 | BD4: =ROUND(IF($Z4="",$T4,$Z4)*(BC4/IF($W4="",$Q4,$W4)),2) -> 0 | BE4: =+ROUND(BD4*0.1,2) -> 0 | BF4: =+SUM(BD4:BE4) -> 0 | BH4: =MAX(0,MIN(IF($Y4<>"",$Y4,$S4),BH$1)-MAX($R4,EOMONTH(BH$1,-1)+1)+1) -> 0 | BI4: =ROUND(IF($Z4="",$T4,$Z4)*(BH4/IF($W4="",$Q4,$W4)),2) -> 0 | BJ4: =+ROUND(BI4*0.1,2) -> 0 | BK4: =+SUM(BI4:BJ4) -> 0 | BM4: =MAX(0,MIN(IF($Y4<>"",$Y4,$S4),BM$1)-MAX($R4,EOMONTH(BM$1,-1)+1)+1) -> 0 | BN4: =ROUND(IF($Z4="",$T4,$Z4)*(BM4/IF($W4="",$Q4,$W4)),2) -> 0 | BO4: =+ROUND(BN4*0.1,2) -> 0 | BP4: =+SUM(BN4:BO4) -> 0 | BR4: =MAX(0,MIN(IF($Y4<>"",$Y4,$S4),BR$1)-MAX($R4,EOMONTH(BR$1,-1)+1)+1) -> 0 | BS4: =ROUND(IF($Z4="",$T4,$Z4)*(BR4/IF($W4="",$Q4,$W4)),2) -> 0 | BT4: =+ROUND(BS4*0.1,2) -> 0 | BU4: =+SUM(BS4:BT4) -> 0 | BW4: =MAX(0,MIN(IF($Y4<>"",$Y4,$S4),BW$1)-MAX($R4,EOMONTH(BW$1,-1)+1)+1) -> 0 | BX4: =ROUND(IF($Z4="",$T4,$Z4)*(BW4/IF($W4="",$Q4,$W4)),2) -> 0 | BY4: =+ROUND(BX4*0.1,2) -> 0 | BZ4: =+SUM(BX4:BY4) -> 0 | CA4: =+AD4+AI4+AN4+AS4+AX4+BC4+BH4+BM4+BR4+BW4 -> 0 | CB4: =+AE4+AJ4+AO4+AT4+AY4+BD4+BI4+BN4+BS4+BX4 -> 0 | CC4: =+AF4+AK4+AP4+AU4+AZ4+BE4+BJ4+BO4+BT4+BY4 -> 0 | CD4: =+SUM(CB4:CC4) -> 0 | CE4: =ROUND(IF($Y4<>"",$Z4,$T4)-CB4,2) -> 0 | CF4: =ROUND(IF($Y4<>"",$AA4,$U4)-CC4,2) -> 0 | CG4: GERENCIA DE TRANSPORTE PUBLICO Y CIRCULACION VIAL | CH4: Pamela Aida Flores Laqui | CI4: Gerente | CJ4: 951 902 578
A5: 4 | B5: 236 | C5: MOQUEGUA | D5: ILO | E5: ILO; ALGARROBAL | F5: MO-611 | G5: EMP. PE-36 - EMP. MO-609 (KM 05+389) | H5: 5.389 | I5: PAVIMENTADO | J5: 880 | K5: 240 | L5: 37939 | M5: 3793 | N5: 41732 | Q5: =+$K5 -> 240 | S5: =IF(Q5+R5=0,"",Q5+R5-1) -> 239 | U5: =+ROUND(T5*0.1,2) -> 0 | V5: =+SUM(T5:U5) -> 0 | X5: =+$R5 -> 0 | Y5: =IF(W5>0,X5+W5-1,"") | AA5: =+ROUND(Z5*0.1,2) -> 0 | AB5: =+SUM(Z5:AA5) -> 0 | AD5: =MAX(0,MIN(IF($Y5<>"",$Y5,$S5),AD$1)-MAX($R5,EOMONTH(AD$1,-1)+1)+1) -> 0 | AE5: =ROUND(IF($Z5="",$T5,$Z5)*(AD5/IF($W5="",$Q5,$W5)),2) -> 0 | AF5: =+ROUND(AE5*0.1,2) -> 0 | AG5: =+SUM(AE5:AF5) -> 0 | AI5: =MAX(0,MIN(IF($Y5<>"",$Y5,$S5),AI$1)-MAX($R5,EOMONTH(AI$1,-1)+1)+1) -> 0 | AJ5: =ROUND(IF($Z5="",$T5,$Z5)*(AI5/IF($W5="",$Q5,$W5)),2) -> 0 | AK5: =+ROUND(AJ5*0.1,2) -> 0 | AL5: =+SUM(AJ5:AK5) -> 0 | AN5: =MAX(0,MIN(IF($Y5<>"",$Y5,$S5),AN$1)-MAX($R5,EOMONTH(AN$1,-1)+1)+1) -> 0 | AO5: =ROUND(IF($Z5="",$T5,$Z5)*(AN5/IF($W5="",$Q5,$W5)),2) -> 0 | AP5: =+ROUND(AO5*0.1,2) -> 0 | AQ5: =+SUM(AO5:AP5) -> 0 | AS5: =MAX(0,MIN(IF($Y5<>"",$Y5,$S5),AS$1)-MAX($R5,EOMONTH(AS$1,-1)+1)+1) -> 0 | AT5: =ROUND(IF($Z5="",$T5,$Z5)*(AS5/IF($W5="",$Q5,$W5)),2) -> 0 | AU5: =+ROUND(AT5*0.1,2) -> 0 | AV5: =+SUM(AT5:AU5) -> 0 | AX5: =MAX(0,MIN(IF($Y5<>"",$Y5,$S5),AX$1)-MAX($R5,EOMONTH(AX$1,-1)+1)+1) -> 0 | AY5: =ROUND(IF($Z5="",$T5,$Z5)*(AX5/IF($W5="",$Q5,$W5)),2) -> 0 | AZ5: =+ROUND(AY5*0.1,2) -> 0 | BA5: =+SUM(AY5:AZ5) -> 0 | BC5: =MAX(0,MIN(IF($Y5<>"",$Y5,$S5),BC$1)-MAX($R5,EOMONTH(BC$1,-1)+1)+1) -> 0 | BD5: =ROUND(IF($Z5="",$T5,$Z5)*(BC5/IF($W5="",$Q5,$W5)),2) -> 0 | BE5: =+ROUND(BD5*0.1,2) -> 0 | BF5: =+SUM(BD5:BE5) -> 0 | BH5: =MAX(0,MIN(IF($Y5<>"",$Y5,$S5),BH$1)-MAX($R5,EOMONTH(BH$1,-1)+1)+1) -> 0 | BI5: =ROUND(IF($Z5="",$T5,$Z5)*(BH5/IF($W5="",$Q5,$W5)),2) -> 0 | BJ5: =+ROUND(BI5*0.1,2) -> 0 | BK5: =+SUM(BI5:BJ5) -> 0 | BM5: =MAX(0,MIN(IF($Y5<>"",$Y5,$S5),BM$1)-MAX($R5,EOMONTH(BM$1,-1)+1)+1) -> 0 | BN5: =ROUND(IF($Z5="",$T5,$Z5)*(BM5/IF($W5="",$Q5,$W5)),2) -> 0 | BO5: =+ROUND(BN5*0.1,2) -> 0 | BP5: =+SUM(BN5:BO5) -> 0 | BR5: =MAX(0,MIN(IF($Y5<>"",$Y5,$S5),BR$1)-MAX($R5,EOMONTH(BR$1,-1)+1)+1) -> 0 | BS5: =ROUND(IF($Z5="",$T5,$Z5)*(BR5/IF($W5="",$Q5,$W5)),2) -> 0 | BT5: =+ROUND(BS5*0.1,2) -> 0 | BU5: =+SUM(BS5:BT5) -> 0 | BW5: =MAX(0,MIN(IF($Y5<>"",$Y5,$S5),BW$1)-MAX($R5,EOMONTH(BW$1,-1)+1)+1) -> 0 | BX5: =ROUND(IF($Z5="",$T5,$Z5)*(BW5/IF($W5="",$Q5,$W5)),2) -> 0 | BY5: =+ROUND(BX5*0.1,2) -> 0 | BZ5: =+SUM(BX5:BY5) -> 0 | CA5: =+AD5+AI5+AN5+AS5+AX5+BC5+BH5+BM5+BR5+BW5 -> 0 | CB5: =+AE5+AJ5+AO5+AT5+AY5+BD5+BI5+BN5+BS5+BX5 -> 0 | CC5: =+AF5+AK5+AP5+AU5+AZ5+BE5+BJ5+BO5+BT5+BY5 -> 0 | CD5: =+SUM(CB5:CC5) -> 0 | CE5: =ROUND(IF($Y5<>"",$Z5,$T5)-CB5,2) -> 0 | CF5: =ROUND(IF($Y5<>"",$AA5,$U5)-CC5,2) -> 0 | CG5: GERENCIA DE TRANSPORTE PUBLICO Y CIRCULACION VIAL | CH5: Pamela Aida Flores Laqui | CI5: Gerente | CJ5: 951 902 578
A6: 5 | B6: 236 | C6: MOQUEGUA | D6: ILO | E6: ILO | F6: MO-612 | G6: EMP. PE-36 (ROTARY) - TERMINAL TERRESTRE - EMP. PE-1S D (KM 04+708) | H6: 4.708 | I6: PAVIMENTADO | J6: 880 | K6: 270 | L6: 37287 | M6: 3729 | N6: 41016 | O6: EXCLUIDO | Q6: =+$K6 -> 270 | S6: =IF(Q6+R6=0,"",Q6+R6-1) -> 269 | U6: =+ROUND(T6*0.1,2) -> 0 | V6: =+SUM(T6:U6) -> 0 | X6: =+$R6 -> 0 | Y6: =IF(W6>0,X6+W6-1,"") | AA6: =+ROUND(Z6*0.1,2) -> 0 | AB6: =+SUM(Z6:AA6) -> 0 | AD6: =MAX(0,MIN(IF($Y6<>"",$Y6,$S6),AD$1)-MAX($R6,EOMONTH(AD$1,-1)+1)+1) -> 0 | AE6: =ROUND(IF($Z6="",$T6,$Z6)*(AD6/IF($W6="",$Q6,$W6)),2) -> 0 | AF6: =+ROUND(AE6*0.1,2) -> 0 | AG6: =+SUM(AE6:AF6) -> 0 | AI6: =MAX(0,MIN(IF($Y6<>"",$Y6,$S6),AI$1)-MAX($R6,EOMONTH(AI$1,-1)+1)+1) -> 0 | AJ6: =ROUND(IF($Z6="",$T6,$Z6)*(AI6/IF($W6="",$Q6,$W6)),2) -> 0 | AK6: =+ROUND(AJ6*0.1,2) -> 0 | AL6: =+SUM(AJ6:AK6) -> 0 | AN6: =MAX(0,MIN(IF($Y6<>"",$Y6,$S6),AN$1)-MAX($R6,EOMONTH(AN$1,-1)+1)+1) -> 0 | AO6: =ROUND(IF($Z6="",$T6,$Z6)*(AN6/IF($W6="",$Q6,$W6)),2) -> 0 | AP6: =+ROUND(AO6*0.1,2) -> 0 | AQ6: =+SUM(AO6:AP6) -> 0 | AS6: =MAX(0,MIN(IF($Y6<>"",$Y6,$S6),AS$1)-MAX($R6,EOMONTH(AS$1,-1)+1)+1) -> 0 | AT6: =ROUND(IF($Z6="",$T6,$Z6)*(AS6/IF($W6="",$Q6,$W6)),2) -> 0 | AU6: =+ROUND(AT6*0.1,2) -> 0 | AV6: =+SUM(AT6:AU6) -> 0 | AX6: =MAX(0,MIN(IF($Y6<>"",$Y6,$S6),AX$1)-MAX($R6,EOMONTH(AX$1,-1)+1)+1) -> 0 | AY6: =ROUND(IF($Z6="",$T6,$Z6)*(AX6/IF($W6="",$Q6,$W6)),2) -> 0 | AZ6: =+ROUND(AY6*0.1,2) -> 0 | BA6: =+SUM(AY6:AZ6) -> 0 | BC6: =MAX(0,MIN(IF($Y6<>"",$Y6,$S6),BC$1)-MAX($R6,EOMONTH(BC$1,-1)+1)+1) -> 0 | BD6: =ROUND(IF($Z6="",$T6,$Z6)*(BC6/IF($W6="",$Q6,$W6)),2) -> 0 | BE6: =+ROUND(BD6*0.1,2) -> 0 | BF6: =+SUM(BD6:BE6) -> 0 | BH6: =MAX(0,MIN(IF($Y6<>"",$Y6,$S6),BH$1)-MAX($R6,EOMONTH(BH$1,-1)+1)+1) -> 0 | BI6: =ROUND(IF($Z6="",$T6,$Z6)*(BH6/IF($W6="",$Q6,$W6)),2) -> 0 | BJ6: =+ROUND(BI6*0.1,2) -> 0 | BK6: =+SUM(BI6:BJ6) -> 0 | BM6: =MAX(0,MIN(IF($Y6<>"",$Y6,$S6),BM$1)-MAX($R6,EOMONTH(BM$1,-1)+1)+1) -> 0 | BN6: =ROUND(IF($Z6="",$T6,$Z6)*(BM6/IF($W6="",$Q6,$W6)),2) -> 0 | BO6: =+ROUND(BN6*0.1,2) -> 0 | BP6: =+SUM(BN6:BO6) -> 0 | BR6: =MAX(0,MIN(IF($Y6<>"",$Y6,$S6),BR$1)-MAX($R6,EOMONTH(BR$1,-1)+1)+1) -> 0 | BS6: =ROUND(IF($Z6="",$T6,$Z6)*(BR6/IF($W6="",$Q6,$W6)),2) -> 0 | BT6: =+ROUND(BS6*0.1,2) -> 0 | BU6: =+SUM(BS6:BT6) -> 0 | BW6: =MAX(0,MIN(IF($Y6<>"",$Y6,$S6),BW$1)-MAX($R6,EOMONTH(BW$1,-1)+1)+1) -> 0 | BX6: =ROUND(IF($Z6="",$T6,$Z6)*(BW6/IF($W6="",$Q6,$W6)),2) -> 0 | BY6: =+ROUND(BX6*0.1,2) -> 0 | BZ6: =+SUM(BX6:BY6) -> 0 | CA6: =+AD6+AI6+AN6+AS6+AX6+BC6+BH6+BM6+BR6+BW6 -> 0 | CB6: =+AE6+AJ6+AO6+AT6+AY6+BD6+BI6+BN6+BS6+BX6 -> 0 | CC6: =+AF6+AK6+AP6+AU6+AZ6+BE6+BJ6+BO6+BT6+BY6 -> 0 | CD6: =+SUM(CB6:CC6) -> 0 | CE6: =ROUND(IF($Y6<>"",$Z6,$T6)-CB6,2) -> 0 | CF6: =ROUND(IF($Y6<>"",$AA6,$U6)-CC6,2) -> 0 | CG6: GERENCIA DE TRANSPORTE PUBLICO Y CIRCULACION VIAL | CH6: Pamela Aida Flores Laqui | CI6: Gerente | CJ6: 951 902 578
A7: 6 | B7: 49 | C7: MOQUEGUA | D7: MARISCAL NIETO | E7: CARUMAS | F7: MO-549 | G7: EMP. PE-36 B (TITIRI) - ARUNTAYA - CACHIMOCO - PASTO GRANDE WILLACOLLO - LORIPUNGO - EMP. PE-36 A (L. D. PUNO) (KM 51+600) | H7: 51.6 | I7: AFIRMADO | J7: 735 | K7: 247 | L7: 312257 | M7: 31226 | N7: 343483 | Q7: =+$K7 -> 247 | S7: =IF(Q7+R7=0,"",Q7+R7-1) -> 246 | U7: =+ROUND(T7*0.1,2) -> 0 | V7: =+SUM(T7:U7) -> 0 | X7: =+$R7 -> 0 | Y7: =IF(W7>0,X7+W7-1,"") | AA7: =+ROUND(Z7*0.1,2) -> 0 | AB7: =+SUM(Z7:AA7) -> 0 | AD7: =MAX(0,MIN(IF($Y7<>"",$Y7,$S7),AD$1)-MAX($R7,EOMONTH(AD$1,-1)+1)+1) -> 0 | AE7: =ROUND(IF($Z7="",$T7,$Z7)*(AD7/IF($W7="",$Q7,$W7)),2) -> 0 | AF7: =+ROUND(AE7*0.1,2) -> 0 | AG7: =+SUM(AE7:AF7) -> 0 | AI7: =MAX(0,MIN(IF($Y7<>"",$Y7,$S7),AI$1)-MAX($R7,EOMONTH(AI$1,-1)+1)+1) -> 0 | AJ7: =ROUND(IF($Z7="",$T7,$Z7)*(AI7/IF($W7="",$Q7,$W7)),2) -> 0 | AK7: =+ROUND(AJ7*0.1,2) -> 0 | AL7: =+SUM(AJ7:AK7) -> 0 | AN7: =MAX(0,MIN(IF($Y7<>"",$Y7,$S7),AN$1)-MAX($R7,EOMONTH(AN$1,-1)+1)+1) -> 0 | AO7: =ROUND(IF($Z7="",$T7,$Z7)*(AN7/IF($W7="",$Q7,$W7)),2) -> 0 | AP7: =+ROUND(AO7*0.1,2) -> 0 | AQ7: =+SUM(AO7:AP7) -> 0 | AS7: =MAX(0,MIN(IF($Y7<>"",$Y7,$S7),AS$1)-MAX($R7,EOMONTH(AS$1,-1)+1)+1) -> 0 | AT7: =ROUND(IF($Z7="",$T7,$Z7)*(AS7/IF($W7="",$Q7,$W7)),2) -> 0 | AU7: =+ROUND(AT7*0.1,2) -> 0 | AV7: =+SUM(AT7:AU7) -> 0 | AX7: =MAX(0,MIN(IF($Y7<>"",$Y7,$S7),AX$1)-MAX($R7,EOMONTH(AX$1,-1)+1)+1) -> 0 | AY7: =ROUND(IF($Z7="",$T7,$Z7)*(AX7/IF($W7="",$Q7,$W7)),2) -> 0 | AZ7: =+ROUND(AY7*0.1,2) -> 0 | BA7: =+SUM(AY7:AZ7) -> 0 | BC7: =MAX(0,MIN(IF($Y7<>"",$Y7,$S7),BC$1)-MAX($R7,EOMONTH(BC$1,-1)+1)+1) -> 0 | BD7: =ROUND(IF($Z7="",$T7,$Z7)*(BC7/IF($W7="",$Q7,$W7)),2) -> 0 | BE7: =+ROUND(BD7*0.1,2) -> 0 | BF7: =+SUM(BD7:BE7) -> 0 | BH7: =MAX(0,MIN(IF($Y7<>"",$Y7,$S7),BH$1)-MAX($R7,EOMONTH(BH$1,-1)+1)+1) -> 0 | BI7: =ROUND(IF($Z7="",$T7,$Z7)*(BH7/IF($W7="",$Q7,$W7)),2) -> 0 | BJ7: =+ROUND(BI7*0.1,2) -> 0 | BK7: =+SUM(BI7:BJ7) -> 0 | BM7: =MAX(0,MIN(IF($Y7<>"",$Y7,$S7),BM$1)-MAX($R7,EOMONTH(BM$1,-1)+1)+1) -> 0 | BN7: =ROUND(IF($Z7="",$T7,$Z7)*(BM7/IF($W7="",$Q7,$W7)),2) -> 0 | BO7: =+ROUND(BN7*0.1,2) -> 0 | BP7: =+SUM(BN7:BO7) -> 0 | BR7: =MAX(0,MIN(IF($Y7<>"",$Y7,$S7),BR$1)-MAX($R7,EOMONTH(BR$1,-1)+1)+1) -> 0 | BS7: =ROUND(IF($Z7="",$T7,$Z7)*(BR7/IF($W7="",$Q7,$W7)),2) -> 0 | BT7: =+ROUND(BS7*0.1,2) -> 0 | BU7: =+SUM(BS7:BT7) -> 0 | BW7: =MAX(0,MIN(IF($Y7<>"",$Y7,$S7),BW$1)-MAX($R7,EOMONTH(BW$1,-1)+1)+1) -> 0 | BX7: =ROUND(IF($Z7="",$T7,$Z7)*(BW7/IF($W7="",$Q7,$W7)),2) -> 0 | BY7: =+ROUND(BX7*0.1,2) -> 0 | BZ7: =+SUM(BX7:BY7) -> 0 | CA7: =+AD7+AI7+AN7+AS7+AX7+BC7+BH7+BM7+BR7+BW7 -> 0 | CB7: =+AE7+AJ7+AO7+AT7+AY7+BD7+BI7+BN7+BS7+BX7 -> 0 | CC7: =+AF7+AK7+AP7+AU7+AZ7+BE7+BJ7+BO7+BT7+BY7 -> 0 | CD7: =+SUM(CB7:CC7) -> 0 | CE7: =ROUND(IF($Y7<>"",$Z7,$T7)-CB7,2) -> 0 | CF7: =ROUND(IF($Y7<>"",$AA7,$U7)-CC7,2) -> 0 | CG7: IVP MARISCAL NIETO | CH7: Wilbert Alfredo Paredes Choquehuanca | CI7: Gerente | CJ7: 979 589 720
A8: 7 | B8: 49 | C8: MOQUEGUA | D8: MARISCAL NIETO | E8: SAN ANTONIO | F8: R1801290 | G8: EMP. PE-1S (CALALUNA) - SAN ANTONIO - COPOCROP - EMP. MO-603 (KM 05+485) | H8: 5.485 | I8: AFIRMADO | J8: 735 | K8: 271 | L8: 36418 | M8: 3642 | N8: 40060 | O8: OS-055-DT | P8: AVCOC EIRL | Q8: 240 | R8: 46144 | S8: =IF(Q8+R8=0,"",Q8+R8-1) -> 46383 | T8: 32251.8 | U8: =+ROUND(T8*0.1,2) -> 3225.18 | V8: =+SUM(T8:U8) -> 35476.98 | X8: =+$R8 -> 46144 | Y8: =IF(W8>0,X8+W8-1,"") | AA8: =+ROUND(Z8*0.1,2) -> 0 | AB8: =+SUM(Z8:AA8) -> 0 | AD8: =MAX(0,MIN(IF($Y8<>"",$Y8,$S8),AD$1)-MAX($R8,EOMONTH(AD$1,-1)+1)+1) -> 0 | AE8: =ROUND(IF($Z8="",$T8,$Z8)*(AD8/IF($W8="",$Q8,$W8)),2) -> 0 | AF8: =+ROUND(AE8*0.1,2) -> 0 | AG8: =+SUM(AE8:AF8) -> 0 | AI8: =MAX(0,MIN(IF($Y8<>"",$Y8,$S8),AI$1)-MAX($R8,EOMONTH(AI$1,-1)+1)+1) -> 0 | AJ8: =ROUND(IF($Z8="",$T8,$Z8)*(AI8/IF($W8="",$Q8,$W8)),2) -> 0 | AK8: =+ROUND(AJ8*0.1,2) -> 0 | AL8: =+SUM(AJ8:AK8) -> 0 | AN8: =MAX(0,MIN(IF($Y8<>"",$Y8,$S8),AN$1)-MAX($R8,EOMONTH(AN$1,-1)+1)+1) -> 30 | AO8: =ROUND(IF($Z8="",$T8,$Z8)*(AN8/IF($W8="",$Q8,$W8)),2) -> 4031.48 | AP8: =+ROUND(AO8*0.1,2) -> 403.15 | AQ8: =+SUM(AO8:AP8) -> 4434.63 | AS8: =MAX(0,MIN(IF($Y8<>"",$Y8,$S8),AS$1)-MAX($R8,EOMONTH(AS$1,-1)+1)+1) -> 30 | AT8: =ROUND(IF($Z8="",$T8,$Z8)*(AS8/IF($W8="",$Q8,$W8)),2) -> 4031.48 | AU8: =+ROUND(AT8*0.1,2) -> 403.15 | AV8: =+SUM(AT8:AU8) -> 4434.63 | AX8: =MAX(0,MIN(IF($Y8<>"",$Y8,$S8),AX$1)-MAX($R8,EOMONTH(AX$1,-1)+1)+1) -> 31 | AY8: =ROUND(IF($Z8="",$T8,$Z8)*(AX8/IF($W8="",$Q8,$W8)),2) -> 4165.86 | AZ8: =+ROUND(AY8*0.1,2) -> 416.59 | BA8: =+SUM(AY8:AZ8) -> 4582.45 | BC8: =MAX(0,MIN(IF($Y8<>"",$Y8,$S8),BC$1)-MAX($R8,EOMONTH(BC$1,-1)+1)+1) -> 31 | BD8: =ROUND(IF($Z8="",$T8,$Z8)*(BC8/IF($W8="",$Q8,$W8)),2) -> 4165.86 | BE8: =+ROUND(BD8*0.1,2) -> 416.59 | BF8: =+SUM(BD8:BE8) -> 4582.45 | BH8: =MAX(0,MIN(IF($Y8<>"",$Y8,$S8),BH$1)-MAX($R8,EOMONTH(BH$1,-1)+1)+1) -> 30 | BI8: =ROUND(IF($Z8="",$T8,$Z8)*(BH8/IF($W8="",$Q8,$W8)),2) -> 4031.48 | BJ8: =+ROUND(BI8*0.1,2) -> 403.15 | BK8: =+SUM(BI8:BJ8) -> 4434.63 | BM8: =MAX(0,MIN(IF($Y8<>"",$Y8,$S8),BM$1)-MAX($R8,EOMONTH(BM$1,-1)+1)+1) -> 31 | BN8: =ROUND(IF($Z8="",$T8,$Z8)*(BM8/IF($W8="",$Q8,$W8)),2) -> 4165.86 | BO8: =+ROUND(BN8*0.1,2) -> 416.59 | BP8: =+SUM(BN8:BO8) -> 4582.45 | BR8: =MAX(0,MIN(IF($Y8<>"",$Y8,$S8),BR$1)-MAX($R8,EOMONTH(BR$1,-1)+1)+1) -> 30 | BS8: =ROUND(IF($Z8="",$T8,$Z8)*(BR8/IF($W8="",$Q8,$W8)),2) -> 4031.48 | BT8: =+ROUND(BS8*0.1,2) -> 403.15 | BU8: =+SUM(BS8:BT8) -> 4434.63 | BW8: =MAX(0,MIN(IF($Y8<>"",$Y8,$S8),BW$1)-MAX($R8,EOMONTH(BW$1,-1)+1)+1) -> 27 | BX8: =ROUND(IF($Z8="",$T8,$Z8)*(BW8/IF($W8="",$Q8,$W8)),2) -> 3628.33 | BY8: =+ROUND(BX8*0.1,2) -> 362.83 | BZ8: =+SUM(BX8:BY8) -> 3991.16 | CA8: =+AD8+AI8+AN8+AS8+AX8+BC8+BH8+BM8+BR8+BW8 -> 240 | CB8: =+AE8+AJ8+AO8+AT8+AY8+BD8+BI8+BN8+BS8+BX8 -> 32251.83 | CC8: =+AF8+AK8+AP8+AU8+AZ8+BE8+BJ8+BO8+BT8+BY8 -> 3225.2 | CD8: =+SUM(CB8:CC8) -> 35477.03 | CE8: =ROUND(IF($Y8<>"",$Z8,$T8)-CB8,2) -> -0.03 | CF8: =ROUND(IF($Y8<>"",$AA8,$U8)-CC8,2) -> -0.02 | CG8: IVP MARISCAL NIETO | CH8: Wilbert Alfredo Paredes Choquehuanca | CI8: Gerente | CJ8: 979 589 720
A9: 8 | B9: 49 | C9: MOQUEGUA | D9: MARISCAL NIETO | E9: SAN ANTONIO | F9: R1801302 | G9: EMP. PE-1S (SAN JOSÉ) - PTE. SANTO DOMINGO - LA MERCED - SACATA - EMP. MO-606 (KM 05+100) | H9: 5.1 | I9: AFIRMADO | J9: 735 | K9: 271 | L9: 33861 | M9: 3386 | N9: 37247 | O9: OS-053-DT | P9: AVCOC EIRL | Q9: 240 | R9: 46144 | S9: =IF(Q9+R9=0,"",Q9+R9-1) -> 46383 | T9: 29988 | U9: =+ROUND(T9*0.1,2) -> 2998.8 | V9: =+SUM(T9:U9) -> 32986.8 | X9: =+$R9 -> 46144 | Y9: =IF(W9>0,X9+W9-1,"") | AA9: =+ROUND(Z9*0.1,2) -> 0 | AB9: =+SUM(Z9:AA9) -> 0 | AD9: =MAX(0,MIN(IF($Y9<>"",$Y9,$S9),AD$1)-MAX($R9,EOMONTH(AD$1,-1)+1)+1) -> 0 | AE9: =ROUND(IF($Z9="",$T9,$Z9)*(AD9/IF($W9="",$Q9,$W9)),2) -> 0 | AF9: =+ROUND(AE9*0.1,2) -> 0 | AG9: =+SUM(AE9:AF9) -> 0 | AI9: =MAX(0,MIN(IF($Y9<>"",$Y9,$S9),AI$1)-MAX($R9,EOMONTH(AI$1,-1)+1)+1) -> 0 | AJ9: =ROUND(IF($Z9="",$T9,$Z9)*(AI9/IF($W9="",$Q9,$W9)),2) -> 0 | AK9: =+ROUND(AJ9*0.1,2) -> 0 | AL9: =+SUM(AJ9:AK9) -> 0 | AN9: =MAX(0,MIN(IF($Y9<>"",$Y9,$S9),AN$1)-MAX($R9,EOMONTH(AN$1,-1)+1)+1) -> 30 | AO9: =ROUND(IF($Z9="",$T9,$Z9)*(AN9/IF($W9="",$Q9,$W9)),2) -> 3748.5 | AP9: =+ROUND(AO9*0.1,2) -> 374.85 | AQ9: =+SUM(AO9:AP9) -> 4123.35 | AS9: =MAX(0,MIN(IF($Y9<>"",$Y9,$S9),AS$1)-MAX($R9,EOMONTH(AS$1,-1)+1)+1) -> 30 | AT9: =ROUND(IF($Z9="",$T9,$Z9)*(AS9/IF($W9="",$Q9,$W9)),2) -> 3748.5 | AU9: =+ROUND(AT9*0.1,2) -> 374.85 | AV9: =+SUM(AT9:AU9) -> 4123.35 | AX9: =MAX(0,MIN(IF($Y9<>"",$Y9,$S9),AX$1)-MAX($R9,EOMONTH(AX$1,-1)+1)+1) -> 31 | AY9: =ROUND(IF($Z9="",$T9,$Z9)*(AX9/IF($W9="",$Q9,$W9)),2) -> 3873.45 | AZ9: =+ROUND(AY9*0.1,2) -> 387.35 | BA9: =+SUM(AY9:AZ9) -> 4260.8 | BC9: =MAX(0,MIN(IF($Y9<>"",$Y9,$S9),BC$1)-MAX($R9,EOMONTH(BC$1,-1)+1)+1) -> 31 | BD9: =ROUND(IF($Z9="",$T9,$Z9)*(BC9/IF($W9="",$Q9,$W9)),2) -> 3873.45 | BE9: =+ROUND(BD9*0.1,2) -> 387.35 | BF9: =+SUM(BD9:BE9) -> 4260.8 | BH9: =MAX(0,MIN(IF($Y9<>"",$Y9,$S9),BH$1)-MAX($R9,EOMONTH(BH$1,-1)+1)+1) -> 30 | BI9: =ROUND(IF($Z9="",$T9,$Z9)*(BH9/IF($W9="",$Q9,$W9)),2) -> 3748.5 | BJ9: =+ROUND(BI9*0.1,2) -> 374.85 | BK9: =+SUM(BI9:BJ9) -> 4123.35 | BM9: =MAX(0,MIN(IF($Y9<>"",$Y9,$S9),BM$1)-MAX($R9,EOMONTH(BM$1,-1)+1)+1) -> 31 | BN9: =ROUND(IF($Z9="",$T9,$Z9)*(BM9/IF($W9="",$Q9,$W9)),2) -> 3873.45 | BO9: =+ROUND(BN9*0.1,2) -> 387.35 | BP9: =+SUM(BN9:BO9) -> 4260.8 | BR9: =MAX(0,MIN(IF($Y9<>"",$Y9,$S9),BR$1)-MAX($R9,EOMONTH(BR$1,-1)+1)+1) -> 30 | BS9: =ROUND(IF($Z9="",$T9,$Z9)*(BR9/IF($W9="",$Q9,$W9)),2) -> 3748.5 | BT9: =+ROUND(BS9*0.1,2) -> 374.85 | BU9: =+SUM(BS9:BT9) -> 4123.35 | BW9: =MAX(0,MIN(IF($Y9<>"",$Y9,$S9),BW$1)-MAX($R9,EOMONTH(BW$1,-1)+1)+1) -> 27 | BX9: =ROUND(IF($Z9="",$T9,$Z9)*(BW9/IF($W9="",$Q9,$W9)),2) -> 3373.65 | BY9: =+ROUND(BX9*0.1,2) -> 337.37 | BZ9: =+SUM(BX9:BY9) -> 3711.02 | CA9: =+AD9+AI9+AN9+AS9+AX9+BC9+BH9+BM9+BR9+BW9 -> 240 | CB9: =+AE9+AJ9+AO9+AT9+AY9+BD9+BI9+BN9+BS9+BX9 -> 29988 | CC9: =+AF9+AK9+AP9+AU9+AZ9+BE9+BJ9+BO9+BT9+BY9 -> 2998.82 | CD9: =+SUM(CB9:CC9) -> 32986.82 | CE9: =ROUND(IF($Y9<>"",$Z9,$T9)-CB9,2) -> 0 | CF9: =ROUND(IF($Y9<>"",$AA9,$U9)-CC9,2) -> -0.02 | CG9: IVP MARISCAL NIETO | CH9: Wilbert Alfredo Paredes Choquehuanca | CI9: Gerente | CJ9: 979 589 720
A10: 9 | B10: 49 | C10: MOQUEGUA | D10: MARISCAL NIETO | E10: MOQUEGUA | F10: MO-598 | G10: EMP. MO-590 - EL RAYO - OCOLLITA - ESTUQUIÑA - LOS ÁNGELES - EMP. MO-579 (TOMBOLOMBO) (KM 07+000) | H10: 7 | I10: PAVIMENTADO | J10: 887.5 | K10: 248 | L10: 51357 | M10: 5136 | N10: 56493 | O10: OS-083-DT | P10: AVCOC EIRL | Q10: 180 | R10: 46205 | S10: =IF(Q10+R10=0,"",Q10+R10-1) -> 46384 | T10: 37275 | U10: =+ROUND(T10*0.1,2) -> 3727.5 | V10: =+SUM(T10:U10) -> 41002.5 | X10: =+$R10 -> 46205 | Y10: =IF(W10>0,X10+W10-1,"") | AA10: =+ROUND(Z10*0.1,2) -> 0 | AB10: =+SUM(Z10:AA10) -> 0 | AD10: =MAX(0,MIN(IF($Y10<>"",$Y10,$S10),AD$1)-MAX($R10,EOMONTH(AD$1,-1)+1)+1) -> 0 | AE10: =ROUND(IF($Z10="",$T10,$Z10)*(AD10/IF($W10="",$Q10,$W10)),2) -> 0 | AF10: =+ROUND(AE10*0.1,2) -> 0 | AG10: =+SUM(AE10:AF10) -> 0 | AI10: =MAX(0,MIN(IF($Y10<>"",$Y10,$S10),AI$1)-MAX($R10,EOMONTH(AI$1,-1)+1)+1) -> 0 | AJ10: =ROUND(IF($Z10="",$T10,$Z10)*(AI10/IF($W10="",$Q10,$W10)),2) -> 0 | AK10: =+ROUND(AJ10*0.1,2) -> 0 | AL10: =+SUM(AJ10:AK10) -> 0 | AN10: =MAX(0,MIN(IF($Y10<>"",$Y10,$S10),AN$1)-MAX($R10,EOMONTH(AN$1,-1)+1)+1) -> 0 | AO10: =ROUND(IF($Z10="",$T10,$Z10)*(AN10/IF($W10="",$Q10,$W10)),2) -> 0 | AP10: =+ROUND(AO10*0.1,2) -> 0 | AQ10: =+SUM(AO10:AP10) -> 0 | AS10: =MAX(0,MIN(IF($Y10<>"",$Y10,$S10),AS$1)-MAX($R10,EOMONTH(AS$1,-1)+1)+1) -> 0 | AT10: =ROUND(IF($Z10="",$T10,$Z10)*(AS10/IF($W10="",$Q10,$W10)),2) -> 0 | AU10: =+ROUND(AT10*0.1,2) -> 0 | AV10: =+SUM(AT10:AU10) -> 0 | AX10: =MAX(0,MIN(IF($Y10<>"",$Y10,$S10),AX$1)-MAX($R10,EOMONTH(AX$1,-1)+1)+1) -> 30 | AY10: =ROUND(IF($Z10="",$T10,$Z10)*(AX10/IF($W10="",$Q10,$W10)),2) -> 6212.5 | AZ10: =+ROUND(AY10*0.1,2) -> 621.25 | BA10: =+SUM(AY10:AZ10) -> 6833.75 | BC10: =MAX(0,MIN(IF($Y10<>"",$Y10,$S10),BC$1)-MAX($R10,EOMONTH(BC$1,-1)+1)+1) -> 31 | BD10: =ROUND(IF($Z10="",$T10,$Z10)*(BC10/IF($W10="",$Q10,$W10)),2) -> 6419.58 | BE10: =+ROUND(BD10*0.1,2) -> 641.96 | BF10: =+SUM(BD10:BE10) -> 7061.54 | BH10: =MAX(0,MIN(IF($Y10<>"",$Y10,$S10),BH$1)-MAX($R10,EOMONTH(BH$1,-1)+1)+1) -> 30 | BI10: =ROUND(IF($Z10="",$T10,$Z10)*(BH10/IF($W10="",$Q10,$W10)),2) -> 6212.5 | BJ10: =+ROUND(BI10*0.1,2) -> 621.25 | BK10: =+SUM(BI10:BJ10) -> 6833.75 | BM10: =MAX(0,MIN(IF($Y10<>"",$Y10,$S10),BM$1)-MAX($R10,EOMONTH(BM$1,-1)+1)+1) -> 31 | BN10: =ROUND(IF($Z10="",$T10,$Z10)*(BM10/IF($W10="",$Q10,$W10)),2) -> 6419.58 | BO10: =+ROUND(BN10*0.1,2) -> 641.96 | BP10: =+SUM(BN10:BO10) -> 7061.54 | BR10: =MAX(0,MIN(IF($Y10<>"",$Y10,$S10),BR$1)-MAX($R10,EOMONTH(BR$1,-1)+1)+1) -> 30 | BS10: =ROUND(IF($Z10="",$T10,$Z10)*(BR10/IF($W10="",$Q10,$W10)),2) -> 6212.5 | BT10: =+ROUND(BS10*0.1,2) -> 621.25 | BU10: =+SUM(BS10:BT10) -> 6833.75 | BW10: =MAX(0,MIN(IF($Y10<>"",$Y10,$S10),BW$1)-MAX($R10,EOMONTH(BW$1,-1)+1)+1) -> 28 | BX10: =ROUND(IF($Z10="",$T10,$Z10)*(BW10/IF($W10="",$Q10,$W10)),2) -> 5798.33 | BY10: =+ROUND(BX10*0.1,2) -> 579.83 | BZ10: =+SUM(BX10:BY10) -> 6378.16 | CA10: =+AD10+AI10+AN10+AS10+AX10+BC10+BH10+BM10+BR10+BW10 -> 180 | CB10: =+AE10+AJ10+AO10+AT10+AY10+BD10+BI10+BN10+BS10+BX10 -> 37274.99 | CC10: =+AF10+AK10+AP10+AU10+AZ10+BE10+BJ10+BO10+BT10+BY10 -> 3727.5 | CD10: =+SUM(CB10:CC10) -> 41002.49 | CE10: =ROUND(IF($Y10<>"",$Z10,$T10)-CB10,2) -> 0.01 | CF10: =ROUND(IF($Y10<>"",$AA10,$U10)-CC10,2) -> 0 | CG10: IVP MARISCAL NIETO | CH10: Wilbert Alfredo Paredes Choquehuanca | CI10: Gerente | CJ10: 979 589 720
A11: 10 | B11: 49 | C11: MOQUEGUA | D11: MARISCAL NIETO | E11: TORATA | F11: MO-583 | G11: EMP. PE-36 A - IE TORATA ALTA - TORATA ALTA (KM 03+524) | H11: 3.524 | I11: PAVIMENTADO | J11: 887.5 | K11: 270 | L11: 28148 | M11: 2815 | N11: 30963 | O11: OS-054-DT | P11: AVCOC EIRL | Q11: 240 | R11: 46144 | S11: =IF(Q11+R11=0,"",Q11+R11-1) -> 46383 | T11: 25020.4 | U11: =+ROUND(T11*0.1,2) -> 2502.04 | V11: =+SUM(T11:U11) -> 27522.44 | X11: =+$R11 -> 46144 | Y11: =IF(W11>0,X11+W11-1,"") | AA11: =+ROUND(Z11*0.1,2) -> 0 | AB11: =+SUM(Z11:AA11) -> 0 | AD11: =MAX(0,MIN(IF($Y11<>"",$Y11,$S11),AD$1)-MAX($R11,EOMONTH(AD$1,-1)+1)+1) -> 0 | AE11: =ROUND(IF($Z11="",$T11,$Z11)*(AD11/IF($W11="",$Q11,$W11)),2) -> 0 | AF11: =+ROUND(AE11*0.1,2) -> 0 | AG11: =+SUM(AE11:AF11) -> 0 | AI11: =MAX(0,MIN(IF($Y11<>"",$Y11,$S11),AI$1)-MAX($R11,EOMONTH(AI$1,-1)+1)+1) -> 0 | AJ11: =ROUND(IF($Z11="",$T11,$Z11)*(AI11/IF($W11="",$Q11,$W11)),2) -> 0 | AK11: =+ROUND(AJ11*0.1,2) -> 0 | AL11: =+SUM(AJ11:AK11) -> 0 | AN11: =MAX(0,MIN(IF($Y11<>"",$Y11,$S11),AN$1)-MAX($R11,EOMONTH(AN$1,-1)+1)+1) -> 30 | AO11: 2223.55 | AP11: =+ROUND(AO11*0.1,2) -> 222.36 | AQ11: =+SUM(AO11:AP11) -> 2445.91 | AS11: =MAX(0,MIN(IF($Y11<>"",$Y11,$S11),AS$1)-MAX($R11,EOMONTH(AS$1,-1)+1)+1) -> 30 | AT11: 2728.27 | AU11: =+ROUND(AT11*0.1,2) -> 272.83 | AV11: =+SUM(AT11:AU11) -> 3001.1 | AX11: =MAX(0,MIN(IF($Y11<>"",$Y11,$S11),AX$1)-MAX($R11,EOMONTH(AX$1,-1)+1)+1) -> 31 | AY11: =ROUND(IF($Z11="",$T11,$Z11)*(AX11/IF($W11="",$Q11,$W11)),2) -> 3231.8 | AZ11: =+ROUND(AY11*0.1,2) -> 323.18 | BA11: =+SUM(AY11:AZ11) -> 3554.98 | BC11: =MAX(0,MIN(IF($Y11<>"",$Y11,$S11),BC$1)-MAX($R11,EOMONTH(BC$1,-1)+1)+1) -> 31 | BD11: =ROUND(IF($Z11="",$T11,$Z11)*(BC11/IF($W11="",$Q11,$W11)),2) -> 3231.8 | BE11: =+ROUND(BD11*0.1,2) -> 323.18 | BF11: =+SUM(BD11:BE11) -> 3554.98 | BH11: =MAX(0,MIN(IF($Y11<>"",$Y11,$S11),BH$1)-MAX($R11,EOMONTH(BH$1,-1)+1)+1) -> 30 | BI11: =ROUND(IF($Z11="",$T11,$Z11)*(BH11/IF($W11="",$Q11,$W11)),2) -> 3127.55 | BJ11: =+ROUND(BI11*0.1,2) -> 312.76 | BK11: =+SUM(BI11:BJ11) -> 3440.31 | BM11: =MAX(0,MIN(IF($Y11<>"",$Y11,$S11),BM$1)-MAX($R11,EOMONTH(BM$1,-1)+1)+1) -> 31 | BN11: =ROUND(IF($Z11="",$T11,$Z11)*(BM11/IF($W11="",$Q11,$W11)),2) -> 3231.8 | BO11: =+ROUND(BN11*0.1,2) -> 323.18 | BP11: =+SUM(BN11:BO11) -> 3554.98 | BR11: =MAX(0,MIN(IF($Y11<>"",$Y11,$S11),BR$1)-MAX($R11,EOMONTH(BR$1,-1)+1)+1) -> 30 | BS11: =ROUND(IF($Z11="",$T11,$Z11)*(BR11/IF($W11="",$Q11,$W11)),2) -> 3127.55 | BT11: =+ROUND(BS11*0.1,2) -> 312.76 | BU11: =+SUM(BS11:BT11) -> 3440.31 | BW11: =MAX(0,MIN(IF($Y11<>"",$Y11,$S11),BW$1)-MAX($R11,EOMONTH(BW$1,-1)+1)+1) -> 27 | BX11: =ROUND(IF($Z11="",$T11,$Z11)*(BW11/IF($W11="",$Q11,$W11)),2) -> 2814.8 | BY11: =+ROUND(BX11*0.1,2) -> 281.48 | BZ11: =+SUM(BX11:BY11) -> 3096.28 | CA11: =+AD11+AI11+AN11+AS11+AX11+BC11+BH11+BM11+BR11+BW11 -> 240 | CB11: =+AE11+AJ11+AO11+AT11+AY11+BD11+BI11+BN11+BS11+BX11 -> 23717.12 | CC11: =+AF11+AK11+AP11+AU11+AZ11+BE11+BJ11+BO11+BT11+BY11 -> 2371.73 | CD11: =+SUM(CB11:CC11) -> 26088.85 | CE11: =ROUND(IF($Y11<>"",$Z11,$T11)-CB11,2) -> 1303.28 | CF11: =ROUND(IF($Y11<>"",$AA11,$U11)-CC11,2) -> 130.31 | CG11: IVP MARISCAL NIETO | CH11: Wilbert Alfredo Paredes Choquehuanca | CI11: Gerente | CJ11: 979 589 720
A12: 11 | B12: 48 | C12: MOQUEGUA | D12: GENERAL SANCHEZ CERRO | E12: OMATE | F12: MO-521 | G12: OMATE(KM 01+525) - CHICHILIN ALTO - CHALLAHUAYO - CARABAYA - COHUACHO (KM 14+931) | H12: 13.406 | I12: AFIRMADO | J12: 735 | K12: 240 | L12: 78827 | M12: 7882 | N12: 86709 | O12: C_391-2026 | P12: CONSORCIO VIAL OMATE | Q12: =+$K12 -> 240 | R12: 46190 | S12: =IF(Q12+R12=0,"",Q12+R12-1) -> 46429 | T12: 74872.83 | U12: =+ROUND(T12*0.1,2) -> 7487.28 | V12: =+SUM(T12:U12) -> 82360.11 | W12: 198 | X12: =+$R12 -> 46190 | Y12: =IF(W12>0,X12+W12-1,"") -> 46387 | Z12: 61770.06 | AA12: =+ROUND(Z12*0.1,2) -> 6177.01 | AB12: =+SUM(Z12:AA12) -> 67947.07 | AD12: =MAX(0,MIN(IF($Y12<>"",$Y12,$S12),AD$1)-MAX($R12,EOMONTH(AD$1,-1)+1)+1) -> 0 | AE12: =ROUND(IF($Z12="",$T12,$Z12)*(AD12/IF($W12="",$Q12,$W12)),2) -> 0 | AF12: =+ROUND(AE12*0.1,2) -> 0 | AG12: =+SUM(AE12:AF12) -> 0 | AI12: =MAX(0,MIN(IF($Y12<>"",$Y12,$S12),AI$1)-MAX($R12,EOMONTH(AI$1,-1)+1)+1) -> 0 | AJ12: =ROUND(IF($Z12="",$T12,$Z12)*(AI12/IF($W12="",$Q12,$W12)),2) -> 0 | AK12: =+ROUND(AJ12*0.1,2) -> 0 | AL12: =+SUM(AJ12:AK12) -> 0 | AN12: =MAX(0,MIN(IF($Y12<>"",$Y12,$S12),AN$1)-MAX($R12,EOMONTH(AN$1,-1)+1)+1) -> 0 | AO12: =ROUND(IF($Z12="",$T12,$Z12)*(AN12/IF($W12="",$Q12,$W12)),2) -> 0 | AP12: =+ROUND(AO12*0.1,2) -> 0 | AQ12: =+SUM(AO12:AP12) -> 0 | AS12: =MAX(0,MIN(IF($Y12<>"",$Y12,$S12),AS$1)-MAX($R12,EOMONTH(AS$1,-1)+1)+1) -> 14 | AT12: =ROUND(IF($Z12="",$T12,$Z12)*(AS12/IF($W12="",$Q12,$W12)),2) -> 4367.58 | AU12: =+ROUND(AT12*0.1,2) -> 436.76 | AV12: =+SUM(AT12:AU12) -> 4804.34 | AX12: =MAX(0,MIN(IF($Y12<>"",$Y12,$S12),AX$1)-MAX($R12,EOMONTH(AX$1,-1)+1)+1) -> 31 | AY12: =ROUND(IF($Z12="",$T12,$Z12)*(AX12/IF($W12="",$Q12,$W12)),2) -> 9671.07 | AZ12: =+ROUND(AY12*0.1,2) -> 967.11 | BA12: =+SUM(AY12:AZ12) -> 10638.18 | BC12: =MAX(0,MIN(IF($Y12<>"",$Y12,$S12),BC$1)-MAX($R12,EOMONTH(BC$1,-1)+1)+1) -> 31 | BD12: =ROUND(IF($Z12="",$T12,$Z12)*(BC12/IF($W12="",$Q12,$W12)),2) -> 9671.07 | BE12: =+ROUND(BD12*0.1,2) -> 967.11 | BF12: =+SUM(BD12:BE12) -> 10638.18 | BH12: =MAX(0,MIN(IF($Y12<>"",$Y12,$S12),BH$1)-MAX($R12,EOMONTH(BH$1,-1)+1)+1) -> 30 | BI12: =ROUND(IF($Z12="",$T12,$Z12)*(BH12/IF($W12="",$Q12,$W12)),2) -> 9359.1 | BJ12: =+ROUND(BI12*0.1,2) -> 935.91 | BK12: =+SUM(BI12:BJ12) -> 10295.01 | BM12: =MAX(0,MIN(IF($Y12<>"",$Y12,$S12),BM$1)-MAX($R12,EOMONTH(BM$1,-1)+1)+1) -> 31 | BN12: =ROUND(IF($Z12="",$T12,$Z12)*(BM12/IF($W12="",$Q12,$W12)),2) -> 9671.07 | BO12: =+ROUND(BN12*0.1,2) -> 967.11 | BP12: =+SUM(BN12:BO12) -> 10638.18 | BR12: =MAX(0,MIN(IF($Y12<>"",$Y12,$S12),BR$1)-MAX($R12,EOMONTH(BR$1,-1)+1)+1) -> 30 | BS12: =ROUND(IF($Z12="",$T12,$Z12)*(BR12/IF($W12="",$Q12,$W12)),2) -> 9359.1 | BT12: =+ROUND(BS12*0.1,2) -> 935.91 | BU12: =+SUM(BS12:BT12) -> 10295.01 | BW12: =MAX(0,MIN(IF($Y12<>"",$Y12,$S12),BW$1)-MAX($R12,EOMONTH(BW$1,-1)+1)+1) -> 31 | BX12: =ROUND(IF($Z12="",$T12,$Z12)*(BW12/IF($W12="",$Q12,$W12)),2) -> 9671.07 | BY12: =+ROUND(BX12*0.1,2) -> 967.11 | BZ12: =+SUM(BX12:BY12) -> 10638.18 | CA12: =+AD12+AI12+AN12+AS12+AX12+BC12+BH12+BM12+BR12+BW12 -> 198 | CB12: =+AE12+AJ12+AO12+AT12+AY12+BD12+BI12+BN12+BS12+BX12 -> 61770.06 | CC12: =+AF12+AK12+AP12+AU12+AZ12+BE12+BJ12+BO12+BT12+BY12 -> 6177.02 | CD12: =+SUM(CB12:CC12) -> 67947.08 | CE12: =ROUND(IF($Y12<>"",$Z12,$T12)-CB12,2) -> 0 | CF12: =ROUND(IF($Y12<>"",$AA12,$U12)-CC12,2) -> -0.01 | CG12: IVP GENERAL SANCHEZ CERRO | CH12: Miler Barrientos Ramos | CI12: Gerente | CJ12: 959 090 019 | CK12: Miler Barrientos Ramos | CL12: Memorando N° 0195-2026/MPGSC/GM/AFPT | CM12: 46112 | CN12: 959 090 019
A13: 12 | B13: 48 | C13: MOQUEGUA | D13: GENERAL SANCHEZ CERRO | E13: OMATE | F13: MO-524 | G13: PUENTE OMATE (KM 1+041) - ANEXO LAJE (KM 1+587), LAJE ( KM 1+952) - CAPILLA VIRGEN COPACABANA (2+386), ANEXO SABAYA ( KM 02+ 534) - SAN MIGUEL (3+476), SAN FRANCISCO (KM 5+689) - I.E. N°43057 - URINAY (7+336) | H13: 13.406 | I13: AFIRMADO | J13: 735 | K13: 261 | L13: 29402 | M13: 2940 | N13: 32342 | O13: OS-519 | P13: ASOCIACIÓN DE MANTENIMIENTO DE VÍAS VECINALES RURALES Y URBANOS SAN BERNARDO | Q13: =+$K13 -> 261 | R13: 46104 | S13: =IF(Q13+R13=0,"",Q13+R13-1) -> 46364 | T13: 28250 | U13: =+ROUND(T13*0.1,2) -> 2825 | V13: =+SUM(T13:U13) -> 31075 | X13: =+$R13 -> 46104 | Y13: =IF(W13>0,X13+W13-1,"") | AA13: =+ROUND(Z13*0.1,2) -> 0 | AB13: =+SUM(Z13:AA13) -> 0 | AD13: =MAX(0,MIN(IF($Y13<>"",$Y13,$S13),AD$1)-MAX($R13,EOMONTH(AD$1,-1)+1)+1) -> 9 | AE13: =ROUND(IF($Z13="",$T13,$Z13)*(AD13/IF($W13="",$Q13,$W13)),2) -> 974.14 | AF13: =+ROUND(AE13*0.1,2) -> 97.41 | AG13: =+SUM(AE13:AF13) -> 1071.55 | AI13: =MAX(0,MIN(IF($Y13<>"",$Y13,$S13),AI$1)-MAX($R13,EOMONTH(AI$1,-1)+1)+1) -> 30 | AJ13: =ROUND(IF($Z13="",$T13,$Z13)*(AI13/IF($W13="",$Q13,$W13)),2) -> 3247.13 | AK13: =+ROUND(AJ13*0.1,2) -> 324.71 | AL13: =+SUM(AJ13:AK13) -> 3571.84 | AN13: =MAX(0,MIN(IF($Y13<>"",$Y13,$S13),AN$1)-MAX($R13,EOMONTH(AN$1,-1)+1)+1) -> 31 | AO13: =ROUND(IF($Z13="",$T13,$Z13)*(AN13/IF($W13="",$Q13,$W13)),2) -> 3355.36 | AP13: =+ROUND(AO13*0.1,2) -> 335.54 | AQ13: =+SUM(AO13:AP13) -> 3690.9 | AS13: =MAX(0,MIN(IF($Y13<>"",$Y13,$S13),AS$1)-MAX($R13,EOMONTH(AS$1,-1)+1)+1) -> 30 | AT13: =ROUND(IF($Z13="",$T13,$Z13)*(AS13/IF($W13="",$Q13,$W13)),2) -> 3247.13 | AU13: =+ROUND(AT13*0.1,2) -> 324.71 | AV13: =+SUM(AT13:AU13) -> 3571.84 | AX13: =MAX(0,MIN(IF($Y13<>"",$Y13,$S13),AX$1)-MAX($R13,EOMONTH(AX$1,-1)+1)+1) -> 31 | AY13: =ROUND(IF($Z13="",$T13,$Z13)*(AX13/IF($W13="",$Q13,$W13)),2) -> 3355.36 | AZ13: =+ROUND(AY13*0.1,2) -> 335.54 | BA13: =+SUM(AY13:AZ13) -> 3690.9 | BC13: =MAX(0,MIN(IF($Y13<>"",$Y13,$S13),BC$1)-MAX($R13,EOMONTH(BC$1,-1)+1)+1) -> 31 | BD13: =ROUND(IF($Z13="",$T13,$Z13)*(BC13/IF($W13="",$Q13,$W13)),2) -> 3355.36 | BE13: =+ROUND(BD13*0.1,2) -> 335.54 | BF13: =+SUM(BD13:BE13) -> 3690.9 | BH13: =MAX(0,MIN(IF($Y13<>"",$Y13,$S13),BH$1)-MAX($R13,EOMONTH(BH$1,-1)+1)+1) -> 30 | BI13: =ROUND(IF($Z13="",$T13,$Z13)*(BH13/IF($W13="",$Q13,$W13)),2) -> 3247.13 | BJ13: =+ROUND(BI13*0.1,2) -> 324.71 | BK13: =+SUM(BI13:BJ13) -> 3571.84 | BM13: =MAX(0,MIN(IF($Y13<>"",$Y13,$S13),BM$1)-MAX($R13,EOMONTH(BM$1,-1)+1)+1) -> 31 | BN13: =ROUND(IF($Z13="",$T13,$Z13)*(BM13/IF($W13="",$Q13,$W13)),2) -> 3355.36 | BO13: =+ROUND(BN13*0.1,2) -> 335.54 | BP13: =+SUM(BN13:BO13) -> 3690.9 | BR13: =MAX(0,MIN(IF($Y13<>"",$Y13,$S13),BR$1)-MAX($R13,EOMONTH(BR$1,-1)+1)+1) -> 30 | BS13: =ROUND(IF($Z13="",$T13,$Z13)*(BR13/IF($W13="",$Q13,$W13)),2) -> 3247.13 | BT13: =+ROUND(BS13*0.1,2) -> 324.71 | BU13: =+SUM(BS13:BT13) -> 3571.84 | BW13: =MAX(0,MIN(IF($Y13<>"",$Y13,$S13),BW$1)-MAX($R13,EOMONTH(BW$1,-1)+1)+1) -> 8 | BX13: =ROUND(IF($Z13="",$T13,$Z13)*(BW13/IF($W13="",$Q13,$W13)),2) -> 865.9 | BY13: =+ROUND(BX13*0.1,2) -> 86.59 | BZ13: =+SUM(BX13:BY13) -> 952.49 | CA13: =+AD13+AI13+AN13+AS13+AX13+BC13+BH13+BM13+BR13+BW13 -> 261 | CB13: =+AE13+AJ13+AO13+AT13+AY13+BD13+BI13+BN13+BS13+BX13 -> 28250 | CC13: =+AF13+AK13+AP13+AU13+AZ13+BE13+BJ13+BO13+BT13+BY13 -> 2825 | CD13: =+SUM(CB13:CC13) -> 31075 | CE13: =ROUND(IF($Y13<>"",$Z13,$T13)-CB13,2) -> 0 | CF13: =ROUND(IF($Y13<>"",$AA13,$U13)-CC13,2) -> 0 | CG13: IVP GENERAL SANCHEZ CERRO | CH13: Miler Barrientos Ramos | CI13: Gerente | CJ13: 959 090 019 | CK13: Miler Barrientos Ramos | CL13: Memorando N° 0195-2026/MPGSC/GM/AFPT | CM13: 46112 | CN13: 959 090 019
A14: 13 | B14: 48 | C14: MOQUEGUA | D14: GENERAL SANCHEZ CERRO | E14: OMATE | F14: R180221 | G14: EMP. MO-522 - ACHICARI - HUASALON - QUINISTACAS - EMP. MO-521 (CHALLAHUAYO) | H14: 4.078 | I14: AFIRMADO | J14: 735 | K14: 261 | L14: 26077 | M14: 2608 | N14: 28685 | O14: OS-180 | P14: ASOCIACIÓN CIVIL SAGRADO CORAZÓN DE JESÚS-OMATE - ASSACOJE | Q14: =+$K14 -> 261 | R14: 46105 | S14: =IF(Q14+R14=0,"",Q14+R14-1) -> 46365 | T14: 25000 | U14: =+ROUND(T14*0.1,2) -> 2500 | V14: =+SUM(T14:U14) -> 27500 | X14: =+$R14 -> 46105 | Y14: =IF(W14>0,X14+W14-1,"") | AA14: =+ROUND(Z14*0.1,2) -> 0 | AB14: =+SUM(Z14:AA14) -> 0 | AD14: =MAX(0,MIN(IF($Y14<>"",$Y14,$S14),AD$1)-MAX($R14,EOMONTH(AD$1,-1)+1)+1) -> 8 | AE14: =ROUND(IF($Z14="",$T14,$Z14)*(AD14/IF($W14="",$Q14,$W14)),2) -> 766.28 | AF14: =+ROUND(AE14*0.1,2) -> 76.63 | AG14: =+SUM(AE14:AF14) -> 842.91 | AI14: =MAX(0,MIN(IF($Y14<>"",$Y14,$S14),AI$1)-MAX($R14,EOMONTH(AI$1,-1)+1)+1) -> 30 | AJ14: =ROUND(IF($Z14="",$T14,$Z14)*(AI14/IF($W14="",$Q14,$W14)),2) -> 2873.56 | AK14: =+ROUND(AJ14*0.1,2) -> 287.36 | AL14: =+SUM(AJ14:AK14) -> 3160.92 | AN14: =MAX(0,MIN(IF($Y14<>"",$Y14,$S14),AN$1)-MAX($R14,EOMONTH(AN$1,-1)+1)+1) -> 31 | AO14: =ROUND(IF($Z14="",$T14,$Z14)*(AN14/IF($W14="",$Q14,$W14)),2) -> 2969.35 | AP14: =+ROUND(AO14*0.1,2) -> 296.94 | AQ14: =+SUM(AO14:AP14) -> 3266.29 | AS14: =MAX(0,MIN(IF($Y14<>"",$Y14,$S14),AS$1)-MAX($R14,EOMONTH(AS$1,-1)+1)+1) -> 30 | AT14: =ROUND(IF($Z14="",$T14,$Z14)*(AS14/IF($W14="",$Q14,$W14)),2) -> 2873.56 | AU14: =+ROUND(AT14*0.1,2) -> 287.36 | AV14: =+SUM(AT14:AU14) -> 3160.92 | AX14: =MAX(0,MIN(IF($Y14<>"",$Y14,$S14),AX$1)-MAX($R14,EOMONTH(AX$1,-1)+1)+1) -> 31 | AY14: =ROUND(IF($Z14="",$T14,$Z14)*(AX14/IF($W14="",$Q14,$W14)),2) -> 2969.35 | AZ14: =+ROUND(AY14*0.1,2) -> 296.94 | BA14: =+SUM(AY14:AZ14) -> 3266.29 | BC14: =MAX(0,MIN(IF($Y14<>"",$Y14,$S14),BC$1)-MAX($R14,EOMONTH(BC$1,-1)+1)+1) -> 31 | BD14: =ROUND(IF($Z14="",$T14,$Z14)*(BC14/IF($W14="",$Q14,$W14)),2) -> 2969.35 | BE14: =+ROUND(BD14*0.1,2) -> 296.94 | BF14: =+SUM(BD14:BE14) -> 3266.29 | BH14: =MAX(0,MIN(IF($Y14<>"",$Y14,$S14),BH$1)-MAX($R14,EOMONTH(BH$1,-1)+1)+1) -> 30 | BI14: =ROUND(IF($Z14="",$T14,$Z14)*(BH14/IF($W14="",$Q14,$W14)),2) -> 2873.56 | BJ14: =+ROUND(BI14*0.1,2) -> 287.36 | BK14: =+SUM(BI14:BJ14) -> 3160.92 | BM14: =MAX(0,MIN(IF($Y14<>"",$Y14,$S14),BM$1)-MAX($R14,EOMONTH(BM$1,-1)+1)+1) -> 31 | BN14: =ROUND(IF($Z14="",$T14,$Z14)*(BM14/IF($W14="",$Q14,$W14)),2) -> 2969.35 | BO14: =+ROUND(BN14*0.1,2) -> 296.94 | BP14: =+SUM(BN14:BO14) -> 3266.29 | BR14: =MAX(0,MIN(IF($Y14<>"",$Y14,$S14),BR$1)-MAX($R14,EOMONTH(BR$1,-1)+1)+1) -> 30 | BS14: =ROUND(IF($Z14="",$T14,$Z14)*(BR14/IF($W14="",$Q14,$W14)),2) -> 2873.56 | BT14: =+ROUND(BS14*0.1,2) -> 287.36 | BU14: =+SUM(BS14:BT14) -> 3160.92 | BW14: =MAX(0,MIN(IF($Y14<>"",$Y14,$S14),BW$1)-MAX($R14,EOMONTH(BW$1,-1)+1)+1) -> 9 | BX14: =ROUND(IF($Z14="",$T14,$Z14)*(BW14/IF($W14="",$Q14,$W14)),2) -> 862.07 | BY14: =+ROUND(BX14*0.1,2) -> 86.21 | BZ14: =+SUM(BX14:BY14) -> 948.28 | CA14: =+AD14+AI14+AN14+AS14+AX14+BC14+BH14+BM14+BR14+BW14 -> 261 | CB14: =+AE14+AJ14+AO14+AT14+AY14+BD14+BI14+BN14+BS14+BX14 -> 24999.99 | CC14: =+AF14+AK14+AP14+AU14+AZ14+BE14+BJ14+BO14+BT14+BY14 -> 2500.04 | CD14: =+SUM(CB14:CC14) -> 27500.03 | CE14: =ROUND(IF($Y14<>"",$Z14,$T14)-CB14,2) -> 0.01 | CF14: =ROUND(IF($Y14<>"",$AA14,$U14)-CC14,2) -> -0.04 | CG14: IVP GENERAL SANCHEZ CERRO | CH14: Miler Barrientos Ramos | CI14: Gerente | CJ14: 959 090 019 | CK14: Miler Barrientos Ramos | CL14: Memorando N° 0195-2026/MPGSC/GM/AFPT | CM14: 46112 | CN14: 959 090 019
A15: 14 | B15: 48 | C15: MOQUEGUA | D15: GENERAL SANCHEZ CERRO | E15: PUQUINA | F15: MO-511 | G15: PUQUINA (KM 01+245) - POCOHUAYO (KM 7+151), POCOHUAYO (KM 07+438) - TILIA - EMP. MO-512 (KM 10+748) | H15: 9.216 | I15: AFIRMADO | J15: 735 | K15: 240 | L15: 54190 | M15: 5419 | N15: 59609 | O15: C_389-2026 | P15: CONSORCIO VIAL OMATE | Q15: =+$K15 -> 240 | R15: 46190 | S15: =IF(Q15+R15=0,"",Q15+R15-1) -> 46429 | T15: 51442.5 | U15: =+ROUND(T15*0.1,2) -> 5144.25 | V15: =+SUM(T15:U15) -> 56586.75 | W15: 198 | X15: =+$R15 -> 46190 | Y15: =IF(W15>0,X15+W15-1,"") -> 46387 | Z15: 42440.07 | AA15: =+ROUND(Z15*0.1,2) -> 4244.01 | AB15: =+SUM(Z15:AA15) -> 46684.08 | AD15: =MAX(0,MIN(IF($Y15<>"",$Y15,$S15),AD$1)-MAX($R15,EOMONTH(AD$1,-1)+1)+1) -> 0 | AE15: =ROUND(IF($Z15="",$T15,$Z15)*(AD15/IF($W15="",$Q15,$W15)),2) -> 0 | AF15: =+ROUND(AE15*0.1,2) -> 0 | AG15: =+SUM(AE15:AF15) -> 0 | AI15: =MAX(0,MIN(IF($Y15<>"",$Y15,$S15),AI$1)-MAX($R15,EOMONTH(AI$1,-1)+1)+1) -> 0 | AJ15: =ROUND(IF($Z15="",$T15,$Z15)*(AI15/IF($W15="",$Q15,$W15)),2) -> 0 | AK15: =+ROUND(AJ15*0.1,2) -> 0 | AL15: =+SUM(AJ15:AK15) -> 0 | AN15: =MAX(0,MIN(IF($Y15<>"",$Y15,$S15),AN$1)-MAX($R15,EOMONTH(AN$1,-1)+1)+1) -> 0 | AO15: =ROUND(IF($Z15="",$T15,$Z15)*(AN15/IF($W15="",$Q15,$W15)),2) -> 0 | AP15: =+ROUND(AO15*0.1,2) -> 0 | AQ15: =+SUM(AO15:AP15) -> 0 | AS15: =MAX(0,MIN(IF($Y15<>"",$Y15,$S15),AS$1)-MAX($R15,EOMONTH(AS$1,-1)+1)+1) -> 14 | AT15: =ROUND(IF($Z15="",$T15,$Z15)*(AS15/IF($W15="",$Q15,$W15)),2) -> 3000.81 | AU15: =+ROUND(AT15*0.1,2) -> 300.08 | AV15: =+SUM(AT15:AU15) -> 3300.89 | AX15: =MAX(0,MIN(IF($Y15<>"",$Y15,$S15),AX$1)-MAX($R15,EOMONTH(AX$1,-1)+1)+1) -> 31 | AY15: =ROUND(IF($Z15="",$T15,$Z15)*(AX15/IF($W15="",$Q15,$W15)),2) -> 6644.66 | AZ15: =+ROUND(AY15*0.1,2) -> 664.47 | BA15: =+SUM(AY15:AZ15) -> 7309.13 | BC15: =MAX(0,MIN(IF($Y15<>"",$Y15,$S15),BC$1)-MAX($R15,EOMONTH(BC$1,-1)+1)+1) -> 31 | BD15: =ROUND(IF($Z15="",$T15,$Z15)*(BC15/IF($W15="",$Q15,$W15)),2) -> 6644.66 | BE15: =+ROUND(BD15*0.1,2) -> 664.47 | BF15: =+SUM(BD15:BE15) -> 7309.13 | BH15: =MAX(0,MIN(IF($Y15<>"",$Y15,$S15),BH$1)-MAX($R15,EOMONTH(BH$1,-1)+1)+1) -> 30 | BI15: =ROUND(IF($Z15="",$T15,$Z15)*(BH15/IF($W15="",$Q15,$W15)),2) -> 6430.31 | BJ15: =+ROUND(BI15*0.1,2) -> 643.03 | BK15: =+SUM(BI15:BJ15) -> 7073.34 | BM15: =MAX(0,MIN(IF($Y15<>"",$Y15,$S15),BM$1)-MAX($R15,EOMONTH(BM$1,-1)+1)+1) -> 31 | BN15: =ROUND(IF($Z15="",$T15,$Z15)*(BM15/IF($W15="",$Q15,$W15)),2) -> 6644.66 | BO15: =+ROUND(BN15*0.1,2) -> 664.47 | BP15: =+SUM(BN15:BO15) -> 7309.13 | BR15: =MAX(0,MIN(IF($Y15<>"",$Y15,$S15),BR$1)-MAX($R15,EOMONTH(BR$1,-1)+1)+1) -> 30 | BS15: =ROUND(IF($Z15="",$T15,$Z15)*(BR15/IF($W15="",$Q15,$W15)),2) -> 6430.31 | BT15: =+ROUND(BS15*0.1,2) -> 643.03 | BU15: =+SUM(BS15:BT15) -> 7073.34 | BW15: =MAX(0,MIN(IF($Y15<>"",$Y15,$S15),BW$1)-MAX($R15,EOMONTH(BW$1,-1)+1)+1) -> 31 | BX15: =ROUND(IF($Z15="",$T15,$Z15)*(BW15/IF($W15="",$Q15,$W15)),2) -> 6644.66 | BY15: =+ROUND(BX15*0.1,2) -> 664.47 | BZ15: =+SUM(BX15:BY15) -> 7309.13 | CA15: =+AD15+AI15+AN15+AS15+AX15+BC15+BH15+BM15+BR15+BW15 -> 198 | CB15: =+AE15+AJ15+AO15+AT15+AY15+BD15+BI15+BN15+BS15+BX15 -> 42440.07 | CC15: =+AF15+AK15+AP15+AU15+AZ15+BE15+BJ15+BO15+BT15+BY15 -> 4244.02 | CD15: =+SUM(CB15:CC15) -> 46684.09 | CE15: =ROUND(IF($Y15<>"",$Z15,$T15)-CB15,2) -> 0 | CF15: =ROUND(IF($Y15<>"",$AA15,$U15)-CC15,2) -> -0.01 | CG15: IVP GENERAL SANCHEZ CERRO | CH15: Miler Barrientos Ramos | CI15: Gerente | CJ15: 959 090 019 | CK15: Miler Barrientos Ramos | CL15: Memorando N° 0195-2026/MPGSC/GM/AFPT | CM15: 46112 | CN15: 959 090 019
A16: 15 | B16: 48 | C16: MOQUEGUA | D16: GENERAL SANCHEZ CERRO | E16: LA CAPILLA | F16: MO-512 | G16: TOHATA (KM 9+671) - COALAQUE - SOJAMURE - CAIMAN - HEMBRUNA (KM 16+019) , HEMBRUNA (KM 16+143) - CHALLAHUAYO - TALA - CURUYO - (KM 21+465), LA CAPILLA (KM 21+579) - VINOMORE - SAHUANAY (KM 24+785) | H16: 14.876 | I16: AFIRMADO | J16: 735 | K16: 240 | L16: 87471 | M16: 8746 | N16: 96217 | O16: C_388-2026 | P16: N & S INGENIERIA Y CONSTRUCCION S.A.C. | Q16: =+$K16 -> 240 | R16: 46190 | S16: =IF(Q16+R16=0,"",Q16+R16-1) -> 46429 | T16: 83097.45 | U16: =+ROUND(T16*0.1,2) -> 8309.75 | V16: =+SUM(T16:U16) -> 91407.2 | W16: 198 | X16: =+$R16 -> 46190 | Y16: =IF(W16>0,X16+W16-1,"") -> 46387 | Z16: 68555.39 | AA16: =+ROUND(Z16*0.1,2) -> 6855.54 | AB16: =+SUM(Z16:AA16) -> 75410.93 | AD16: =MAX(0,MIN(IF($Y16<>"",$Y16,$S16),AD$1)-MAX($R16,EOMONTH(AD$1,-1)+1)+1) -> 0 | AE16: =ROUND(IF($Z16="",$T16,$Z16)*(AD16/IF($W16="",$Q16,$W16)),2) -> 0 | AF16: =+ROUND(AE16*0.1,2) -> 0 | AG16: =+SUM(AE16:AF16) -> 0 | AI16: =MAX(0,MIN(IF($Y16<>"",$Y16,$S16),AI$1)-MAX($R16,EOMONTH(AI$1,-1)+1)+1) -> 0 | AJ16: =ROUND(IF($Z16="",$T16,$Z16)*(AI16/IF($W16="",$Q16,$W16)),2) -> 0 | AK16: =+ROUND(AJ16*0.1,2) -> 0 | AL16: =+SUM(AJ16:AK16) -> 0 | AN16: =MAX(0,MIN(IF($Y16<>"",$Y16,$S16),AN$1)-MAX($R16,EOMONTH(AN$1,-1)+1)+1) -> 0 | AO16: =ROUND(IF($Z16="",$T16,$Z16)*(AN16/IF($W16="",$Q16,$W16)),2) -> 0 | AP16: =+ROUND(AO16*0.1,2) -> 0 | AQ16: =+SUM(AO16:AP16) -> 0 | AS16: =MAX(0,MIN(IF($Y16<>"",$Y16,$S16),AS$1)-MAX($R16,EOMONTH(AS$1,-1)+1)+1) -> 14 | AT16: =ROUND(IF($Z16="",$T16,$Z16)*(AS16/IF($W16="",$Q16,$W16)),2) -> 4847.35 | AU16: =+ROUND(AT16*0.1,2) -> 484.74 | AV16: =+SUM(AT16:AU16) -> 5332.09 | AX16: =MAX(0,MIN(IF($Y16<>"",$Y16,$S16),AX$1)-MAX($R16,EOMONTH(AX$1,-1)+1)+1) -> 31 | AY16: =ROUND(IF($Z16="",$T16,$Z16)*(AX16/IF($W16="",$Q16,$W16)),2) -> 10733.42 | AZ16: =+ROUND(AY16*0.1,2) -> 1073.34 | BA16: =+SUM(AY16:AZ16) -> 11806.76 | BC16: =MAX(0,MIN(IF($Y16<>"",$Y16,$S16),BC$1)-MAX($R16,EOMONTH(BC$1,-1)+1)+1) -> 31 | BD16: =ROUND(IF($Z16="",$T16,$Z16)*(BC16/IF($W16="",$Q16,$W16)),2) -> 10733.42 | BE16: =+ROUND(BD16*0.1,2) -> 1073.34 | BF16: =+SUM(BD16:BE16) -> 11806.76 | BH16: =MAX(0,MIN(IF($Y16<>"",$Y16,$S16),BH$1)-MAX($R16,EOMONTH(BH$1,-1)+1)+1) -> 30 | BI16: =ROUND(IF($Z16="",$T16,$Z16)*(BH16/IF($W16="",$Q16,$W16)),2) -> 10387.18 | BJ16: =+ROUND(BI16*0.1,2) -> 1038.72 | BK16: =+SUM(BI16:BJ16) -> 11425.9 | BM16: =MAX(0,MIN(IF($Y16<>"",$Y16,$S16),BM$1)-MAX($R16,EOMONTH(BM$1,-1)+1)+1) -> 31 | BN16: =ROUND(IF($Z16="",$T16,$Z16)*(BM16/IF($W16="",$Q16,$W16)),2) -> 10733.42 | BO16: =+ROUND(BN16*0.1,2) -> 1073.34 | BP16: =+SUM(BN16:BO16) -> 11806.76 | BR16: =MAX(0,MIN(IF($Y16<>"",$Y16,$S16),BR$1)-MAX($R16,EOMONTH(BR$1,-1)+1)+1) -> 30 | BS16: =ROUND(IF($Z16="",$T16,$Z16)*(BR16/IF($W16="",$Q16,$W16)),2) -> 10387.18 | BT16: =+ROUND(BS16*0.1,2) -> 1038.72 | BU16: =+SUM(BS16:BT16) -> 11425.9 | BW16: =MAX(0,MIN(IF($Y16<>"",$Y16,$S16),BW$1)-MAX($R16,EOMONTH(BW$1,-1)+1)+1) -> 31 | BX16: =ROUND(IF($Z16="",$T16,$Z16)*(BW16/IF($W16="",$Q16,$W16)),2) -> 10733.42 | BY16: =+ROUND(BX16*0.1,2) -> 1073.34 | BZ16: =+SUM(BX16:BY16) -> 11806.76 | CA16: =+AD16+AI16+AN16+AS16+AX16+BC16+BH16+BM16+BR16+BW16 -> 198 | CB16: =+AE16+AJ16+AO16+AT16+AY16+BD16+BI16+BN16+BS16+BX16 -> 68555.39 | CC16: =+AF16+AK16+AP16+AU16+AZ16+BE16+BJ16+BO16+BT16+BY16 -> 6855.54 | CD16: =+SUM(CB16:CC16) -> 75410.93 | CE16: =ROUND(IF($Y16<>"",$Z16,$T16)-CB16,2) -> 0 | CF16: =ROUND(IF($Y16<>"",$AA16,$U16)-CC16,2) -> 0 | CG16: IVP GENERAL SANCHEZ CERRO | CH16: Miler Barrientos Ramos | CI16: Gerente | CJ16: 959 090 019 | CK16: Miler Barrientos Ramos | CL16: Memorando N° 0195-2026/MPGSC/GM/AFPT | CM16: 46112 | CN16: 959 090 019
A17: 16 | B17: 48 | C17: MOQUEGUA | D17: GENERAL SANCHEZ CERRO | E17: UBINAS | F17: MO-529 | G17: EMP. MO-100 - SANCAYA - C.P. SACOHAYA (KM 03+480), C.P. SACOHAYA (KM 03+675) - EMP. MO-101 (KM 12+865) | H17: 12.67 | I17: AFIRMADO | J17: 735 | K17: 240 | L17: 74500 | M17: 7449 | N17: 81949 | O17: C_390-2026 | P17: N & S INGENIERIA Y CONSTRUCCION S.A.C. | Q17: =+$K17 -> 240 | R17: 46190 | S17: =IF(Q17+R17=0,"",Q17+R17-1) -> 46429 | T17: 70775 | U17: =+ROUND(T17*0.1,2) -> 7077.5 | V17: =+SUM(T17:U17) -> 77852.5 | W17: 198 | X17: =+$R17 -> 46190 | Y17: =IF(W17>0,X17+W17-1,"") -> 46387 | Z17: 58389.95 | AA17: =+ROUND(Z17*0.1,2) -> 5839 | AB17: =+SUM(Z17:AA17) -> 64228.95 | AD17: =MAX(0,MIN(IF($Y17<>"",$Y17,$S17),AD$1)-MAX($R17,EOMONTH(AD$1,-1)+1)+1) -> 0 | AE17: =ROUND(IF($Z17="",$T17,$Z17)*(AD17/IF($W17="",$Q17,$W17)),2) -> 0 | AF17: =+ROUND(AE17*0.1,2) -> 0 | AG17: =+SUM(AE17:AF17) -> 0 | AI17: =MAX(0,MIN(IF($Y17<>"",$Y17,$S17),AI$1)-MAX($R17,EOMONTH(AI$1,-1)+1)+1) -> 0 | AJ17: =ROUND(IF($Z17="",$T17,$Z17)*(AI17/IF($W17="",$Q17,$W17)),2) -> 0 | AK17: =+ROUND(AJ17*0.1,2) -> 0 | AL17: =+SUM(AJ17:AK17) -> 0 | AN17: =MAX(0,MIN(IF($Y17<>"",$Y17,$S17),AN$1)-MAX($R17,EOMONTH(AN$1,-1)+1)+1) -> 0 | AO17: =ROUND(IF($Z17="",$T17,$Z17)*(AN17/IF($W17="",$Q17,$W17)),2) -> 0 | AP17: =+ROUND(AO17*0.1,2) -> 0 | AQ17: =+SUM(AO17:AP17) -> 0 | AS17: =MAX(0,MIN(IF($Y17<>"",$Y17,$S17),AS$1)-MAX($R17,EOMONTH(AS$1,-1)+1)+1) -> 14 | AT17: =ROUND(IF($Z17="",$T17,$Z17)*(AS17/IF($W17="",$Q17,$W17)),2) -> 4128.58 | AU17: =+ROUND(AT17*0.1,2) -> 412.86 | AV17: =+SUM(AT17:AU17) -> 4541.44 | AX17: =MAX(0,MIN(IF($Y17<>"",$Y17,$S17),AX$1)-MAX($R17,EOMONTH(AX$1,-1)+1)+1) -> 31 | AY17: =ROUND(IF($Z17="",$T17,$Z17)*(AX17/IF($W17="",$Q17,$W17)),2) -> 9141.86 | AZ17: =+ROUND(AY17*0.1,2) -> 914.19 | BA17: =+SUM(AY17:AZ17) -> 10056.05 | BC17: =MAX(0,MIN(IF($Y17<>"",$Y17,$S17),BC$1)-MAX($R17,EOMONTH(BC$1,-1)+1)+1) -> 31 | BD17: =ROUND(IF($Z17="",$T17,$Z17)*(BC17/IF($W17="",$Q17,$W17)),2) -> 9141.86 | BE17: =+ROUND(BD17*0.1,2) -> 914.19 | BF17: =+SUM(BD17:BE17) -> 10056.05 | BH17: =MAX(0,MIN(IF($Y17<>"",$Y17,$S17),BH$1)-MAX($R17,EOMONTH(BH$1,-1)+1)+1) -> 30 | BI17: =ROUND(IF($Z17="",$T17,$Z17)*(BH17/IF($W17="",$Q17,$W17)),2) -> 8846.96 | BJ17: =+ROUND(BI17*0.1,2) -> 884.7 | BK17: =+SUM(BI17:BJ17) -> 9731.66 | BM17: =MAX(0,MIN(IF($Y17<>"",$Y17,$S17),BM$1)-MAX($R17,EOMONTH(BM$1,-1)+1)+1) -> 31 | BN17: =ROUND(IF($Z17="",$T17,$Z17)*(BM17/IF($W17="",$Q17,$W17)),2) -> 9141.86 | BO17: =+ROUND(BN17*0.1,2) -> 914.19 | BP17: =+SUM(BN17:BO17) -> 10056.05 | BR17: =MAX(0,MIN(IF($Y17<>"",$Y17,$S17),BR$1)-MAX($R17,EOMONTH(BR$1,-1)+1)+1) -> 30 | BS17: =ROUND(IF($Z17="",$T17,$Z17)*(BR17/IF($W17="",$Q17,$W17)),2) -> 8846.96 | BT17: =+ROUND(BS17*0.1,2) -> 884.7 | BU17: =+SUM(BS17:BT17) -> 9731.66 | BW17: =MAX(0,MIN(IF($Y17<>"",$Y17,$S17),BW$1)-MAX($R17,EOMONTH(BW$1,-1)+1)+1) -> 31 | BX17: =ROUND(IF($Z17="",$T17,$Z17)*(BW17/IF($W17="",$Q17,$W17)),2) -> 9141.86 | BY17: =+ROUND(BX17*0.1,2) -> 914.19 | BZ17: =+SUM(BX17:BY17) -> 10056.05 | CA17: =+AD17+AI17+AN17+AS17+AX17+BC17+BH17+BM17+BR17+BW17 -> 198 | CB17: =+AE17+AJ17+AO17+AT17+AY17+BD17+BI17+BN17+BS17+BX17 -> 58389.94 | CC17: =+AF17+AK17+AP17+AU17+AZ17+BE17+BJ17+BO17+BT17+BY17 -> 5839.02 | CD17: =+SUM(CB17:CC17) -> 64228.96 | CE17: =ROUND(IF($Y17<>"",$Z17,$T17)-CB17,2) -> 0.01 | CF17: =ROUND(IF($Y17<>"",$AA17,$U17)-CC17,2) -> -0.02 | CG17: IVP GENERAL SANCHEZ CERRO | CH17: Miler Barrientos Ramos | CI17: Gerente | CJ17: 959 090 019 | CK17: Miler Barrientos Ramos | CL17: Memorando N° 0195-2026/MPGSC/GM/AFPT | CM17: 46112 | CN17: 959 090 019
A18: 17 | B18: 48 | C18: MOQUEGUA | D18: GENERAL SANCHEZ CERRO | E18: UBINAS | F18: R180238 | G18: EMP. MO-101 - EMP. MO-529 | H18: 6.516 | I18: AFIRMADO | J18: 735 | K18: 240 | L18: 38314 | M18: 3831 | N18: 42145 | O18: OS-172 | P18: ASOCIACIÓN CIVIL SAGRADO CORAZÓN DE JESÚS-OMATE - ASSACOJE | Q18: =+$K18 -> 240 | R18: 46101 | S18: =IF(Q18+R18=0,"",Q18+R18-1) -> 46340 | T18: 36700 | U18: =+ROUND(T18*0.1,2) -> 3670 | V18: =+SUM(T18:U18) -> 40370 | X18: =+$R18 -> 46101 | Y18: =IF(W18>0,X18+W18-1,"") | AA18: =+ROUND(Z18*0.1,2) -> 0 | AB18: =+SUM(Z18:AA18) -> 0 | AD18: =MAX(0,MIN(IF($Y18<>"",$Y18,$S18),AD$1)-MAX($R18,EOMONTH(AD$1,-1)+1)+1) -> 12 | AE18: =ROUND(IF($Z18="",$T18,$Z18)*(AD18/IF($W18="",$Q18,$W18)),2) -> 1835 | AF18: =+ROUND(AE18*0.1,2) -> 183.5 | AG18: =+SUM(AE18:AF18) -> 2018.5 | AI18: =MAX(0,MIN(IF($Y18<>"",$Y18,$S18),AI$1)-MAX($R18,EOMONTH(AI$1,-1)+1)+1) -> 30 | AJ18: =ROUND(IF($Z18="",$T18,$Z18)*(AI18/IF($W18="",$Q18,$W18)),2) -> 4587.5 | AK18: =+ROUND(AJ18*0.1,2) -> 458.75 | AL18: =+SUM(AJ18:AK18) -> 5046.25 | AN18: =MAX(0,MIN(IF($Y18<>"",$Y18,$S18),AN$1)-MAX($R18,EOMONTH(AN$1,-1)+1)+1) -> 31 | AO18: =ROUND(IF($Z18="",$T18,$Z18)*(AN18/IF($W18="",$Q18,$W18)),2) -> 4740.42 | AP18: =+ROUND(AO18*0.1,2) -> 474.04 | AQ18: =+SUM(AO18:AP18) -> 5214.46 | AS18: =MAX(0,MIN(IF($Y18<>"",$Y18,$S18),AS$1)-MAX($R18,EOMONTH(AS$1,-1)+1)+1) -> 30 | AT18: =ROUND(IF($Z18="",$T18,$Z18)*(AS18/IF($W18="",$Q18,$W18)),2) -> 4587.5 | AU18: =+ROUND(AT18*0.1,2) -> 458.75 | AV18: =+SUM(AT18:AU18) -> 5046.25 | AX18: =MAX(0,MIN(IF($Y18<>"",$Y18,$S18),AX$1)-MAX($R18,EOMONTH(AX$1,-1)+1)+1) -> 31 | AY18: =ROUND(IF($Z18="",$T18,$Z18)*(AX18/IF($W18="",$Q18,$W18)),2) -> 4740.42 | AZ18: =+ROUND(AY18*0.1,2) -> 474.04 | BA18: =+SUM(AY18:AZ18) -> 5214.46 | BC18: =MAX(0,MIN(IF($Y18<>"",$Y18,$S18),BC$1)-MAX($R18,EOMONTH(BC$1,-1)+1)+1) -> 31 | BD18: =ROUND(IF($Z18="",$T18,$Z18)*(BC18/IF($W18="",$Q18,$W18)),2) -> 4740.42 | BE18: =+ROUND(BD18*0.1,2) -> 474.04 | BF18: =+SUM(BD18:BE18) -> 5214.46 | BH18: =MAX(0,MIN(IF($Y18<>"",$Y18,$S18),BH$1)-MAX($R18,EOMONTH(BH$1,-1)+1)+1) -> 30 | BI18: =ROUND(IF($Z18="",$T18,$Z18)*(BH18/IF($W18="",$Q18,$W18)),2) -> 4587.5 | BJ18: =+ROUND(BI18*0.1,2) -> 458.75 | BK18: =+SUM(BI18:BJ18) -> 5046.25 | BM18: =MAX(0,MIN(IF($Y18<>"",$Y18,$S18),BM$1)-MAX($R18,EOMONTH(BM$1,-1)+1)+1) -> 31 | BN18: =ROUND(IF($Z18="",$T18,$Z18)*(BM18/IF($W18="",$Q18,$W18)),2) -> 4740.42 | BO18: =+ROUND(BN18*0.1,2) -> 474.04 | BP18: =+SUM(BN18:BO18) -> 5214.46 | BR18: =MAX(0,MIN(IF($Y18<>"",$Y18,$S18),BR$1)-MAX($R18,EOMONTH(BR$1,-1)+1)+1) -> 14 | BS18: =ROUND(IF($Z18="",$T18,$Z18)*(BR18/IF($W18="",$Q18,$W18)),2) -> 2140.83 | BT18: =+ROUND(BS18*0.1,2) -> 214.08 | BU18: =+SUM(BS18:BT18) -> 2354.91 | BW18: =MAX(0,MIN(IF($Y18<>"",$Y18,$S18),BW$1)-MAX($R18,EOMONTH(BW$1,-1)+1)+1) -> 0 | BX18: =ROUND(IF($Z18="",$T18,$Z18)*(BW18/IF($W18="",$Q18,$W18)),2) -> 0 | BY18: =+ROUND(BX18*0.1,2) -> 0 | BZ18: =+SUM(BX18:BY18) -> 0 | CA18: =+AD18+AI18+AN18+AS18+AX18+BC18+BH18+BM18+BR18+BW18 -> 240 | CB18: =+AE18+AJ18+AO18+AT18+AY18+BD18+BI18+BN18+BS18+BX18 -> 36700.01 | CC18: =+AF18+AK18+AP18+AU18+AZ18+BE18+BJ18+BO18+BT18+BY18 -> 3669.99 | CD18: =+SUM(CB18:CC18) -> 40370 | CE18: =ROUND(IF($Y18<>"",$Z18,$T18)-CB18,2) -> -0.01 | CF18: =ROUND(IF($Y18<>"",$AA18,$U18)-CC18,2) -> 0.01 | CG18: IVP GENERAL SANCHEZ CERRO | CH18: Miler Barrientos Ramos | CI18: Gerente | CJ18: 959 090 019 | CK18: Miler Barrientos Ramos | CL18: Memorando N° 0195-2026/MPGSC/GM/AFPT | CM18: 46112 | CN18: 959 090 019
A19: 18 | B19: 48 | C19: MOQUEGUA | D19: GENERAL SANCHEZ CERRO | E19: UBINAS | F19: MO-530 | G19: EMP. MO-101 (MAYUMAYU)-ESCACHA (KM 07+081) | H19: 7.081 | I19: AFIRMADO | J19: 735 | K19: 240 | L19: 41636 | M19: 4164 | N19: 45800 | O19: OS-530 | P19: N & S INGENIERIA Y CONSTRUCCION S.A.C. | Q19: =+$K19 -> 240 | R19: 46107 | S19: =IF(Q19+R19=0,"",Q19+R19-1) -> 46346 | T19: 40000 | U19: =+ROUND(T19*0.1,2) -> 4000 | V19: =+SUM(T19:U19) -> 44000 | X19: =+$R19 -> 46107 | Y19: =IF(W19>0,X19+W19-1,"") | AA19: =+ROUND(Z19*0.1,2) -> 0 | AB19: =+SUM(Z19:AA19) -> 0 | AD19: =MAX(0,MIN(IF($Y19<>"",$Y19,$S19),AD$1)-MAX($R19,EOMONTH(AD$1,-1)+1)+1) -> 6 | AE19: =ROUND(IF($Z19="",$T19,$Z19)*(AD19/IF($W19="",$Q19,$W19)),2) -> 1000 | AF19: =+ROUND(AE19*0.1,2) -> 100 | AG19: =+SUM(AE19:AF19) -> 1100 | AI19: =MAX(0,MIN(IF($Y19<>"",$Y19,$S19),AI$1)-MAX($R19,EOMONTH(AI$1,-1)+1)+1) -> 30 | AJ19: =ROUND(IF($Z19="",$T19,$Z19)*(AI19/IF($W19="",$Q19,$W19)),2) -> 5000 | AK19: =+ROUND(AJ19*0.1,2) -> 500 | AL19: =+SUM(AJ19:AK19) -> 5500 | AN19: =MAX(0,MIN(IF($Y19<>"",$Y19,$S19),AN$1)-MAX($R19,EOMONTH(AN$1,-1)+1)+1) -> 31 | AO19: =ROUND(IF($Z19="",$T19,$Z19)*(AN19/IF($W19="",$Q19,$W19)),2) -> 5166.67 | AP19: =+ROUND(AO19*0.1,2) -> 516.67 | AQ19: =+SUM(AO19:AP19) -> 5683.34 | AS19: =MAX(0,MIN(IF($Y19<>"",$Y19,$S19),AS$1)-MAX($R19,EOMONTH(AS$1,-1)+1)+1) -> 30 | AT19: =ROUND(IF($Z19="",$T19,$Z19)*(AS19/IF($W19="",$Q19,$W19)),2) -> 5000 | AU19: =+ROUND(AT19*0.1,2) -> 500 | AV19: =+SUM(AT19:AU19) -> 5500 | AX19: =MAX(0,MIN(IF($Y19<>"",$Y19,$S19),AX$1)-MAX($R19,EOMONTH(AX$1,-1)+1)+1) -> 31 | AY19: =ROUND(IF($Z19="",$T19,$Z19)*(AX19/IF($W19="",$Q19,$W19)),2) -> 5166.67 | AZ19: =+ROUND(AY19*0.1,2) -> 516.67 | BA19: =+SUM(AY19:AZ19) -> 5683.34 | BC19: =MAX(0,MIN(IF($Y19<>"",$Y19,$S19),BC$1)-MAX($R19,EOMONTH(BC$1,-1)+1)+1) -> 31 | BD19: =ROUND(IF($Z19="",$T19,$Z19)*(BC19/IF($W19="",$Q19,$W19)),2) -> 5166.67 | BE19: =+ROUND(BD19*0.1,2) -> 516.67 | BF19: =+SUM(BD19:BE19) -> 5683.34 | BH19: =MAX(0,MIN(IF($Y19<>"",$Y19,$S19),BH$1)-MAX($R19,EOMONTH(BH$1,-1)+1)+1) -> 30 | BI19: =ROUND(IF($Z19="",$T19,$Z19)*(BH19/IF($W19="",$Q19,$W19)),2) -> 5000 | BJ19: =+ROUND(BI19*0.1,2) -> 500 | BK19: =+SUM(BI19:BJ19) -> 5500 | BM19: =MAX(0,MIN(IF($Y19<>"",$Y19,$S19),BM$1)-MAX($R19,EOMONTH(BM$1,-1)+1)+1) -> 31 | BN19: =ROUND(IF($Z19="",$T19,$Z19)*(BM19/IF($W19="",$Q19,$W19)),2) -> 5166.67 | BO19: =+ROUND(BN19*0.1,2) -> 516.67 | BP19: =+SUM(BN19:BO19) -> 5683.34 | BR19: =MAX(0,MIN(IF($Y19<>"",$Y19,$S19),BR$1)-MAX($R19,EOMONTH(BR$1,-1)+1)+1) -> 20 | BS19: =ROUND(IF($Z19="",$T19,$Z19)*(BR19/IF($W19="",$Q19,$W19)),2) -> 3333.33 | BT19: =+ROUND(BS19*0.1,2) -> 333.33 | BU19: =+SUM(BS19:BT19) -> 3666.66 | BW19: =MAX(0,MIN(IF($Y19<>"",$Y19,$S19),BW$1)-MAX($R19,EOMONTH(BW$1,-1)+1)+1) -> 0 | BX19: =ROUND(IF($Z19="",$T19,$Z19)*(BW19/IF($W19="",$Q19,$W19)),2) -> 0 | BY19: =+ROUND(BX19*0.1,2) -> 0 | BZ19: =+SUM(BX19:BY19) -> 0 | CA19: =+AD19+AI19+AN19+AS19+AX19+BC19+BH19+BM19+BR19+BW19 -> 240 | CB19: =+AE19+AJ19+AO19+AT19+AY19+BD19+BI19+BN19+BS19+BX19 -> 40000.01 | CC19: =+AF19+AK19+AP19+AU19+AZ19+BE19+BJ19+BO19+BT19+BY19 -> 4000.01 | CD19: =+SUM(CB19:CC19) -> 44000.02 | CE19: =ROUND(IF($Y19<>"",$Z19,$T19)-CB19,2) -> -0.01 | CF19: =ROUND(IF($Y19<>"",$AA19,$U19)-CC19,2) -> -0.01 | CG19: IVP GENERAL SANCHEZ CERRO | CH19: Miler Barrientos Ramos | CI19: Gerente | CJ19: 959 090 019 | CK19: Miler Barrientos Ramos | CL19: Memorando N° 0195-2026/MPGSC/GM/AFPT | CM19: 46112 | CN19: 959 090 019
A20: 19 | B20: 48 | C20: MOQUEGUA | D20: GENERAL SANCHEZ CERRO | E20: COALAQUE | F20: MO-518 | G20: EMP. MO-108 (COALAQUE) - INGRESANTES - ALTO INFIERNILLO - CHACLACA (KM 05+393) | H20: 5.393 | I20: AFIRMADO | J20: 735 | K20: 240 | L20: 31711 | M20: 3171 | N20: 34882 | O20: OS-158 | P20: ASOCIACIÓN DE MANTENIMIENTO DE VÍAS VECINALES RURALES Y URBANOS SAN BERNARDO | Q20: =+$K20 -> 240 | R20: 46104 | S20: =IF(Q20+R20=0,"",Q20+R20-1) -> 46343 | T20: 30000 | U20: =+ROUND(T20*0.1,2) -> 3000 | V20: =+SUM(T20:U20) -> 33000 | X20: =+$R20 -> 46104 | Y20: =IF(W20>0,X20+W20-1,"") | AA20: =+ROUND(Z20*0.1,2) -> 0 | AB20: =+SUM(Z20:AA20) -> 0 | AD20: =MAX(0,MIN(IF($Y20<>"",$Y20,$S20),AD$1)-MAX($R20,EOMONTH(AD$1,-1)+1)+1) -> 9 | AE20: =ROUND(IF($Z20="",$T20,$Z20)*(AD20/IF($W20="",$Q20,$W20)),2) -> 1125 | AF20: =+ROUND(AE20*0.1,2) -> 112.5 | AG20: =+SUM(AE20:AF20) -> 1237.5 | AI20: =MAX(0,MIN(IF($Y20<>"",$Y20,$S20),AI$1)-MAX($R20,EOMONTH(AI$1,-1)+1)+1) -> 30 | AJ20: =ROUND(IF($Z20="",$T20,$Z20)*(AI20/IF($W20="",$Q20,$W20)),2) -> 3750 | AK20: =+ROUND(AJ20*0.1,2) -> 375 | AL20: =+SUM(AJ20:AK20) -> 4125 | AN20: =MAX(0,MIN(IF($Y20<>"",$Y20,$S20),AN$1)-MAX($R20,EOMONTH(AN$1,-1)+1)+1) -> 31 | AO20: =ROUND(IF($Z20="",$T20,$Z20)*(AN20/IF($W20="",$Q20,$W20)),2) -> 3875 | AP20: =+ROUND(AO20*0.1,2) -> 387.5 | AQ20: =+SUM(AO20:AP20) -> 4262.5 | AS20: =MAX(0,MIN(IF($Y20<>"",$Y20,$S20),AS$1)-MAX($R20,EOMONTH(AS$1,-1)+1)+1) -> 30 | AT20: =ROUND(IF($Z20="",$T20,$Z20)*(AS20/IF($W20="",$Q20,$W20)),2) -> 3750 | AU20: =+ROUND(AT20*0.1,2) -> 375 | AV20: =+SUM(AT20:AU20) -> 4125 | AX20: =MAX(0,MIN(IF($Y20<>"",$Y20,$S20),AX$1)-MAX($R20,EOMONTH(AX$1,-1)+1)+1) -> 31 | AY20: =ROUND(IF($Z20="",$T20,$Z20)*(AX20/IF($W20="",$Q20,$W20)),2) -> 3875 | AZ20: =+ROUND(AY20*0.1,2) -> 387.5 | BA20: =+SUM(AY20:AZ20) -> 4262.5 | BC20: =MAX(0,MIN(IF($Y20<>"",$Y20,$S20),BC$1)-MAX($R20,EOMONTH(BC$1,-1)+1)+1) -> 31 | BD20: =ROUND(IF($Z20="",$T20,$Z20)*(BC20/IF($W20="",$Q20,$W20)),2) -> 3875 | BE20: =+ROUND(BD20*0.1,2) -> 387.5 | BF20: =+SUM(BD20:BE20) -> 4262.5 | BH20: =MAX(0,MIN(IF($Y20<>"",$Y20,$S20),BH$1)-MAX($R20,EOMONTH(BH$1,-1)+1)+1) -> 30 | BI20: =ROUND(IF($Z20="",$T20,$Z20)*(BH20/IF($W20="",$Q20,$W20)),2) -> 3750 | BJ20: =+ROUND(BI20*0.1,2) -> 375 | BK20: =+SUM(BI20:BJ20) -> 4125 | BM20: =MAX(0,MIN(IF($Y20<>"",$Y20,$S20),BM$1)-MAX($R20,EOMONTH(BM$1,-1)+1)+1) -> 31 | BN20: =ROUND(IF($Z20="",$T20,$Z20)*(BM20/IF($W20="",$Q20,$W20)),2) -> 3875 | BO20: =+ROUND(BN20*0.1,2) -> 387.5 | BP20: =+SUM(BN20:BO20) -> 4262.5 | BR20: =MAX(0,MIN(IF($Y20<>"",$Y20,$S20),BR$1)-MAX($R20,EOMONTH(BR$1,-1)+1)+1) -> 17 | BS20: =ROUND(IF($Z20="",$T20,$Z20)*(BR20/IF($W20="",$Q20,$W20)),2) -> 2125 | BT20: =+ROUND(BS20*0.1,2) -> 212.5 | BU20: =+SUM(BS20:BT20) -> 2337.5 | BW20: =MAX(0,MIN(IF($Y20<>"",$Y20,$S20),BW$1)-MAX($R20,EOMONTH(BW$1,-1)+1)+1) -> 0 | BX20: =ROUND(IF($Z20="",$T20,$Z20)*(BW20/IF($W20="",$Q20,$W20)),2) -> 0 | BY20: =+ROUND(BX20*0.1,2) -> 0 | BZ20: =+SUM(BX20:BY20) -> 0 | CA20: =+AD20+AI20+AN20+AS20+AX20+BC20+BH20+BM20+BR20+BW20 -> 240 | CB20: =+AE20+AJ20+AO20+AT20+AY20+BD20+BI20+BN20+BS20+BX20 -> 30000 | CC20: =+AF20+AK20+AP20+AU20+AZ20+BE20+BJ20+BO20+BT20+BY20 -> 3000 | CD20: =+SUM(CB20:CC20) -> 33000 | CE20: =ROUND(IF($Y20<>"",$Z20,$T20)-CB20,2) -> 0 | CF20: =ROUND(IF($Y20<>"",$AA20,$U20)-CC20,2) -> 0 | CG20: IVP GENERAL SANCHEZ CERRO | CH20: Miler Barrientos Ramos | CI20: Gerente | CJ20: 959 090 019 | CK20: Miler Barrientos Ramos | CL20: Memorando N° 0195-2026/MPGSC/GM/AFPT | CM20: 46112 | CN20: 959 090 019
A21: 20 | B21: 48 | C21: MOQUEGUA | D21: GENERAL SANCHEZ CERRO | E21: COALAQUE | F21: MO-516 | G21: EMP. MO-108-PAMPA DOLORES -ULUCAN (KM 06+989) | H21: 6.989 | I21: AFIRMADO | J21: 735 | K21: 240 | L21: 41095 | M21: 4110 | N21: 45205 | O21: EXCLUIDO | Q21: =+$K21 -> 240 | S21: =IF(Q21+R21=0,"",Q21+R21-1) -> 239 | U21: =+ROUND(T21*0.1,2) -> 0 | V21: =+SUM(T21:U21) -> 0 | X21: =+$R21 -> 0 | Y21: =IF(W21>0,X21+W21-1,"") | AA21: =+ROUND(Z21*0.1,2) -> 0 | AB21: =+SUM(Z21:AA21) -> 0 | AD21: =MAX(0,MIN(IF($Y21<>"",$Y21,$S21),AD$1)-MAX($R21,EOMONTH(AD$1,-1)+1)+1) -> 0 | AE21: =ROUND(IF($Z21="",$T21,$Z21)*(AD21/IF($W21="",$Q21,$W21)),2) -> 0 | AF21: =+ROUND(AE21*0.1,2) -> 0 | AG21: =+SUM(AE21:AF21) -> 0 | AI21: =MAX(0,MIN(IF($Y21<>"",$Y21,$S21),AI$1)-MAX($R21,EOMONTH(AI$1,-1)+1)+1) -> 0 | AJ21: =ROUND(IF($Z21="",$T21,$Z21)*(AI21/IF($W21="",$Q21,$W21)),2) -> 0 | AK21: =+ROUND(AJ21*0.1,2) -> 0 | AL21: =+SUM(AJ21:AK21) -> 0 | AN21: =MAX(0,MIN(IF($Y21<>"",$Y21,$S21),AN$1)-MAX($R21,EOMONTH(AN$1,-1)+1)+1) -> 0 | AO21: =ROUND(IF($Z21="",$T21,$Z21)*(AN21/IF($W21="",$Q21,$W21)),2) -> 0 | AP21: =+ROUND(AO21*0.1,2) -> 0 | AQ21: =+SUM(AO21:AP21) -> 0 | AS21: =MAX(0,MIN(IF($Y21<>"",$Y21,$S21),AS$1)-MAX($R21,EOMONTH(AS$1,-1)+1)+1) -> 0 | AT21: =ROUND(IF($Z21="",$T21,$Z21)*(AS21/IF($W21="",$Q21,$W21)),2) -> 0 | AU21: =+ROUND(AT21*0.1,2) -> 0 | AV21: =+SUM(AT21:AU21) -> 0 | AX21: =MAX(0,MIN(IF($Y21<>"",$Y21,$S21),AX$1)-MAX($R21,EOMONTH(AX$1,-1)+1)+1) -> 0 | AY21: =ROUND(IF($Z21="",$T21,$Z21)*(AX21/IF($W21="",$Q21,$W21)),2) -> 0 | AZ21: =+ROUND(AY21*0.1,2) -> 0 | BA21: =+SUM(AY21:AZ21) -> 0 | BC21: =MAX(0,MIN(IF($Y21<>"",$Y21,$S21),BC$1)-MAX($R21,EOMONTH(BC$1,-1)+1)+1) -> 0 | BD21: =ROUND(IF($Z21="",$T21,$Z21)*(BC21/IF($W21="",$Q21,$W21)),2) -> 0 | BE21: =+ROUND(BD21*0.1,2) -> 0 | BF21: =+SUM(BD21:BE21) -> 0 | BH21: =MAX(0,MIN(IF($Y21<>"",$Y21,$S21),BH$1)-MAX($R21,EOMONTH(BH$1,-1)+1)+1) -> 0 | BI21: =ROUND(IF($Z21="",$T21,$Z21)*(BH21/IF($W21="",$Q21,$W21)),2) -> 0 | BJ21: =+ROUND(BI21*0.1,2) -> 0 | BK21: =+SUM(BI21:BJ21) -> 0 | BM21: =MAX(0,MIN(IF($Y21<>"",$Y21,$S21),BM$1)-MAX($R21,EOMONTH(BM$1,-1)+1)+1) -> 0 | BN21: =ROUND(IF($Z21="",$T21,$Z21)*(BM21/IF($W21="",$Q21,$W21)),2) -> 0 | BO21: =+ROUND(BN21*0.1,2) -> 0 | BP21: =+SUM(BN21:BO21) -> 0 | BR21: =MAX(0,MIN(IF($Y21<>"",$Y21,$S21),BR$1)-MAX($R21,EOMONTH(BR$1,-1)+1)+1) -> 0 | BS21: =ROUND(IF($Z21="",$T21,$Z21)*(BR21/IF($W21="",$Q21,$W21)),2) -> 0 | BT21: =+ROUND(BS21*0.1,2) -> 0 | BU21: =+SUM(BS21:BT21) -> 0 | BW21: =MAX(0,MIN(IF($Y21<>"",$Y21,$S21),BW$1)-MAX($R21,EOMONTH(BW$1,-1)+1)+1) -> 0 | BX21: =ROUND(IF($Z21="",$T21,$Z21)*(BW21/IF($W21="",$Q21,$W21)),2) -> 0 | BY21: =+ROUND(BX21*0.1,2) -> 0 | BZ21: =+SUM(BX21:BY21) -> 0 | CA21: =+AD21+AI21+AN21+AS21+AX21+BC21+BH21+BM21+BR21+BW21 -> 0 | CB21: =+AE21+AJ21+AO21+AT21+AY21+BD21+BI21+BN21+BS21+BX21 -> 0 | CC21: =+AF21+AK21+AP21+AU21+AZ21+BE21+BJ21+BO21+BT21+BY21 -> 0 | CD21: =+SUM(CB21:CC21) -> 0 | CE21: =ROUND(IF($Y21<>"",$Z21,$T21)-CB21,2) -> 0 | CF21: =ROUND(IF($Y21<>"",$AA21,$U21)-CC21,2) -> 0 | CG21: IVP GENERAL SANCHEZ CERRO | CH21: Miler Barrientos Ramos | CI21: Gerente | CJ21: 959 090 019 | CK21: Miler Barrientos Ramos | CL21: Memorando N° 0195-2026/MPGSC/GM/AFPT | CM21: 46112 | CN21: 959 090 019
A22: 21 | B22: 48 | C22: MOQUEGUA | D22: GENERAL SANCHEZ CERRO | E22: COALAQUE | F22: R180219 | G22: EMP. MO-516 (ULUCAN) - PALCAMAYO (KM 02+984) | H22: 2.984 | I22: AFIRMADO | J22: 735 | K22: 266 | L22: 19447 | M22: 1945 | N22: 21392 | O22: EXCLUIDO | Q22: =+$K22 -> 266 | S22: =IF(Q22+R22=0,"",Q22+R22-1) -> 265 | U22: =+ROUND(T22*0.1,2) -> 0 | V22: =+SUM(T22:U22) -> 0 | X22: =+$R22 -> 0 | Y22: =IF(W22>0,X22+W22-1,"") | AA22: =+ROUND(Z22*0.1,2) -> 0 | AB22: =+SUM(Z22:AA22) -> 0 | AD22: =MAX(0,MIN(IF($Y22<>"",$Y22,$S22),AD$1)-MAX($R22,EOMONTH(AD$1,-1)+1)+1) -> 0 | AE22: =ROUND(IF($Z22="",$T22,$Z22)*(AD22/IF($W22="",$Q22,$W22)),2) -> 0 | AF22: =+ROUND(AE22*0.1,2) -> 0 | AG22: =+SUM(AE22:AF22) -> 0 | AI22: =MAX(0,MIN(IF($Y22<>"",$Y22,$S22),AI$1)-MAX($R22,EOMONTH(AI$1,-1)+1)+1) -> 0 | AJ22: =ROUND(IF($Z22="",$T22,$Z22)*(AI22/IF($W22="",$Q22,$W22)),2) -> 0 | AK22: =+ROUND(AJ22*0.1,2) -> 0 | AL22: =+SUM(AJ22:AK22) -> 0 | AN22: =MAX(0,MIN(IF($Y22<>"",$Y22,$S22),AN$1)-MAX($R22,EOMONTH(AN$1,-1)+1)+1) -> 0 | AO22: =ROUND(IF($Z22="",$T22,$Z22)*(AN22/IF($W22="",$Q22,$W22)),2) -> 0 | AP22: =+ROUND(AO22*0.1,2) -> 0 | AQ22: =+SUM(AO22:AP22) -> 0 | AS22: =MAX(0,MIN(IF($Y22<>"",$Y22,$S22),AS$1)-MAX($R22,EOMONTH(AS$1,-1)+1)+1) -> 0 | AT22: =ROUND(IF($Z22="",$T22,$Z22)*(AS22/IF($W22="",$Q22,$W22)),2) -> 0 | AU22: =+ROUND(AT22*0.1,2) -> 0 | AV22: =+SUM(AT22:AU22) -> 0 | AX22: =MAX(0,MIN(IF($Y22<>"",$Y22,$S22),AX$1)-MAX($R22,EOMONTH(AX$1,-1)+1)+1) -> 0 | AY22: =ROUND(IF($Z22="",$T22,$Z22)*(AX22/IF($W22="",$Q22,$W22)),2) -> 0 | AZ22: =+ROUND(AY22*0.1,2) -> 0 | BA22: =+SUM(AY22:AZ22) -> 0 | BC22: =MAX(0,MIN(IF($Y22<>"",$Y22,$S22),BC$1)-MAX($R22,EOMONTH(BC$1,-1)+1)+1) -> 0 | BD22: =ROUND(IF($Z22="",$T22,$Z22)*(BC22/IF($W22="",$Q22,$W22)),2) -> 0 | BE22: =+ROUND(BD22*0.1,2) -> 0 | BF22: =+SUM(BD22:BE22) -> 0 | BH22: =MAX(0,MIN(IF($Y22<>"",$Y22,$S22),BH$1)-MAX($R22,EOMONTH(BH$1,-1)+1)+1) -> 0 | BI22: =ROUND(IF($Z22="",$T22,$Z22)*(BH22/IF($W22="",$Q22,$W22)),2) -> 0 | BJ22: =+ROUND(BI22*0.1,2) -> 0 | BK22: =+SUM(BI22:BJ22) -> 0 | BM22: =MAX(0,MIN(IF($Y22<>"",$Y22,$S22),BM$1)-MAX($R22,EOMONTH(BM$1,-1)+1)+1) -> 0 | BN22: =ROUND(IF($Z22="",$T22,$Z22)*(BM22/IF($W22="",$Q22,$W22)),2) -> 0 | BO22: =+ROUND(BN22*0.1,2) -> 0 | BP22: =+SUM(BN22:BO22) -> 0 | BR22: =MAX(0,MIN(IF($Y22<>"",$Y22,$S22),BR$1)-MAX($R22,EOMONTH(BR$1,-1)+1)+1) -> 0 | BS22: =ROUND(IF($Z22="",$T22,$Z22)*(BR22/IF($W22="",$Q22,$W22)),2) -> 0 | BT22: =+ROUND(BS22*0.1,2) -> 0 | BU22: =+SUM(BS22:BT22) -> 0 | BW22: =MAX(0,MIN(IF($Y22<>"",$Y22,$S22),BW$1)-MAX($R22,EOMONTH(BW$1,-1)+1)+1) -> 0 | BX22: =ROUND(IF($Z22="",$T22,$Z22)*(BW22/IF($W22="",$Q22,$W22)),2) -> 0 | BY22: =+ROUND(BX22*0.1,2) -> 0 | BZ22: =+SUM(BX22:BY22) -> 0 | CA22: =+AD22+AI22+AN22+AS22+AX22+BC22+BH22+BM22+BR22+BW22 -> 0 | CB22: =+AE22+AJ22+AO22+AT22+AY22+BD22+BI22+BN22+BS22+BX22 -> 0 | CC22: =+AF22+AK22+AP22+AU22+AZ22+BE22+BJ22+BO22+BT22+BY22 -> 0 | CD22: =+SUM(CB22:CC22) -> 0 | CE22: =ROUND(IF($Y22<>"",$Z22,$T22)-CB22,2) -> 0 | CF22: =ROUND(IF($Y22<>"",$AA22,$U22)-CC22,2) -> 0 | CG22: IVP GENERAL SANCHEZ CERRO | CH22: Miler Barrientos Ramos | CI22: Gerente | CJ22: 959 090 019 | CK22: Miler Barrientos Ramos | CL22: Memorando N° 0195-2026/MPGSC/GM/AFPT | CM22: 46112 | CN22: 959 090 019
A23: 22 | B23: 51 | C23: TACNA | D23: CANDARAVE | E23: QUILAHUANI | F23: TA-549 | G23: EMP. TA-103 (ARICOTA) - MARJANI (KM 2+031) | H23: 2.031 | I23: AFIRMADO | J23: 735 | K23: 240 | L23: 11942 | M23: 1194 | N23: 13136 | O23: O.S. 000155 | P23: GRUPO PAVE CONTRATISTAS & CONSULTORES E.I.R.L | Q23: =+$K23 -> 240 | R23: 46146 | S23: =IF(Q23+R23=0,"",Q23+R23-1) -> 46385 | T23: 11942 | U23: =+ROUND(T23*0.1,2) -> 1194.2 | V23: =+SUM(T23:U23) -> 13136.2 | X23: =+$R23 -> 46146 | Y23: =IF(W23>0,X23+W23-1,"") | AA23: =+ROUND(Z23*0.1,2) -> 0 | AB23: =+SUM(Z23:AA23) -> 0 | AD23: =MAX(0,MIN(IF($Y23<>"",$Y23,$S23),AD$1)-MAX($R23,EOMONTH(AD$1,-1)+1)+1) -> 0 | AE23: =ROUND(IF($Z23="",$T23,$Z23)*(AD23/IF($W23="",$Q23,$W23)),2) -> 0 | AF23: =+ROUND(AE23*0.1,2) -> 0 | AG23: =+SUM(AE23:AF23) -> 0 | AI23: =MAX(0,MIN(IF($Y23<>"",$Y23,$S23),AI$1)-MAX($R23,EOMONTH(AI$1,-1)+1)+1) -> 0 | AJ23: =ROUND(IF($Z23="",$T23,$Z23)*(AI23/IF($W23="",$Q23,$W23)),2) -> 0 | AK23: =+ROUND(AJ23*0.1,2) -> 0 | AL23: =+SUM(AJ23:AK23) -> 0 | AN23: =MAX(0,MIN(IF($Y23<>"",$Y23,$S23),AN$1)-MAX($R23,EOMONTH(AN$1,-1)+1)+1) -> 28 | AO23: =ROUND(IF($Z23="",$T23,$Z23)*(AN23/IF($W23="",$Q23,$W23)),2) -> 1393.23 | AP23: =+ROUND(AO23*0.1,2) -> 139.32 | AQ23: =+SUM(AO23:AP23) -> 1532.55 | AS23: =MAX(0,MIN(IF($Y23<>"",$Y23,$S23),AS$1)-MAX($R23,EOMONTH(AS$1,-1)+1)+1) -> 30 | AT23: =ROUND(IF($Z23="",$T23,$Z23)*(AS23/IF($W23="",$Q23,$W23)),2) -> 1492.75 | AU23: =+ROUND(AT23*0.1,2) -> 149.28 | AV23: =+SUM(AT23:AU23) -> 1642.03 | AX23: =MAX(0,MIN(IF($Y23<>"",$Y23,$S23),AX$1)-MAX($R23,EOMONTH(AX$1,-1)+1)+1) -> 31 | AY23: =ROUND(IF($Z23="",$T23,$Z23)*(AX23/IF($W23="",$Q23,$W23)),2) -> 1542.51 | AZ23: =+ROUND(AY23*0.1,2) -> 154.25 | BA23: =+SUM(AY23:AZ23) -> 1696.76 | BC23: =MAX(0,MIN(IF($Y23<>"",$Y23,$S23),BC$1)-MAX($R23,EOMONTH(BC$1,-1)+1)+1) -> 31 | BD23: =ROUND(IF($Z23="",$T23,$Z23)*(BC23/IF($W23="",$Q23,$W23)),2) -> 1542.51 | BE23: =+ROUND(BD23*0.1,2) -> 154.25 | BF23: =+SUM(BD23:BE23) -> 1696.76 | BH23: =MAX(0,MIN(IF($Y23<>"",$Y23,$S23),BH$1)-MAX($R23,EOMONTH(BH$1,-1)+1)+1) -> 30 | BI23: =ROUND(IF($Z23="",$T23,$Z23)*(BH23/IF($W23="",$Q23,$W23)),2) -> 1492.75 | BJ23: =+ROUND(BI23*0.1,2) -> 149.28 | BK23: =+SUM(BI23:BJ23) -> 1642.03 | BM23: =MAX(0,MIN(IF($Y23<>"",$Y23,$S23),BM$1)-MAX($R23,EOMONTH(BM$1,-1)+1)+1) -> 31 | BN23: =ROUND(IF($Z23="",$T23,$Z23)*(BM23/IF($W23="",$Q23,$W23)),2) -> 1542.51 | BO23: =+ROUND(BN23*0.1,2) -> 154.25 | BP23: =+SUM(BN23:BO23) -> 1696.76 | BR23: =MAX(0,MIN(IF($Y23<>"",$Y23,$S23),BR$1)-MAX($R23,EOMONTH(BR$1,-1)+1)+1) -> 30 | BS23: =ROUND(IF($Z23="",$T23,$Z23)*(BR23/IF($W23="",$Q23,$W23)),2) -> 1492.75 | BT23: =+ROUND(BS23*0.1,2) -> 149.28 | BU23: =+SUM(BS23:BT23) -> 1642.03 | BW23: =MAX(0,MIN(IF($Y23<>"",$Y23,$S23),BW$1)-MAX($R23,EOMONTH(BW$1,-1)+1)+1) -> 29 | BX23: =ROUND(IF($Z23="",$T23,$Z23)*(BW23/IF($W23="",$Q23,$W23)),2) -> 1442.99 | BY23: =+ROUND(BX23*0.1,2) -> 144.3 | BZ23: =+SUM(BX23:BY23) -> 1587.29 | CA23: =+AD23+AI23+AN23+AS23+AX23+BC23+BH23+BM23+BR23+BW23 -> 240 | CB23: =+AE23+AJ23+AO23+AT23+AY23+BD23+BI23+BN23+BS23+BX23 -> 11942 | CC23: =+AF23+AK23+AP23+AU23+AZ23+BE23+BJ23+BO23+BT23+BY23 -> 1194.21 | CD23: =+SUM(CB23:CC23) -> 13136.21 | CE23: =ROUND(IF($Y23<>"",$Z23,$T23)-CB23,2) -> 0 | CF23: =ROUND(IF($Y23<>"",$AA23,$U23)-CC23,2) -> -0.01 | CG23: IVP CANDARAVE | CH23: Alonso Mario Laura Paniagua | CI23: Gerente | CJ23: 969 494 987 | CK23: Alejandro Teobaldo Gonzales Huaraguara | CL23: Memorandum N° 011-2026-USLO-GM/MPC | CM23: 46142 | CN23: 985 200 188
A24: 23 | B24: 51 | C24: TACNA | D24: CANDARAVE | E24: CAMILACA | F24: TA-521 | G24: EMP. TA-109 - PTA. CARRETERA (ALTO CAMILACA) | H24: 5.842 | I24: AFIRMADO | J24: 735 | K24: 240 | L24: 34351 | M24: 3435 | N24: 37786 | O24: O.S. 000154 | P24: GRUPO PAVE CONTRATISTAS & CONSULTORES E.I.R.L | Q24: =+$K24 -> 240 | R24: 46146 | S24: =IF(Q24+R24=0,"",Q24+R24-1) -> 46385 | T24: 34351 | U24: =+ROUND(T24*0.1,2) -> 3435.1 | V24: =+SUM(T24:U24) -> 37786.1 | X24: =+$R24 -> 46146 | Y24: =IF(W24>0,X24+W24-1,"") | AA24: =+ROUND(Z24*0.1,2) -> 0 | AB24: =+SUM(Z24:AA24) -> 0 | AD24: =MAX(0,MIN(IF($Y24<>"",$Y24,$S24),AD$1)-MAX($R24,EOMONTH(AD$1,-1)+1)+1) -> 0 | AE24: =ROUND(IF($Z24="",$T24,$Z24)*(AD24/IF($W24="",$Q24,$W24)),2) -> 0 | AF24: =+ROUND(AE24*0.1,2) -> 0 | AG24: =+SUM(AE24:AF24) -> 0 | AI24: =MAX(0,MIN(IF($Y24<>"",$Y24,$S24),AI$1)-MAX($R24,EOMONTH(AI$1,-1)+1)+1) -> 0 | AJ24: =ROUND(IF($Z24="",$T24,$Z24)*(AI24/IF($W24="",$Q24,$W24)),2) -> 0 | AK24: =+ROUND(AJ24*0.1,2) -> 0 | AL24: =+SUM(AJ24:AK24) -> 0 | AN24: =MAX(0,MIN(IF($Y24<>"",$Y24,$S24),AN$1)-MAX($R24,EOMONTH(AN$1,-1)+1)+1) -> 28 | AO24: =ROUND(IF($Z24="",$T24,$Z24)*(AN24/IF($W24="",$Q24,$W24)),2) -> 4007.62 | AP24: =+ROUND(AO24*0.1,2) -> 400.76 | AQ24: =+SUM(AO24:AP24) -> 4408.38 | AS24: =MAX(0,MIN(IF($Y24<>"",$Y24,$S24),AS$1)-MAX($R24,EOMONTH(AS$1,-1)+1)+1) -> 30 | AT24: =ROUND(IF($Z24="",$T24,$Z24)*(AS24/IF($W24="",$Q24,$W24)),2) -> 4293.88 | AU24: =+ROUND(AT24*0.1,2) -> 429.39 | AV24: =+SUM(AT24:AU24) -> 4723.27 | AX24: =MAX(0,MIN(IF($Y24<>"",$Y24,$S24),AX$1)-MAX($R24,EOMONTH(AX$1,-1)+1)+1) -> 31 | AY24: =ROUND(IF($Z24="",$T24,$Z24)*(AX24/IF($W24="",$Q24,$W24)),2) -> 4437 | AZ24: =+ROUND(AY24*0.1,2) -> 443.7 | BA24: =+SUM(AY24:AZ24) -> 4880.7 | BC24: =MAX(0,MIN(IF($Y24<>"",$Y24,$S24),BC$1)-MAX($R24,EOMONTH(BC$1,-1)+1)+1) -> 31 | BD24: =ROUND(IF($Z24="",$T24,$Z24)*(BC24/IF($W24="",$Q24,$W24)),2) -> 4437 | BE24: =+ROUND(BD24*0.1,2) -> 443.7 | BF24: =+SUM(BD24:BE24) -> 4880.7 | BH24: =MAX(0,MIN(IF($Y24<>"",$Y24,$S24),BH$1)-MAX($R24,EOMONTH(BH$1,-1)+1)+1) -> 30 | BI24: =ROUND(IF($Z24="",$T24,$Z24)*(BH24/IF($W24="",$Q24,$W24)),2) -> 4293.88 | BJ24: =+ROUND(BI24*0.1,2) -> 429.39 | BK24: =+SUM(BI24:BJ24) -> 4723.27 | BM24: =MAX(0,MIN(IF($Y24<>"",$Y24,$S24),BM$1)-MAX($R24,EOMONTH(BM$1,-1)+1)+1) -> 31 | BN24: =ROUND(IF($Z24="",$T24,$Z24)*(BM24/IF($W24="",$Q24,$W24)),2) -> 4437 | BO24: =+ROUND(BN24*0.1,2) -> 443.7 | BP24: =+SUM(BN24:BO24) -> 4880.7 | BR24: =MAX(0,MIN(IF($Y24<>"",$Y24,$S24),BR$1)-MAX($R24,EOMONTH(BR$1,-1)+1)+1) -> 30 | BS24: =ROUND(IF($Z24="",$T24,$Z24)*(BR24/IF($W24="",$Q24,$W24)),2) -> 4293.88 | BT24: =+ROUND(BS24*0.1,2) -> 429.39 | BU24: =+SUM(BS24:BT24) -> 4723.27 | BW24: =MAX(0,MIN(IF($Y24<>"",$Y24,$S24),BW$1)-MAX($R24,EOMONTH(BW$1,-1)+1)+1) -> 29 | BX24: =ROUND(IF($Z24="",$T24,$Z24)*(BW24/IF($W24="",$Q24,$W24)),2) -> 4150.75 | BY24: =+ROUND(BX24*0.1,2) -> 415.08 | BZ24: =+SUM(BX24:BY24) -> 4565.83 | CA24: =+AD24+AI24+AN24+AS24+AX24+BC24+BH24+BM24+BR24+BW24 -> 240 | CB24: =+AE24+AJ24+AO24+AT24+AY24+BD24+BI24+BN24+BS24+BX24 -> 34351.01 | CC24: =+AF24+AK24+AP24+AU24+AZ24+BE24+BJ24+BO24+BT24+BY24 -> 3435.11 | CD24: =+SUM(CB24:CC24) -> 37786.12 | CE24: =ROUND(IF($Y24<>"",$Z24,$T24)-CB24,2) -> -0.01 | CF24: =ROUND(IF($Y24<>"",$AA24,$U24)-CC24,2) -> -0.01 | CG24: IVP CANDARAVE | CH24: Alonso Mario Laura Paniagua | CI24: Gerente | CJ24: 969 494 987 | CK24: Alejandro Teobaldo Gonzales Huaraguara | CL24: Memorandum N° 011-2026-USLO-GM/MPC | CM24: 46142 | CN24: 985 200 188
A25: 24 | B25: 51 | C25: TACNA | D25: CANDARAVE | E25: HUANUARA; CANDARAVE; CURIBAYA | F25: TA-544 | G25: EMP. TA-109 - DV. ANTAVILCA - EMP. TA-104 (LAGUNA ARICOTA) | H25: 26.9 | I25: AFIRMADO | J25: 735 | K25: 240 | L25: 158172 | M25: 15817 | N25: 173989 | O25: Contrato N° 02-2026-MPС | P25: CONSORCIO VIAL ARICOTA | Q25: =+$K25 -> 240 | R25: 46223 | S25: =IF(Q25+R25=0,"",Q25+R25-1) -> 46462 | T25: 118360 | U25: =+ROUND(T25*0.1,2) -> 11836 | V25: =+SUM(T25:U25) -> 130196 | W25: 163 | X25: =+$R25 -> 46223 | Y25: =IF(W25>0,X25+W25-1,"") -> 46385 | Z25: 107425.15 | AA25: =+ROUND(Z25*0.1,2) -> 10742.52 | AB25: =+SUM(Z25:AA25) -> 118167.67 | AD25: =MAX(0,MIN(IF($Y25<>"",$Y25,$S25),AD$1)-MAX($R25,EOMONTH(AD$1,-1)+1)+1) -> 0 | AE25: =ROUND(IF($Z25="",$T25,$Z25)*(AD25/IF($W25="",$Q25,$W25)),2) -> 0 | AF25: =+ROUND(AE25*0.1,2) -> 0 | AG25: =+SUM(AE25:AF25) -> 0 | AI25: =MAX(0,MIN(IF($Y25<>"",$Y25,$S25),AI$1)-MAX($R25,EOMONTH(AI$1,-1)+1)+1) -> 0 | AJ25: =ROUND(IF($Z25="",$T25,$Z25)*(AI25/IF($W25="",$Q25,$W25)),2) -> 0 | AK25: =+ROUND(AJ25*0.1,2) -> 0 | AL25: =+SUM(AJ25:AK25) -> 0 | AN25: =MAX(0,MIN(IF($Y25<>"",$Y25,$S25),AN$1)-MAX($R25,EOMONTH(AN$1,-1)+1)+1) -> 0 | AO25: =ROUND(IF($Z25="",$T25,$Z25)*(AN25/IF($W25="",$Q25,$W25)),2) -> 0 | AP25: =+ROUND(AO25*0.1,2) -> 0 | AQ25: =+SUM(AO25:AP25) -> 0 | AS25: =MAX(0,MIN(IF($Y25<>"",$Y25,$S25),AS$1)-MAX($R25,EOMONTH(AS$1,-1)+1)+1) -> 0 | AT25: =ROUND(IF($Z25="",$T25,$Z25)*(AS25/IF($W25="",$Q25,$W25)),2) -> 0 | AU25: =+ROUND(AT25*0.1,2) -> 0 | AV25: =+SUM(AT25:AU25) -> 0 | AX25: =MAX(0,MIN(IF($Y25<>"",$Y25,$S25),AX$1)-MAX($R25,EOMONTH(AX$1,-1)+1)+1) -> 12 | AY25: =ROUND(IF($Z25="",$T25,$Z25)*(AX25/IF($W25="",$Q25,$W25)),2) -> 7908.6 | AZ25: =+ROUND(AY25*0.1,2) -> 790.86 | BA25: =+SUM(AY25:AZ25) -> 8699.46 | BC25: =MAX(0,MIN(IF($Y25<>"",$Y25,$S25),BC$1)-MAX($R25,EOMONTH(BC$1,-1)+1)+1) -> 31 | BD25: =ROUND(IF($Z25="",$T25,$Z25)*(BC25/IF($W25="",$Q25,$W25)),2) -> 20430.55 | BE25: =+ROUND(BD25*0.1,2) -> 2043.06 | BF25: =+SUM(BD25:BE25) -> 22473.61 | BH25: =MAX(0,MIN(IF($Y25<>"",$Y25,$S25),BH$1)-MAX($R25,EOMONTH(BH$1,-1)+1)+1) -> 30 | BI25: =ROUND(IF($Z25="",$T25,$Z25)*(BH25/IF($W25="",$Q25,$W25)),2) -> 19771.5 | BJ25: =+ROUND(BI25*0.1,2) -> 1977.15 | BK25: =+SUM(BI25:BJ25) -> 21748.65 | BM25: =MAX(0,MIN(IF($Y25<>"",$Y25,$S25),BM$1)-MAX($R25,EOMONTH(BM$1,-1)+1)+1) -> 31 | BN25: =ROUND(IF($Z25="",$T25,$Z25)*(BM25/IF($W25="",$Q25,$W25)),2) -> 20430.55 | BO25: =+ROUND(BN25*0.1,2) -> 2043.06 | BP25: =+SUM(BN25:BO25) -> 22473.61 | BR25: =MAX(0,MIN(IF($Y25<>"",$Y25,$S25),BR$1)-MAX($R25,EOMONTH(BR$1,-1)+1)+1) -> 30 | BS25: =ROUND(IF($Z25="",$T25,$Z25)*(BR25/IF($W25="",$Q25,$W25)),2) -> 19771.5 | BT25: =+ROUND(BS25*0.1,2) -> 1977.15 | BU25: =+SUM(BS25:BT25) -> 21748.65 | BW25: =MAX(0,MIN(IF($Y25<>"",$Y25,$S25),BW$1)-MAX($R25,EOMONTH(BW$1,-1)+1)+1) -> 29 | BX25: =ROUND(IF($Z25="",$T25,$Z25)*(BW25/IF($W25="",$Q25,$W25)),2) -> 19112.45 | BY25: =+ROUND(BX25*0.1,2) -> 1911.25 | BZ25: =+SUM(BX25:BY25) -> 21023.7 | CA25: =+AD25+AI25+AN25+AS25+AX25+BC25+BH25+BM25+BR25+BW25 -> 163 | CB25: =+AE25+AJ25+AO25+AT25+AY25+BD25+BI25+BN25+BS25+BX25 -> 107425.15 | CC25: =+AF25+AK25+AP25+AU25+AZ25+BE25+BJ25+BO25+BT25+BY25 -> 10742.53 | CD25: =+SUM(CB25:CC25) -> 118167.68 | CE25: =ROUND(IF($Y25<>"",$Z25,$T25)-CB25,2) -> 0 | CF25: =ROUND(IF($Y25<>"",$AA25,$U25)-CC25,2) -> -0.01 | CG25: IVP CANDARAVE | CH25: Alonso Mario Laura Paniagua | CI25: Gerente | CJ25: 969 494 987 | CK25: Alonso Mario Laura Paniagua | CL25: Memorandum N° 013-2026-USLO-GM/MPC | CM25: 46220 | CN25: 969 494 987
A26: 25 | B26: 51 | C26: TACNA | D26: CANDARAVE | E26: CAMILACA | F26: TA-515 | G26: EMP. TA-519 (DV. ALTO CAMILACA)- PTA. CARRETERA (KM 104+852) | H26: 7.2 | I26: AFIRMADO | J26: 735 | K26: 240 | L26: 42336 | M26: 4234 | N26: 46570 | O26: O.S. 000153 | P26: GEDICO CONTRATISTAS GENERALES E.I.R.L | Q26: =+$K26 -> 240 | R26: 46146 | S26: =IF(Q26+R26=0,"",Q26+R26-1) -> 46385 | T26: 42336 | U26: =+ROUND(T26*0.1,2) -> 4233.6 | V26: =+SUM(T26:U26) -> 46569.6 | X26: =+$R26 -> 46146 | Y26: =IF(W26>0,X26+W26-1,"") | AA26: =+ROUND(Z26*0.1,2) -> 0 | AB26: =+SUM(Z26:AA26) -> 0 | AD26: =MAX(0,MIN(IF($Y26<>"",$Y26,$S26),AD$1)-MAX($R26,EOMONTH(AD$1,-1)+1)+1) -> 0 | AE26: =ROUND(IF($Z26="",$T26,$Z26)*(AD26/IF($W26="",$Q26,$W26)),2) -> 0 | AF26: =+ROUND(AE26*0.1,2) -> 0 | AG26: =+SUM(AE26:AF26) -> 0 | AI26: =MAX(0,MIN(IF($Y26<>"",$Y26,$S26),AI$1)-MAX($R26,EOMONTH(AI$1,-1)+1)+1) -> 0 | AJ26: =ROUND(IF($Z26="",$T26,$Z26)*(AI26/IF($W26="",$Q26,$W26)),2) -> 0 | AK26: =+ROUND(AJ26*0.1,2) -> 0 | AL26: =+SUM(AJ26:AK26) -> 0 | AN26: =MAX(0,MIN(IF($Y26<>"",$Y26,$S26),AN$1)-MAX($R26,EOMONTH(AN$1,-1)+1)+1) -> 28 | AO26: =ROUND(IF($Z26="",$T26,$Z26)*(AN26/IF($W26="",$Q26,$W26)),2) -> 4939.2 | AP26: =+ROUND(AO26*0.1,2) -> 493.92 | AQ26: =+SUM(AO26:AP26) -> 5433.12 | AS26: =MAX(0,MIN(IF($Y26<>"",$Y26,$S26),AS$1)-MAX($R26,EOMONTH(AS$1,-1)+1)+1) -> 30 | AT26: =ROUND(IF($Z26="",$T26,$Z26)*(AS26/IF($W26="",$Q26,$W26)),2) -> 5292 | AU26: =+ROUND(AT26*0.1,2) -> 529.2 | AV26: =+SUM(AT26:AU26) -> 5821.2 | AX26: =MAX(0,MIN(IF($Y26<>"",$Y26,$S26),AX$1)-MAX($R26,EOMONTH(AX$1,-1)+1)+1) -> 31 | AY26: =ROUND(IF($Z26="",$T26,$Z26)*(AX26/IF($W26="",$Q26,$W26)),2) -> 5468.4 | AZ26: =+ROUND(AY26*0.1,2) -> 546.84 | BA26: =+SUM(AY26:AZ26) -> 6015.24 | BC26: =MAX(0,MIN(IF($Y26<>"",$Y26,$S26),BC$1)-MAX($R26,EOMONTH(BC$1,-1)+1)+1) -> 31 | BD26: =ROUND(IF($Z26="",$T26,$Z26)*(BC26/IF($W26="",$Q26,$W26)),2) -> 5468.4 | BE26: =+ROUND(BD26*0.1,2) -> 546.84 | BF26: =+SUM(BD26:BE26) -> 6015.24 | BH26: =MAX(0,MIN(IF($Y26<>"",$Y26,$S26),BH$1)-MAX($R26,EOMONTH(BH$1,-1)+1)+1) -> 30 | BI26: =ROUND(IF($Z26="",$T26,$Z26)*(BH26/IF($W26="",$Q26,$W26)),2) -> 5292 | BJ26: =+ROUND(BI26*0.1,2) -> 529.2 | BK26: =+SUM(BI26:BJ26) -> 5821.2 | BM26: =MAX(0,MIN(IF($Y26<>"",$Y26,$S26),BM$1)-MAX($R26,EOMONTH(BM$1,-1)+1)+1) -> 31 | BN26: =ROUND(IF($Z26="",$T26,$Z26)*(BM26/IF($W26="",$Q26,$W26)),2) -> 5468.4 | BO26: =+ROUND(BN26*0.1,2) -> 546.84 | BP26: =+SUM(BN26:BO26) -> 6015.24 | BR26: =MAX(0,MIN(IF($Y26<>"",$Y26,$S26),BR$1)-MAX($R26,EOMONTH(BR$1,-1)+1)+1) -> 30 | BS26: =ROUND(IF($Z26="",$T26,$Z26)*(BR26/IF($W26="",$Q26,$W26)),2) -> 5292 | BT26: =+ROUND(BS26*0.1,2) -> 529.2 | BU26: =+SUM(BS26:BT26) -> 5821.2 | BW26: =MAX(0,MIN(IF($Y26<>"",$Y26,$S26),BW$1)-MAX($R26,EOMONTH(BW$1,-1)+1)+1) -> 29 | BX26: =ROUND(IF($Z26="",$T26,$Z26)*(BW26/IF($W26="",$Q26,$W26)),2) -> 5115.6 | BY26: =+ROUND(BX26*0.1,2) -> 511.56 | BZ26: =+SUM(BX26:BY26) -> 5627.16 | CA26: =+AD26+AI26+AN26+AS26+AX26+BC26+BH26+BM26+BR26+BW26 -> 240 | CB26: =+AE26+AJ26+AO26+AT26+AY26+BD26+BI26+BN26+BS26+BX26 -> 42336 | CC26: =+AF26+AK26+AP26+AU26+AZ26+BE26+BJ26+BO26+BT26+BY26 -> 4233.6 | CD26: =+SUM(CB26:CC26) -> 46569.6 | CE26: =ROUND(IF($Y26<>"",$Z26,$T26)-CB26,2) -> 0 | CF26: =ROUND(IF($Y26<>"",$AA26,$U26)-CC26,2) -> 0 | CG26: IVP CANDARAVE | CH26: Alonso Mario Laura Paniagua | CI26: Gerente | CJ26: 969 494 987 | CK26: Alonso Mario Laura Paniagua | CL26: Memorandum N° 012-2026-USLO-GM/MPC | CM26: 46142 | CN26: 969 494 987
A27: 26 | B27: 51 | C27: TACNA | D27: CANDARAVE | E27: CANDARAVE | F27: TA-504 | G27: EMP. TA-105- SALLACPUJO-BAJAÑAMI-JACHACALA -EMP. TA-103 | H27: 6.517 | I27: AFIRMADO | J27: 735 | K27: 240 | L27: 38320 | M27: 3832 | N27: 42152 | O27: O.S. 000152 | P27: GEDICO CONTRATISTAS GENERALES E.I.R.L | Q27: =+$K27 -> 240 | R27: 46146 | S27: =IF(Q27+R27=0,"",Q27+R27-1) -> 46385 | T27: 38320 | U27: =+ROUND(T27*0.1,2) -> 3832 | V27: =+SUM(T27:U27) -> 42152 | X27: =+$R27 -> 46146 | Y27: =IF(W27>0,X27+W27-1,"") | AA27: =+ROUND(Z27*0.1,2) -> 0 | AB27: =+SUM(Z27:AA27) -> 0 | AD27: =MAX(0,MIN(IF($Y27<>"",$Y27,$S27),AD$1)-MAX($R27,EOMONTH(AD$1,-1)+1)+1) -> 0 | AE27: =ROUND(IF($Z27="",$T27,$Z27)*(AD27/IF($W27="",$Q27,$W27)),2) -> 0 | AF27: =+ROUND(AE27*0.1,2) -> 0 | AG27: =+SUM(AE27:AF27) -> 0 | AI27: =MAX(0,MIN(IF($Y27<>"",$Y27,$S27),AI$1)-MAX($R27,EOMONTH(AI$1,-1)+1)+1) -> 0 | AJ27: =ROUND(IF($Z27="",$T27,$Z27)*(AI27/IF($W27="",$Q27,$W27)),2) -> 0 | AK27: =+ROUND(AJ27*0.1,2) -> 0 | AL27: =+SUM(AJ27:AK27) -> 0 | AN27: =MAX(0,MIN(IF($Y27<>"",$Y27,$S27),AN$1)-MAX($R27,EOMONTH(AN$1,-1)+1)+1) -> 28 | AO27: =ROUND(IF($Z27="",$T27,$Z27)*(AN27/IF($W27="",$Q27,$W27)),2) -> 4470.67 | AP27: =+ROUND(AO27*0.1,2) -> 447.07 | AQ27: =+SUM(AO27:AP27) -> 4917.74 | AS27: =MAX(0,MIN(IF($Y27<>"",$Y27,$S27),AS$1)-MAX($R27,EOMONTH(AS$1,-1)+1)+1) -> 30 | AT27: =ROUND(IF($Z27="",$T27,$Z27)*(AS27/IF($W27="",$Q27,$W27)),2) -> 4790 | AU27: =+ROUND(AT27*0.1,2) -> 479 | AV27: =+SUM(AT27:AU27) -> 5269 | AX27: =MAX(0,MIN(IF($Y27<>"",$Y27,$S27),AX$1)-MAX($R27,EOMONTH(AX$1,-1)+1)+1) -> 31 | AY27: =ROUND(IF($Z27="",$T27,$Z27)*(AX27/IF($W27="",$Q27,$W27)),2) -> 4949.67 | AZ27: =+ROUND(AY27*0.1,2) -> 494.97 | BA27: =+SUM(AY27:AZ27) -> 5444.64 | BC27: =MAX(0,MIN(IF($Y27<>"",$Y27,$S27),BC$1)-MAX($R27,EOMONTH(BC$1,-1)+1)+1) -> 31 | BD27: =ROUND(IF($Z27="",$T27,$Z27)*(BC27/IF($W27="",$Q27,$W27)),2) -> 4949.67 | BE27: =+ROUND(BD27*0.1,2) -> 494.97 | BF27: =+SUM(BD27:BE27) -> 5444.64 | BH27: =MAX(0,MIN(IF($Y27<>"",$Y27,$S27),BH$1)-MAX($R27,EOMONTH(BH$1,-1)+1)+1) -> 30 | BI27: =ROUND(IF($Z27="",$T27,$Z27)*(BH27/IF($W27="",$Q27,$W27)),2) -> 4790 | BJ27: =+ROUND(BI27*0.1,2) -> 479 | BK27: =+SUM(BI27:BJ27) -> 5269 | BM27: =MAX(0,MIN(IF($Y27<>"",$Y27,$S27),BM$1)-MAX($R27,EOMONTH(BM$1,-1)+1)+1) -> 31 | BN27: =ROUND(IF($Z27="",$T27,$Z27)*(BM27/IF($W27="",$Q27,$W27)),2) -> 4949.67 | BO27: =+ROUND(BN27*0.1,2) -> 494.97 | BP27: =+SUM(BN27:BO27) -> 5444.64 | BR27: =MAX(0,MIN(IF($Y27<>"",$Y27,$S27),BR$1)-MAX($R27,EOMONTH(BR$1,-1)+1)+1) -> 30 | BS27: =ROUND(IF($Z27="",$T27,$Z27)*(BR27/IF($W27="",$Q27,$W27)),2) -> 4790 | BT27: =+ROUND(BS27*0.1,2) -> 479 | BU27: =+SUM(BS27:BT27) -> 5269 | BW27: =MAX(0,MIN(IF($Y27<>"",$Y27,$S27),BW$1)-MAX($R27,EOMONTH(BW$1,-1)+1)+1) -> 29 | BX27: =ROUND(IF($Z27="",$T27,$Z27)*(BW27/IF($W27="",$Q27,$W27)),2) -> 4630.33 | BY27: =+ROUND(BX27*0.1,2) -> 463.03 | BZ27: =+SUM(BX27:BY27) -> 5093.36 | CA27: =+AD27+AI27+AN27+AS27+AX27+BC27+BH27+BM27+BR27+BW27 -> 240 | CB27: =+AE27+AJ27+AO27+AT27+AY27+BD27+BI27+BN27+BS27+BX27 -> 38320.01 | CC27: =+AF27+AK27+AP27+AU27+AZ27+BE27+BJ27+BO27+BT27+BY27 -> 3832.01 | CD27: =+SUM(CB27:CC27) -> 42152.02 | CE27: =ROUND(IF($Y27<>"",$Z27,$T27)-CB27,2) -> -0.01 | CF27: =ROUND(IF($Y27<>"",$AA27,$U27)-CC27,2) -> -0.01 | CG27: IVP CANDARAVE | CH27: Alonso Mario Laura Paniagua | CI27: Gerente | CJ27: 969 494 987 | CK27: Alonso Mario Laura Paniagua | CL27: Memorandum N° 012-2026-USLO-GM/MPC | CM27: 46142 | CN27: 969 494 987
A28: 27 | B28: 52 | C28: TACNA | D28: JORGE BASADRE | E28: LOCUMBA | F28: TA-573 | G28: CINTO (KM 15+173) - MATOGROSO - PTA. CARRETERA (KM 18+714) | H28: 3.541 | I28: AFIRMADO | J28: 735 | K28: 250 | L28: 21688 | M28: 2170 | N28: 23858 | O28: 001-2026-IVPMJB | P28: AVCOC EIRL | Q28: =+$K28 -> 250 | R28: 46099 | S28: =IF(Q28+R28=0,"",Q28+R28-1) -> 46348 | T28: 21688 | U28: =+ROUND(T28*0.1,2) -> 2168.8 | V28: =+SUM(T28:U28) -> 23856.8 | X28: =+$R28 -> 46099 | Y28: =IF(W28>0,X28+W28-1,"") | AA28: =+ROUND(Z28*0.1,2) -> 0 | AB28: =+SUM(Z28:AA28) -> 0 | AD28: =MAX(0,MIN(IF($Y28<>"",$Y28,$S28),AD$1)-MAX($R28,EOMONTH(AD$1,-1)+1)+1) -> 14 | AE28: =ROUND(IF($Z28="",$T28,$Z28)*(AD28/IF($W28="",$Q28,$W28)),2) -> 1214.53 | AF28: =+ROUND(AE28*0.1,2) -> 121.45 | AG28: =+SUM(AE28:AF28) -> 1335.98 | AI28: =MAX(0,MIN(IF($Y28<>"",$Y28,$S28),AI$1)-MAX($R28,EOMONTH(AI$1,-1)+1)+1) -> 30 | AJ28: =ROUND(IF($Z28="",$T28,$Z28)*(AI28/IF($W28="",$Q28,$W28)),2) -> 2602.56 | AK28: =+ROUND(AJ28*0.1,2) -> 260.26 | AL28: =+SUM(AJ28:AK28) -> 2862.82 | AN28: =MAX(0,MIN(IF($Y28<>"",$Y28,$S28),AN$1)-MAX($R28,EOMONTH(AN$1,-1)+1)+1) -> 31 | AO28: =ROUND(IF($Z28="",$T28,$Z28)*(AN28/IF($W28="",$Q28,$W28)),2) -> 2689.31 | AP28: =+ROUND(AO28*0.1,2) -> 268.93 | AQ28: =+SUM(AO28:AP28) -> 2958.24 | AS28: =MAX(0,MIN(IF($Y28<>"",$Y28,$S28),AS$1)-MAX($R28,EOMONTH(AS$1,-1)+1)+1) -> 30 | AT28: =ROUND(IF($Z28="",$T28,$Z28)*(AS28/IF($W28="",$Q28,$W28)),2) -> 2602.56 | AU28: =+ROUND(AT28*0.1,2) -> 260.26 | AV28: =+SUM(AT28:AU28) -> 2862.82 | AX28: =MAX(0,MIN(IF($Y28<>"",$Y28,$S28),AX$1)-MAX($R28,EOMONTH(AX$1,-1)+1)+1) -> 31 | AY28: =ROUND(IF($Z28="",$T28,$Z28)*(AX28/IF($W28="",$Q28,$W28)),2) -> 2689.31 | AZ28: =+ROUND(AY28*0.1,2) -> 268.93 | BA28: =+SUM(AY28:AZ28) -> 2958.24 | BC28: =MAX(0,MIN(IF($Y28<>"",$Y28,$S28),BC$1)-MAX($R28,EOMONTH(BC$1,-1)+1)+1) -> 31 | BD28: =ROUND(IF($Z28="",$T28,$Z28)*(BC28/IF($W28="",$Q28,$W28)),2) -> 2689.31 | BE28: =+ROUND(BD28*0.1,2) -> 268.93 | BF28: =+SUM(BD28:BE28) -> 2958.24 | BH28: =MAX(0,MIN(IF($Y28<>"",$Y28,$S28),BH$1)-MAX($R28,EOMONTH(BH$1,-1)+1)+1) -> 30 | BI28: =ROUND(IF($Z28="",$T28,$Z28)*(BH28/IF($W28="",$Q28,$W28)),2) -> 2602.56 | BJ28: =+ROUND(BI28*0.1,2) -> 260.26 | BK28: =+SUM(BI28:BJ28) -> 2862.82 | BM28: =MAX(0,MIN(IF($Y28<>"",$Y28,$S28),BM$1)-MAX($R28,EOMONTH(BM$1,-1)+1)+1) -> 31 | BN28: =ROUND(IF($Z28="",$T28,$Z28)*(BM28/IF($W28="",$Q28,$W28)),2) -> 2689.31 | BO28: =+ROUND(BN28*0.1,2) -> 268.93 | BP28: =+SUM(BN28:BO28) -> 2958.24 | BR28: =MAX(0,MIN(IF($Y28<>"",$Y28,$S28),BR$1)-MAX($R28,EOMONTH(BR$1,-1)+1)+1) -> 22 | BS28: =ROUND(IF($Z28="",$T28,$Z28)*(BR28/IF($W28="",$Q28,$W28)),2) -> 1908.54 | BT28: =+ROUND(BS28*0.1,2) -> 190.85 | BU28: =+SUM(BS28:BT28) -> 2099.39 | BW28: =MAX(0,MIN(IF($Y28<>"",$Y28,$S28),BW$1)-MAX($R28,EOMONTH(BW$1,-1)+1)+1) -> 0 | BX28: =ROUND(IF($Z28="",$T28,$Z28)*(BW28/IF($W28="",$Q28,$W28)),2) -> 0 | BY28: =+ROUND(BX28*0.1,2) -> 0 | BZ28: =+SUM(BX28:BY28) -> 0 | CA28: =+AD28+AI28+AN28+AS28+AX28+BC28+BH28+BM28+BR28+BW28 -> 250 | CB28: =+AE28+AJ28+AO28+AT28+AY28+BD28+BI28+BN28+BS28+BX28 -> 21687.99 | CC28: =+AF28+AK28+AP28+AU28+AZ28+BE28+BJ28+BO28+BT28+BY28 -> 2168.8 | CD28: =+SUM(CB28:CC28) -> 23856.79 | CE28: =ROUND(IF($Y28<>"",$Z28,$T28)-CB28,2) -> 0.01 | CF28: =ROUND(IF($Y28<>"",$AA28,$U28)-CC28,2) -> 0 | CG28: IVP JORGE BASADRE | CH28: Walter Vidal Quispe Cutipa | CI28: Gerente | CJ28: 930 925 020 | CK28: Walter Vidal Quispe Cutipa | CL28: Memorándum N° 017-2026-CGG-G.G./IVPM-JB | CM28: 46098 | CN28: 930 925 020
A29: 28 | B29: 52 | C29: TACNA | D29: JORGE BASADRE | E29: LOCUMBA | F29: TA-578 | G29: EMP. PE-1S - LA AURORA - PTA. CARRETERA (KM 02+984) | H29: 2.984 | I29: AFIRMADO | J29: 735 | K29: 263 | L29: 19227 | M29: 1924 | N29: 21151 | O29: 002-2026-IVPMJB | P29: DARLY ROXANA COTRINA SANTISTEBAN | Q29: =+$K29 -> 263 | R29: 46099 | S29: =IF(Q29+R29=0,"",Q29+R29-1) -> 46361 | T29: 19227 | U29: =+ROUND(T29*0.1,2) -> 1922.7 | V29: =+SUM(T29:U29) -> 21149.7 | X29: =+$R29 -> 46099 | Y29: =IF(W29>0,X29+W29-1,"") | AA29: =+ROUND(Z29*0.1,2) -> 0 | AB29: =+SUM(Z29:AA29) -> 0 | AD29: =MAX(0,MIN(IF($Y29<>"",$Y29,$S29),AD$1)-MAX($R29,EOMONTH(AD$1,-1)+1)+1) -> 14 | AE29: =ROUND(IF($Z29="",$T29,$Z29)*(AD29/IF($W29="",$Q29,$W29)),2) -> 1023.49 | AF29: =+ROUND(AE29*0.1,2) -> 102.35 | AG29: =+SUM(AE29:AF29) -> 1125.84 | AI29: =MAX(0,MIN(IF($Y29<>"",$Y29,$S29),AI$1)-MAX($R29,EOMONTH(AI$1,-1)+1)+1) -> 30 | AJ29: =ROUND(IF($Z29="",$T29,$Z29)*(AI29/IF($W29="",$Q29,$W29)),2) -> 2193.19 | AK29: =+ROUND(AJ29*0.1,2) -> 219.32 | AL29: =+SUM(AJ29:AK29) -> 2412.51 | AN29: =MAX(0,MIN(IF($Y29<>"",$Y29,$S29),AN$1)-MAX($R29,EOMONTH(AN$1,-1)+1)+1) -> 31 | AO29: =ROUND(IF($Z29="",$T29,$Z29)*(AN29/IF($W29="",$Q29,$W29)),2) -> 2266.3 | AP29: =+ROUND(AO29*0.1,2) -> 226.63 | AQ29: =+SUM(AO29:AP29) -> 2492.93 | AS29: =MAX(0,MIN(IF($Y29<>"",$Y29,$S29),AS$1)-MAX($R29,EOMONTH(AS$1,-1)+1)+1) -> 30 | AT29: =ROUND(IF($Z29="",$T29,$Z29)*(AS29/IF($W29="",$Q29,$W29)),2) -> 2193.19 | AU29: =+ROUND(AT29*0.1,2) -> 219.32 | AV29: =+SUM(AT29:AU29) -> 2412.51 | AX29: =MAX(0,MIN(IF($Y29<>"",$Y29,$S29),AX$1)-MAX($R29,EOMONTH(AX$1,-1)+1)+1) -> 31 | AY29: =ROUND(IF($Z29="",$T29,$Z29)*(AX29/IF($W29="",$Q29,$W29)),2) -> 2266.3 | AZ29: =+ROUND(AY29*0.1,2) -> 226.63 | BA29: =+SUM(AY29:AZ29) -> 2492.93 | BC29: =MAX(0,MIN(IF($Y29<>"",$Y29,$S29),BC$1)-MAX($R29,EOMONTH(BC$1,-1)+1)+1) -> 31 | BD29: =ROUND(IF($Z29="",$T29,$Z29)*(BC29/IF($W29="",$Q29,$W29)),2) -> 2266.3 | BE29: =+ROUND(BD29*0.1,2) -> 226.63 | BF29: =+SUM(BD29:BE29) -> 2492.93 | BH29: =MAX(0,MIN(IF($Y29<>"",$Y29,$S29),BH$1)-MAX($R29,EOMONTH(BH$1,-1)+1)+1) -> 30 | BI29: =ROUND(IF($Z29="",$T29,$Z29)*(BH29/IF($W29="",$Q29,$W29)),2) -> 2193.19 | BJ29: =+ROUND(BI29*0.1,2) -> 219.32 | BK29: =+SUM(BI29:BJ29) -> 2412.51 | BM29: =MAX(0,MIN(IF($Y29<>"",$Y29,$S29),BM$1)-MAX($R29,EOMONTH(BM$1,-1)+1)+1) -> 31 | BN29: =ROUND(IF($Z29="",$T29,$Z29)*(BM29/IF($W29="",$Q29,$W29)),2) -> 2266.3 | BO29: =+ROUND(BN29*0.1,2) -> 226.63 | BP29: =+SUM(BN29:BO29) -> 2492.93 | BR29: =MAX(0,MIN(IF($Y29<>"",$Y29,$S29),BR$1)-MAX($R29,EOMONTH(BR$1,-1)+1)+1) -> 30 | BS29: =ROUND(IF($Z29="",$T29,$Z29)*(BR29/IF($W29="",$Q29,$W29)),2) -> 2193.19 | BT29: =+ROUND(BS29*0.1,2) -> 219.32 | BU29: =+SUM(BS29:BT29) -> 2412.51 | BW29: =MAX(0,MIN(IF($Y29<>"",$Y29,$S29),BW$1)-MAX($R29,EOMONTH(BW$1,-1)+1)+1) -> 5 | BX29: =ROUND(IF($Z29="",$T29,$Z29)*(BW29/IF($W29="",$Q29,$W29)),2) -> 365.53 | BY29: =+ROUND(BX29*0.1,2) -> 36.55 | BZ29: =+SUM(BX29:BY29) -> 402.08 | CA29: =+AD29+AI29+AN29+AS29+AX29+BC29+BH29+BM29+BR29+BW29 -> 263 | CB29: =+AE29+AJ29+AO29+AT29+AY29+BD29+BI29+BN29+BS29+BX29 -> 19226.98 | CC29: =+AF29+AK29+AP29+AU29+AZ29+BE29+BJ29+BO29+BT29+BY29 -> 1922.7 | CD29: =+SUM(CB29:CC29) -> 21149.68 | CE29: =ROUND(IF($Y29<>"",$Z29,$T29)-CB29,2) -> 0.02 | CF29: =ROUND(IF($Y29<>"",$AA29,$U29)-CC29,2) -> 0 | CG29: IVP JORGE BASADRE | CH29: Walter Vidal Quispe Cutipa | CI29: Gerente | CJ29: 930 925 020 | CK29: Walter Vidal Quispe Cutipa | CL29: Memorándum N° 017-2026-CGG-G.G./IVPM-JB | CM29: 46098 | CN29: 930 925 020
A30: 29 | B30: 52 | C30: TACNA | D30: JORGE BASADRE | E30: ILABAYA | F30: TA-572 | G30: EMP. TA-109 (OCONCHAY) - EMP. R230302 (KM 08+202) | H30: 8.203 | I30: AFIRMADO | J30: 735 | K30: 270 | L30: 54262 | M30: 5427 | N30: 59689 | O30: 010-2026-IVPMJB | P30: AVCOC EIRL | Q30: =+$K30 -> 270 | R30: 46167 | S30: =IF(Q30+R30=0,"",Q30+R30-1) -> 46436 | T30: 54262 | U30: =+ROUND(T30*0.1,2) -> 5426.2 | V30: =+SUM(T30:U30) -> 59688.2 | W30: 213 | X30: =+$R30 -> 46167 | Y30: =IF(W30>0,X30+W30-1,"") -> 46379 | Z30: 42806.69 | AA30: =+ROUND(Z30*0.1,2) -> 4280.67 | AB30: =+SUM(Z30:AA30) -> 47087.36 | AD30: =MAX(0,MIN(IF($Y30<>"",$Y30,$S30),AD$1)-MAX($R30,EOMONTH(AD$1,-1)+1)+1) -> 0 | AE30: =ROUND(IF($Z30="",$T30,$Z30)*(AD30/IF($W30="",$Q30,$W30)),2) -> 0 | AF30: =+ROUND(AE30*0.1,2) -> 0 | AG30: =+SUM(AE30:AF30) -> 0 | AI30: =MAX(0,MIN(IF($Y30<>"",$Y30,$S30),AI$1)-MAX($R30,EOMONTH(AI$1,-1)+1)+1) -> 0 | AJ30: =ROUND(IF($Z30="",$T30,$Z30)*(AI30/IF($W30="",$Q30,$W30)),2) -> 0 | AK30: =+ROUND(AJ30*0.1,2) -> 0 | AL30: =+SUM(AJ30:AK30) -> 0 | AN30: =MAX(0,MIN(IF($Y30<>"",$Y30,$S30),AN$1)-MAX($R30,EOMONTH(AN$1,-1)+1)+1) -> 7 | AO30: =ROUND(IF($Z30="",$T30,$Z30)*(AN30/IF($W30="",$Q30,$W30)),2) -> 1406.79 | AP30: =+ROUND(AO30*0.1,2) -> 140.68 | AQ30: =+SUM(AO30:AP30) -> 1547.47 | AS30: =MAX(0,MIN(IF($Y30<>"",$Y30,$S30),AS$1)-MAX($R30,EOMONTH(AS$1,-1)+1)+1) -> 30 | AT30: =ROUND(IF($Z30="",$T30,$Z30)*(AS30/IF($W30="",$Q30,$W30)),2) -> 6029.11 | AU30: =+ROUND(AT30*0.1,2) -> 602.91 | AV30: =+SUM(AT30:AU30) -> 6632.02 | AX30: =MAX(0,MIN(IF($Y30<>"",$Y30,$S30),AX$1)-MAX($R30,EOMONTH(AX$1,-1)+1)+1) -> 31 | AY30: =ROUND(IF($Z30="",$T30,$Z30)*(AX30/IF($W30="",$Q30,$W30)),2) -> 6230.08 | AZ30: =+ROUND(AY30*0.1,2) -> 623.01 | BA30: =+SUM(AY30:AZ30) -> 6853.09 | BC30: =MAX(0,MIN(IF($Y30<>"",$Y30,$S30),BC$1)-MAX($R30,EOMONTH(BC$1,-1)+1)+1) -> 31 | BD30: =ROUND(IF($Z30="",$T30,$Z30)*(BC30/IF($W30="",$Q30,$W30)),2) -> 6230.08 | BE30: =+ROUND(BD30*0.1,2) -> 623.01 | BF30: =+SUM(BD30:BE30) -> 6853.09 | BH30: =MAX(0,MIN(IF($Y30<>"",$Y30,$S30),BH$1)-MAX($R30,EOMONTH(BH$1,-1)+1)+1) -> 30 | BI30: =ROUND(IF($Z30="",$T30,$Z30)*(BH30/IF($W30="",$Q30,$W30)),2) -> 6029.11 | BJ30: =+ROUND(BI30*0.1,2) -> 602.91 | BK30: =+SUM(BI30:BJ30) -> 6632.02 | BM30: =MAX(0,MIN(IF($Y30<>"",$Y30,$S30),BM$1)-MAX($R30,EOMONTH(BM$1,-1)+1)+1) -> 31 | BN30: =ROUND(IF($Z30="",$T30,$Z30)*(BM30/IF($W30="",$Q30,$W30)),2) -> 6230.08 | BO30: =+ROUND(BN30*0.1,2) -> 623.01 | BP30: =+SUM(BN30:BO30) -> 6853.09 | BR30: =MAX(0,MIN(IF($Y30<>"",$Y30,$S30),BR$1)-MAX($R30,EOMONTH(BR$1,-1)+1)+1) -> 30 | BS30: =ROUND(IF($Z30="",$T30,$Z30)*(BR30/IF($W30="",$Q30,$W30)),2) -> 6029.11 | BT30: =+ROUND(BS30*0.1,2) -> 602.91 | BU30: =+SUM(BS30:BT30) -> 6632.02 | BW30: =MAX(0,MIN(IF($Y30<>"",$Y30,$S30),BW$1)-MAX($R30,EOMONTH(BW$1,-1)+1)+1) -> 23 | BX30: =ROUND(IF($Z30="",$T30,$Z30)*(BW30/IF($W30="",$Q30,$W30)),2) -> 4622.32 | BY30: =+ROUND(BX30*0.1,2) -> 462.23 | BZ30: =+SUM(BX30:BY30) -> 5084.55 | CA30: =+AD30+AI30+AN30+AS30+AX30+BC30+BH30+BM30+BR30+BW30 -> 213 | CB30: =+AE30+AJ30+AO30+AT30+AY30+BD30+BI30+BN30+BS30+BX30 -> 42806.68 | CC30: =+AF30+AK30+AP30+AU30+AZ30+BE30+BJ30+BO30+BT30+BY30 -> 4280.67 | CD30: =+SUM(CB30:CC30) -> 47087.35 | CE30: =ROUND(IF($Y30<>"",$Z30,$T30)-CB30,2) -> 0.01 | CF30: =ROUND(IF($Y30<>"",$AA30,$U30)-CC30,2) -> 0 | CG30: IVP JORGE BASADRE | CH30: Walter Vidal Quispe Cutipa | CI30: Gerente | CJ30: 930 925 020 | CK30: Walter Vidal Quispe Cutipa | CL30: Memorándum N° 017-2026-CGG-G.G./IVPM-JB | CM30: 46098 | CN30: 930 925 020
A31: 30 | B31: 52 | C31: TACNA | D31: JORGE BASADRE | E31: LOCUMBA ILABAYA | F31: R230302 | G31: EMP.TA-572 - EMP.R230305 (KM 06+742) | H31: 6.742 | I31: AFIRMADO | J31: 735 | K31: 245 | L31: 40468 | M31: 4048 | N31: 44516 | O31: 003-2026-IVPMJB | P31: AVCOC EIRL | Q31: =+$K31 -> 245 | R31: 46099 | S31: =IF(Q31+R31=0,"",Q31+R31-1) -> 46343 | T31: 40468 | U31: =+ROUND(T31*0.1,2) -> 4046.8 | V31: =+SUM(T31:U31) -> 44514.8 | X31: =+$R31 -> 46099 | Y31: =IF(W31>0,X31+W31-1,"") | AA31: =+ROUND(Z31*0.1,2) -> 0 | AB31: =+SUM(Z31:AA31) -> 0 | AD31: =MAX(0,MIN(IF($Y31<>"",$Y31,$S31),AD$1)-MAX($R31,EOMONTH(AD$1,-1)+1)+1) -> 14 | AE31: =ROUND(IF($Z31="",$T31,$Z31)*(AD31/IF($W31="",$Q31,$W31)),2) -> 2312.46 | AF31: =+ROUND(AE31*0.1,2) -> 231.25 | AG31: =+SUM(AE31:AF31) -> 2543.71 | AI31: =MAX(0,MIN(IF($Y31<>"",$Y31,$S31),AI$1)-MAX($R31,EOMONTH(AI$1,-1)+1)+1) -> 30 | AJ31: =ROUND(IF($Z31="",$T31,$Z31)*(AI31/IF($W31="",$Q31,$W31)),2) -> 4955.27 | AK31: =+ROUND(AJ31*0.1,2) -> 495.53 | AL31: =+SUM(AJ31:AK31) -> 5450.8 | AN31: =MAX(0,MIN(IF($Y31<>"",$Y31,$S31),AN$1)-MAX($R31,EOMONTH(AN$1,-1)+1)+1) -> 31 | AO31: =ROUND(IF($Z31="",$T31,$Z31)*(AN31/IF($W31="",$Q31,$W31)),2) -> 5120.44 | AP31: =+ROUND(AO31*0.1,2) -> 512.04 | AQ31: =+SUM(AO31:AP31) -> 5632.48 | AS31: =MAX(0,MIN(IF($Y31<>"",$Y31,$S31),AS$1)-MAX($R31,EOMONTH(AS$1,-1)+1)+1) -> 30 | AT31: =ROUND(IF($Z31="",$T31,$Z31)*(AS31/IF($W31="",$Q31,$W31)),2) -> 4955.27 | AU31: =+ROUND(AT31*0.1,2) -> 495.53 | AV31: =+SUM(AT31:AU31) -> 5450.8 | AX31: =MAX(0,MIN(IF($Y31<>"",$Y31,$S31),AX$1)-MAX($R31,EOMONTH(AX$1,-1)+1)+1) -> 31 | AY31: =ROUND(IF($Z31="",$T31,$Z31)*(AX31/IF($W31="",$Q31,$W31)),2) -> 5120.44 | AZ31: =+ROUND(AY31*0.1,2) -> 512.04 | BA31: =+SUM(AY31:AZ31) -> 5632.48 | BC31: =MAX(0,MIN(IF($Y31<>"",$Y31,$S31),BC$1)-MAX($R31,EOMONTH(BC$1,-1)+1)+1) -> 31 | BD31: =ROUND(IF($Z31="",$T31,$Z31)*(BC31/IF($W31="",$Q31,$W31)),2) -> 5120.44 | BE31: =+ROUND(BD31*0.1,2) -> 512.04 | BF31: =+SUM(BD31:BE31) -> 5632.48 | BH31: =MAX(0,MIN(IF($Y31<>"",$Y31,$S31),BH$1)-MAX($R31,EOMONTH(BH$1,-1)+1)+1) -> 30 | BI31: =ROUND(IF($Z31="",$T31,$Z31)*(BH31/IF($W31="",$Q31,$W31)),2) -> 4955.27 | BJ31: =+ROUND(BI31*0.1,2) -> 495.53 | BK31: =+SUM(BI31:BJ31) -> 5450.8 | BM31: =MAX(0,MIN(IF($Y31<>"",$Y31,$S31),BM$1)-MAX($R31,EOMONTH(BM$1,-1)+1)+1) -> 31 | BN31: =ROUND(IF($Z31="",$T31,$Z31)*(BM31/IF($W31="",$Q31,$W31)),2) -> 5120.44 | BO31: =+ROUND(BN31*0.1,2) -> 512.04 | BP31: =+SUM(BN31:BO31) -> 5632.48 | BR31: =MAX(0,MIN(IF($Y31<>"",$Y31,$S31),BR$1)-MAX($R31,EOMONTH(BR$1,-1)+1)+1) -> 17 | BS31: =ROUND(IF($Z31="",$T31,$Z31)*(BR31/IF($W31="",$Q31,$W31)),2) -> 2807.98 | BT31: =+ROUND(BS31*0.1,2) -> 280.8 | BU31: =+SUM(BS31:BT31) -> 3088.78 | BW31: =MAX(0,MIN(IF($Y31<>"",$Y31,$S31),BW$1)-MAX($R31,EOMONTH(BW$1,-1)+1)+1) -> 0 | BX31: =ROUND(IF($Z31="",$T31,$Z31)*(BW31/IF($W31="",$Q31,$W31)),2) -> 0 | BY31: =+ROUND(BX31*0.1,2) -> 0 | BZ31: =+SUM(BX31:BY31) -> 0 | CA31: =+AD31+AI31+AN31+AS31+AX31+BC31+BH31+BM31+BR31+BW31 -> 245 | CB31: =+AE31+AJ31+AO31+AT31+AY31+BD31+BI31+BN31+BS31+BX31 -> 40468.01 | CC31: =+AF31+AK31+AP31+AU31+AZ31+BE31+BJ31+BO31+BT31+BY31 -> 4046.8 | CD31: =+SUM(CB31:CC31) -> 44514.81 | CE31: =ROUND(IF($Y31<>"",$Z31,$T31)-CB31,2) -> -0.01 | CF31: =ROUND(IF($Y31<>"",$AA31,$U31)-CC31,2) -> 0 | CG31: IVP JORGE BASADRE | CH31: Walter Vidal Quispe Cutipa | CI31: Gerente | CJ31: 930 925 020 | CK31: Walter Vidal Quispe Cutipa | CL31: Memorándum N° 017-2026-CGG-G.G./IVPM-JB | CM31: 46098 | CN31: 930 925 020
A32: 31 | B32: 52 | C32: TACNA | D32: JORGE BASADRE | E32: LOCUMBA | F32: TA-575 | G32: EMP. TA-109 - CUAYLATA - EMP. TA-109 (DV. CHIPE) | H32: 6.49 | I32: AFIRMADO | J32: 735 | K32: 240 | L32: 38161 | M32: 3817 | N32: 41978 | O32: 004-2026-IVPMJB | P32: AVCOC EIRL | Q32: =+$K32 -> 240 | R32: 46099 | S32: =IF(Q32+R32=0,"",Q32+R32-1) -> 46338 | T32: 38161 | U32: =+ROUND(T32*0.1,2) -> 3816.1 | V32: =+SUM(T32:U32) -> 41977.1 | X32: =+$R32 -> 46099 | Y32: =IF(W32>0,X32+W32-1,"") | AA32: =+ROUND(Z32*0.1,2) -> 0 | AB32: =+SUM(Z32:AA32) -> 0 | AD32: =MAX(0,MIN(IF($Y32<>"",$Y32,$S32),AD$1)-MAX($R32,EOMONTH(AD$1,-1)+1)+1) -> 14 | AE32: =ROUND(IF($Z32="",$T32,$Z32)*(AD32/IF($W32="",$Q32,$W32)),2) -> 2226.06 | AF32: =+ROUND(AE32*0.1,2) -> 222.61 | AG32: =+SUM(AE32:AF32) -> 2448.67 | AI32: =MAX(0,MIN(IF($Y32<>"",$Y32,$S32),AI$1)-MAX($R32,EOMONTH(AI$1,-1)+1)+1) -> 30 | AJ32: =ROUND(IF($Z32="",$T32,$Z32)*(AI32/IF($W32="",$Q32,$W32)),2) -> 4770.13 | AK32: =+ROUND(AJ32*0.1,2) -> 477.01 | AL32: =+SUM(AJ32:AK32) -> 5247.14 | AN32: =MAX(0,MIN(IF($Y32<>"",$Y32,$S32),AN$1)-MAX($R32,EOMONTH(AN$1,-1)+1)+1) -> 31 | AO32: =ROUND(IF($Z32="",$T32,$Z32)*(AN32/IF($W32="",$Q32,$W32)),2) -> 4929.13 | AP32: =+ROUND(AO32*0.1,2) -> 492.91 | AQ32: =+SUM(AO32:AP32) -> 5422.04 | AS32: =MAX(0,MIN(IF($Y32<>"",$Y32,$S32),AS$1)-MAX($R32,EOMONTH(AS$1,-1)+1)+1) -> 30 | AT32: =ROUND(IF($Z32="",$T32,$Z32)*(AS32/IF($W32="",$Q32,$W32)),2) -> 4770.13 | AU32: =+ROUND(AT32*0.1,2) -> 477.01 | AV32: =+SUM(AT32:AU32) -> 5247.14 | AX32: =MAX(0,MIN(IF($Y32<>"",$Y32,$S32),AX$1)-MAX($R32,EOMONTH(AX$1,-1)+1)+1) -> 31 | AY32: =ROUND(IF($Z32="",$T32,$Z32)*(AX32/IF($W32="",$Q32,$W32)),2) -> 4929.13 | AZ32: =+ROUND(AY32*0.1,2) -> 492.91 | BA32: =+SUM(AY32:AZ32) -> 5422.04 | BC32: =MAX(0,MIN(IF($Y32<>"",$Y32,$S32),BC$1)-MAX($R32,EOMONTH(BC$1,-1)+1)+1) -> 31 | BD32: =ROUND(IF($Z32="",$T32,$Z32)*(BC32/IF($W32="",$Q32,$W32)),2) -> 4929.13 | BE32: =+ROUND(BD32*0.1,2) -> 492.91 | BF32: =+SUM(BD32:BE32) -> 5422.04 | BH32: =MAX(0,MIN(IF($Y32<>"",$Y32,$S32),BH$1)-MAX($R32,EOMONTH(BH$1,-1)+1)+1) -> 30 | BI32: =ROUND(IF($Z32="",$T32,$Z32)*(BH32/IF($W32="",$Q32,$W32)),2) -> 4770.13 | BJ32: =+ROUND(BI32*0.1,2) -> 477.01 | BK32: =+SUM(BI32:BJ32) -> 5247.14 | BM32: =MAX(0,MIN(IF($Y32<>"",$Y32,$S32),BM$1)-MAX($R32,EOMONTH(BM$1,-1)+1)+1) -> 31 | BN32: =ROUND(IF($Z32="",$T32,$Z32)*(BM32/IF($W32="",$Q32,$W32)),2) -> 4929.13 | BO32: =+ROUND(BN32*0.1,2) -> 492.91 | BP32: =+SUM(BN32:BO32) -> 5422.04 | BR32: =MAX(0,MIN(IF($Y32<>"",$Y32,$S32),BR$1)-MAX($R32,EOMONTH(BR$1,-1)+1)+1) -> 12 | BS32: =ROUND(IF($Z32="",$T32,$Z32)*(BR32/IF($W32="",$Q32,$W32)),2) -> 1908.05 | BT32: =+ROUND(BS32*0.1,2) -> 190.81 | BU32: =+SUM(BS32:BT32) -> 2098.86 | BW32: =MAX(0,MIN(IF($Y32<>"",$Y32,$S32),BW$1)-MAX($R32,EOMONTH(BW$1,-1)+1)+1) -> 0 | BX32: =ROUND(IF($Z32="",$T32,$Z32)*(BW32/IF($W32="",$Q32,$W32)),2) -> 0 | BY32: =+ROUND(BX32*0.1,2) -> 0 | BZ32: =+SUM(BX32:BY32) -> 0 | CA32: =+AD32+AI32+AN32+AS32+AX32+BC32+BH32+BM32+BR32+BW32 -> 240 | CB32: =+AE32+AJ32+AO32+AT32+AY32+BD32+BI32+BN32+BS32+BX32 -> 38161.02 | CC32: =+AF32+AK32+AP32+AU32+AZ32+BE32+BJ32+BO32+BT32+BY32 -> 3816.09 | CD32: =+SUM(CB32:CC32) -> 41977.11 | CE32: =ROUND(IF($Y32<>"",$Z32,$T32)-CB32,2) -> -0.02 | CF32: =ROUND(IF($Y32<>"",$AA32,$U32)-CC32,2) -> 0.01 | CG32: IVP JORGE BASADRE | CH32: Walter Vidal Quispe Cutipa | CI32: Gerente | CJ32: 930 925 020 | CK32: Walter Vidal Quispe Cutipa | CL32: Memorándum N° 017-2026-CGG-G.G./IVPM-JB | CM32: 46098 | CN32: 930 925 020
A33: 32 | B33: 52 | C33: TACNA | D33: JORGE BASADRE | E33: LOCUMBA | F33: TA-574 | G33: EMP. TA-109 (SAGOLLO) - EMP. TA-573 (DV. PTE CINTO) | H33: 6.98 | I33: AFIRMADO | J33: 735 | K33: 240 | L33: 41042 | M33: 4105 | N33: 45147 | O33: 005-2026-IVPMJB | P33: AVCOC EIRL | Q33: =+$K33 -> 240 | R33: 46099 | S33: =IF(Q33+R33=0,"",Q33+R33-1) -> 46338 | T33: 41042 | U33: =+ROUND(T33*0.1,2) -> 4104.2 | V33: =+SUM(T33:U33) -> 45146.2 | X33: =+$R33 -> 46099 | Y33: =IF(W33>0,X33+W33-1,"") | AA33: =+ROUND(Z33*0.1,2) -> 0 | AB33: =+SUM(Z33:AA33) -> 0 | AD33: =MAX(0,MIN(IF($Y33<>"",$Y33,$S33),AD$1)-MAX($R33,EOMONTH(AD$1,-1)+1)+1) -> 14 | AE33: =ROUND(IF($Z33="",$T33,$Z33)*(AD33/IF($W33="",$Q33,$W33)),2) -> 2394.12 | AF33: =+ROUND(AE33*0.1,2) -> 239.41 | AG33: =+SUM(AE33:AF33) -> 2633.53 | AI33: =MAX(0,MIN(IF($Y33<>"",$Y33,$S33),AI$1)-MAX($R33,EOMONTH(AI$1,-1)+1)+1) -> 30 | AJ33: =ROUND(IF($Z33="",$T33,$Z33)*(AI33/IF($W33="",$Q33,$W33)),2) -> 5130.25 | AK33: =+ROUND(AJ33*0.1,2) -> 513.03 | AL33: =+SUM(AJ33:AK33) -> 5643.28 | AN33: =MAX(0,MIN(IF($Y33<>"",$Y33,$S33),AN$1)-MAX($R33,EOMONTH(AN$1,-1)+1)+1) -> 31 | AO33: =ROUND(IF($Z33="",$T33,$Z33)*(AN33/IF($W33="",$Q33,$W33)),2) -> 5301.26 | AP33: =+ROUND(AO33*0.1,2) -> 530.13 | AQ33: =+SUM(AO33:AP33) -> 5831.39 | AS33: =MAX(0,MIN(IF($Y33<>"",$Y33,$S33),AS$1)-MAX($R33,EOMONTH(AS$1,-1)+1)+1) -> 30 | AT33: =ROUND(IF($Z33="",$T33,$Z33)*(AS33/IF($W33="",$Q33,$W33)),2) -> 5130.25 | AU33: =+ROUND(AT33*0.1,2) -> 513.03 | AV33: =+SUM(AT33:AU33) -> 5643.28 | AX33: =MAX(0,MIN(IF($Y33<>"",$Y33,$S33),AX$1)-MAX($R33,EOMONTH(AX$1,-1)+1)+1) -> 31 | AY33: =ROUND(IF($Z33="",$T33,$Z33)*(AX33/IF($W33="",$Q33,$W33)),2) -> 5301.26 | AZ33: =+ROUND(AY33*0.1,2) -> 530.13 | BA33: =+SUM(AY33:AZ33) -> 5831.39 | BC33: =MAX(0,MIN(IF($Y33<>"",$Y33,$S33),BC$1)-MAX($R33,EOMONTH(BC$1,-1)+1)+1) -> 31 | BD33: =ROUND(IF($Z33="",$T33,$Z33)*(BC33/IF($W33="",$Q33,$W33)),2) -> 5301.26 | BE33: =+ROUND(BD33*0.1,2) -> 530.13 | BF33: =+SUM(BD33:BE33) -> 5831.39 | BH33: =MAX(0,MIN(IF($Y33<>"",$Y33,$S33),BH$1)-MAX($R33,EOMONTH(BH$1,-1)+1)+1) -> 30 | BI33: =ROUND(IF($Z33="",$T33,$Z33)*(BH33/IF($W33="",$Q33,$W33)),2) -> 5130.25 | BJ33: =+ROUND(BI33*0.1,2) -> 513.03 | BK33: =+SUM(BI33:BJ33) -> 5643.28 | BM33: =MAX(0,MIN(IF($Y33<>"",$Y33,$S33),BM$1)-MAX($R33,EOMONTH(BM$1,-1)+1)+1) -> 31 | BN33: =ROUND(IF($Z33="",$T33,$Z33)*(BM33/IF($W33="",$Q33,$W33)),2) -> 5301.26 | BO33: =+ROUND(BN33*0.1,2) -> 530.13 | BP33: =+SUM(BN33:BO33) -> 5831.39 | BR33: =MAX(0,MIN(IF($Y33<>"",$Y33,$S33),BR$1)-MAX($R33,EOMONTH(BR$1,-1)+1)+1) -> 12 | BS33: =ROUND(IF($Z33="",$T33,$Z33)*(BR33/IF($W33="",$Q33,$W33)),2) -> 2052.1 | BT33: =+ROUND(BS33*0.1,2) -> 205.21 | BU33: =+SUM(BS33:BT33) -> 2257.31 | BW33: =MAX(0,MIN(IF($Y33<>"",$Y33,$S33),BW$1)-MAX($R33,EOMONTH(BW$1,-1)+1)+1) -> 0 | BX33: =ROUND(IF($Z33="",$T33,$Z33)*(BW33/IF($W33="",$Q33,$W33)),2) -> 0 | BY33: =+ROUND(BX33*0.1,2) -> 0 | BZ33: =+SUM(BX33:BY33) -> 0 | CA33: =+AD33+AI33+AN33+AS33+AX33+BC33+BH33+BM33+BR33+BW33 -> 240 | CB33: =+AE33+AJ33+AO33+AT33+AY33+BD33+BI33+BN33+BS33+BX33 -> 41042.01 | CC33: =+AF33+AK33+AP33+AU33+AZ33+BE33+BJ33+BO33+BT33+BY33 -> 4104.23 | CD33: =+SUM(CB33:CC33) -> 45146.24 | CE33: =ROUND(IF($Y33<>"",$Z33,$T33)-CB33,2) -> -0.01 | CF33: =ROUND(IF($Y33<>"",$AA33,$U33)-CC33,2) -> -0.03 | CG33: IVP JORGE BASADRE | CH33: Walter Vidal Quispe Cutipa | CI33: Gerente | CJ33: 930 925 020 | CK33: Walter Vidal Quispe Cutipa | CL33: Memorándum N° 017-2026-CGG-G.G./IVPM-JB | CM33: 46098 | CN33: 930 925 020
A34: 33 | B34: 52 | C34: TACNA | D34: JORGE BASADRE | E34: LOCUMBA | F34: TA-573 | G34: EMP. TA-109 (LOCUMBA) - PTE. CINTO - BARRIAL - CINTO (KM 15+173) | H34: 15.173 | I34: PAVIMENTADO | J34: 808 | K34: 270 | L34: 110338 | M34: 11034 | N34: 121372 | O34: 009-2026-IVPMJB | P34: AVCOC EIRL | Q34: =+$K34 -> 270 | R34: 46167 | S34: =IF(Q34+R34=0,"",Q34+R34-1) -> 46436 | T34: 110338 | U34: =+ROUND(T34*0.1,2) -> 11033.8 | V34: =+SUM(T34:U34) -> 121371.8 | W34: 213 | X34: =+$R34 -> 46167 | Y34: =IF(W34>0,X34+W34-1,"") -> 46379 | Z34: 87044.42 | AA34: =+ROUND(Z34*0.1,2) -> 8704.44 | AB34: =+SUM(Z34:AA34) -> 95748.86 | AD34: =MAX(0,MIN(IF($Y34<>"",$Y34,$S34),AD$1)-MAX($R34,EOMONTH(AD$1,-1)+1)+1) -> 0 | AE34: =ROUND(IF($Z34="",$T34,$Z34)*(AD34/IF($W34="",$Q34,$W34)),2) -> 0 | AF34: =+ROUND(AE34*0.1,2) -> 0 | AG34: =+SUM(AE34:AF34) -> 0 | AI34: =MAX(0,MIN(IF($Y34<>"",$Y34,$S34),AI$1)-MAX($R34,EOMONTH(AI$1,-1)+1)+1) -> 0 | AJ34: =ROUND(IF($Z34="",$T34,$Z34)*(AI34/IF($W34="",$Q34,$W34)),2) -> 0 | AK34: =+ROUND(AJ34*0.1,2) -> 0 | AL34: =+SUM(AJ34:AK34) -> 0 | AN34: =MAX(0,MIN(IF($Y34<>"",$Y34,$S34),AN$1)-MAX($R34,EOMONTH(AN$1,-1)+1)+1) -> 7 | AO34: =ROUND(IF($Z34="",$T34,$Z34)*(AN34/IF($W34="",$Q34,$W34)),2) -> 2860.61 | AP34: =+ROUND(AO34*0.1,2) -> 286.06 | AQ34: =+SUM(AO34:AP34) -> 3146.67 | AS34: =MAX(0,MIN(IF($Y34<>"",$Y34,$S34),AS$1)-MAX($R34,EOMONTH(AS$1,-1)+1)+1) -> 30 | AT34: =ROUND(IF($Z34="",$T34,$Z34)*(AS34/IF($W34="",$Q34,$W34)),2) -> 12259.78 | AU34: =+ROUND(AT34*0.1,2) -> 1225.98 | AV34: =+SUM(AT34:AU34) -> 13485.76 | AX34: =MAX(0,MIN(IF($Y34<>"",$Y34,$S34),AX$1)-MAX($R34,EOMONTH(AX$1,-1)+1)+1) -> 31 | AY34: =ROUND(IF($Z34="",$T34,$Z34)*(AX34/IF($W34="",$Q34,$W34)),2) -> 12668.44 | AZ34: =+ROUND(AY34*0.1,2) -> 1266.84 | BA34: =+SUM(AY34:AZ34) -> 13935.28 | BC34: =MAX(0,MIN(IF($Y34<>"",$Y34,$S34),BC$1)-MAX($R34,EOMONTH(BC$1,-1)+1)+1) -> 31 | BD34: =ROUND(IF($Z34="",$T34,$Z34)*(BC34/IF($W34="",$Q34,$W34)),2) -> 12668.44 | BE34: =+ROUND(BD34*0.1,2) -> 1266.84 | BF34: =+SUM(BD34:BE34) -> 13935.28 | BH34: =MAX(0,MIN(IF($Y34<>"",$Y34,$S34),BH$1)-MAX($R34,EOMONTH(BH$1,-1)+1)+1) -> 30 | BI34: =ROUND(IF($Z34="",$T34,$Z34)*(BH34/IF($W34="",$Q34,$W34)),2) -> 12259.78 | BJ34: =+ROUND(BI34*0.1,2) -> 1225.98 | BK34: =+SUM(BI34:BJ34) -> 13485.76 | BM34: =MAX(0,MIN(IF($Y34<>"",$Y34,$S34),BM$1)-MAX($R34,EOMONTH(BM$1,-1)+1)+1) -> 31 | BN34: =ROUND(IF($Z34="",$T34,$Z34)*(BM34/IF($W34="",$Q34,$W34)),2) -> 12668.44 | BO34: =+ROUND(BN34*0.1,2) -> 1266.84 | BP34: =+SUM(BN34:BO34) -> 13935.28 | BR34: =MAX(0,MIN(IF($Y34<>"",$Y34,$S34),BR$1)-MAX($R34,EOMONTH(BR$1,-1)+1)+1) -> 30 | BS34: =ROUND(IF($Z34="",$T34,$Z34)*(BR34/IF($W34="",$Q34,$W34)),2) -> 12259.78 | BT34: =+ROUND(BS34*0.1,2) -> 1225.98 | BU34: =+SUM(BS34:BT34) -> 13485.76 | BW34: =MAX(0,MIN(IF($Y34<>"",$Y34,$S34),BW$1)-MAX($R34,EOMONTH(BW$1,-1)+1)+1) -> 23 | BX34: =ROUND(IF($Z34="",$T34,$Z34)*(BW34/IF($W34="",$Q34,$W34)),2) -> 9399.16 | BY34: =+ROUND(BX34*0.1,2) -> 939.92 | BZ34: =+SUM(BX34:BY34) -> 10339.08 | CA34: =+AD34+AI34+AN34+AS34+AX34+BC34+BH34+BM34+BR34+BW34 -> 213 | CB34: =+AE34+AJ34+AO34+AT34+AY34+BD34+BI34+BN34+BS34+BX34 -> 87044.43 | CC34: =+AF34+AK34+AP34+AU34+AZ34+BE34+BJ34+BO34+BT34+BY34 -> 8704.44 | CD34: =+SUM(CB34:CC34) -> 95748.87 | CE34: =ROUND(IF($Y34<>"",$Z34,$T34)-CB34,2) -> -0.01 | CF34: =ROUND(IF($Y34<>"",$AA34,$U34)-CC34,2) -> 0 | CG34: IVP JORGE BASADRE | CH34: Walter Vidal Quispe Cutipa | CI34: Gerente | CJ34: 930 925 020 | CK34: Walter Vidal Quispe Cutipa | CL34: Memorándum N° 017-2026-CGG-G.G./IVPM-JB | CM34: 46098 | CN34: 930 925 020
A35: 34 | B35: 52 | C35: TACNA | D35: JORGE BASADRE | E35: ITE | F35: TA-581 | G35: ALFARILLO (KM 01+929) - LAS VILCAS (KM 04+920) | H35: 2.991 | I35: PAVIMENTADO | J35: 808 | K35: 260 | L35: 20944 | M35: 2094 | N35: 23038 | O35: 006-2026-IVPMJB | P35: DARLY ROXANA COTRINA SANTISTEBAN | Q35: =+$K35 -> 260 | R35: 46099 | S35: =IF(Q35+R35=0,"",Q35+R35-1) -> 46358 | T35: 20944 | U35: =+ROUND(T35*0.1,2) -> 2094.4 | V35: =+SUM(T35:U35) -> 23038.4 | X35: =+$R35 -> 46099 | Y35: =IF(W35>0,X35+W35-1,"") | AA35: =+ROUND(Z35*0.1,2) -> 0 | AB35: =+SUM(Z35:AA35) -> 0 | AD35: =MAX(0,MIN(IF($Y35<>"",$Y35,$S35),AD$1)-MAX($R35,EOMONTH(AD$1,-1)+1)+1) -> 14 | AE35: =ROUND(IF($Z35="",$T35,$Z35)*(AD35/IF($W35="",$Q35,$W35)),2) -> 1127.75 | AF35: =+ROUND(AE35*0.1,2) -> 112.78 | AG35: =+SUM(AE35:AF35) -> 1240.53 | AI35: =MAX(0,MIN(IF($Y35<>"",$Y35,$S35),AI$1)-MAX($R35,EOMONTH(AI$1,-1)+1)+1) -> 30 | AJ35: =ROUND(IF($Z35="",$T35,$Z35)*(AI35/IF($W35="",$Q35,$W35)),2) -> 2416.62 | AK35: =+ROUND(AJ35*0.1,2) -> 241.66 | AL35: =+SUM(AJ35:AK35) -> 2658.28 | AN35: =MAX(0,MIN(IF($Y35<>"",$Y35,$S35),AN$1)-MAX($R35,EOMONTH(AN$1,-1)+1)+1) -> 31 | AO35: =ROUND(IF($Z35="",$T35,$Z35)*(AN35/IF($W35="",$Q35,$W35)),2) -> 2497.17 | AP35: =+ROUND(AO35*0.1,2) -> 249.72 | AQ35: =+SUM(AO35:AP35) -> 2746.89 | AS35: =MAX(0,MIN(IF($Y35<>"",$Y35,$S35),AS$1)-MAX($R35,EOMONTH(AS$1,-1)+1)+1) -> 30 | AT35: =ROUND(IF($Z35="",$T35,$Z35)*(AS35/IF($W35="",$Q35,$W35)),2) -> 2416.62 | AU35: =+ROUND(AT35*0.1,2) -> 241.66 | AV35: =+SUM(AT35:AU35) -> 2658.28 | AX35: =MAX(0,MIN(IF($Y35<>"",$Y35,$S35),AX$1)-MAX($R35,EOMONTH(AX$1,-1)+1)+1) -> 31 | AY35: =ROUND(IF($Z35="",$T35,$Z35)*(AX35/IF($W35="",$Q35,$W35)),2) -> 2497.17 | AZ35: =+ROUND(AY35*0.1,2) -> 249.72 | BA35: =+SUM(AY35:AZ35) -> 2746.89 | BC35: =MAX(0,MIN(IF($Y35<>"",$Y35,$S35),BC$1)-MAX($R35,EOMONTH(BC$1,-1)+1)+1) -> 31 | BD35: =ROUND(IF($Z35="",$T35,$Z35)*(BC35/IF($W35="",$Q35,$W35)),2) -> 2497.17 | BE35: =+ROUND(BD35*0.1,2) -> 249.72 | BF35: =+SUM(BD35:BE35) -> 2746.89 | BH35: =MAX(0,MIN(IF($Y35<>"",$Y35,$S35),BH$1)-MAX($R35,EOMONTH(BH$1,-1)+1)+1) -> 30 | BI35: =ROUND(IF($Z35="",$T35,$Z35)*(BH35/IF($W35="",$Q35,$W35)),2) -> 2416.62 | BJ35: =+ROUND(BI35*0.1,2) -> 241.66 | BK35: =+SUM(BI35:BJ35) -> 2658.28 | BM35: =MAX(0,MIN(IF($Y35<>"",$Y35,$S35),BM$1)-MAX($R35,EOMONTH(BM$1,-1)+1)+1) -> 31 | BN35: =ROUND(IF($Z35="",$T35,$Z35)*(BM35/IF($W35="",$Q35,$W35)),2) -> 2497.17 | BO35: =+ROUND(BN35*0.1,2) -> 249.72 | BP35: =+SUM(BN35:BO35) -> 2746.89 | BR35: =MAX(0,MIN(IF($Y35<>"",$Y35,$S35),BR$1)-MAX($R35,EOMONTH(BR$1,-1)+1)+1) -> 30 | BS35: =ROUND(IF($Z35="",$T35,$Z35)*(BR35/IF($W35="",$Q35,$W35)),2) -> 2416.62 | BT35: =+ROUND(BS35*0.1,2) -> 241.66 | BU35: =+SUM(BS35:BT35) -> 2658.28 | BW35: =MAX(0,MIN(IF($Y35<>"",$Y35,$S35),BW$1)-MAX($R35,EOMONTH(BW$1,-1)+1)+1) -> 2 | BX35: =ROUND(IF($Z35="",$T35,$Z35)*(BW35/IF($W35="",$Q35,$W35)),2) -> 161.11 | BY35: =+ROUND(BX35*0.1,2) -> 16.11 | BZ35: =+SUM(BX35:BY35) -> 177.22 | CA35: =+AD35+AI35+AN35+AS35+AX35+BC35+BH35+BM35+BR35+BW35 -> 260 | CB35: =+AE35+AJ35+AO35+AT35+AY35+BD35+BI35+BN35+BS35+BX35 -> 20944.02 | CC35: =+AF35+AK35+AP35+AU35+AZ35+BE35+BJ35+BO35+BT35+BY35 -> 2094.41 | CD35: =+SUM(CB35:CC35) -> 23038.43 | CE35: =ROUND(IF($Y35<>"",$Z35,$T35)-CB35,2) -> -0.02 | CF35: =ROUND(IF($Y35<>"",$AA35,$U35)-CC35,2) -> -0.01 | CG35: IVP JORGE BASADRE | CH35: Walter Vidal Quispe Cutipa | CI35: Gerente | CJ35: 930 925 020 | CK35: Walter Vidal Quispe Cutipa | CL35: Memorándum N° 017-2026-CGG-G.G./IVPM-JB | CM35: 46098 | CN35: 930 925 020
A36: 35 | B36: 52 | C36: TACNA | D36: JORGE BASADRE | E36: ITE | F36: TA-586 | G36: EMP. TA-101 - EMP. TA-587 | H36: 2.242 | I36: PAVIMENTADO | J36: 808 | K36: 260 | L36: 15699 | M36: 1570 | N36: 17269 | O36: 007-2026-IVPMJB | P36: DARLY ROXANA COTRINA SANTISTEBAN | Q36: =+$K36 -> 260 | R36: 46099 | S36: =IF(Q36+R36=0,"",Q36+R36-1) -> 46358 | T36: 15699 | U36: =+ROUND(T36*0.1,2) -> 1569.9 | V36: =+SUM(T36:U36) -> 17268.9 | X36: =+$R36 -> 46099 | Y36: =IF(W36>0,X36+W36-1,"") | AA36: =+ROUND(Z36*0.1,2) -> 0 | AB36: =+SUM(Z36:AA36) -> 0 | AD36: =MAX(0,MIN(IF($Y36<>"",$Y36,$S36),AD$1)-MAX($R36,EOMONTH(AD$1,-1)+1)+1) -> 14 | AE36: =ROUND(IF($Z36="",$T36,$Z36)*(AD36/IF($W36="",$Q36,$W36)),2) -> 845.33 | AF36: =+ROUND(AE36*0.1,2) -> 84.53 | AG36: =+SUM(AE36:AF36) -> 929.86 | AI36: =MAX(0,MIN(IF($Y36<>"",$Y36,$S36),AI$1)-MAX($R36,EOMONTH(AI$1,-1)+1)+1) -> 30 | AJ36: =ROUND(IF($Z36="",$T36,$Z36)*(AI36/IF($W36="",$Q36,$W36)),2) -> 1811.42 | AK36: =+ROUND(AJ36*0.1,2) -> 181.14 | AL36: =+SUM(AJ36:AK36) -> 1992.56 | AN36: =MAX(0,MIN(IF($Y36<>"",$Y36,$S36),AN$1)-MAX($R36,EOMONTH(AN$1,-1)+1)+1) -> 31 | AO36: =ROUND(IF($Z36="",$T36,$Z36)*(AN36/IF($W36="",$Q36,$W36)),2) -> 1871.8 | AP36: =+ROUND(AO36*0.1,2) -> 187.18 | AQ36: =+SUM(AO36:AP36) -> 2058.98 | AS36: =MAX(0,MIN(IF($Y36<>"",$Y36,$S36),AS$1)-MAX($R36,EOMONTH(AS$1,-1)+1)+1) -> 30 | AT36: =ROUND(IF($Z36="",$T36,$Z36)*(AS36/IF($W36="",$Q36,$W36)),2) -> 1811.42 | AU36: =+ROUND(AT36*0.1,2) -> 181.14 | AV36: =+SUM(AT36:AU36) -> 1992.56 | AX36: =MAX(0,MIN(IF($Y36<>"",$Y36,$S36),AX$1)-MAX($R36,EOMONTH(AX$1,-1)+1)+1) -> 31 | AY36: =ROUND(IF($Z36="",$T36,$Z36)*(AX36/IF($W36="",$Q36,$W36)),2) -> 1871.8 | AZ36: =+ROUND(AY36*0.1,2) -> 187.18 | BA36: =+SUM(AY36:AZ36) -> 2058.98 | BC36: =MAX(0,MIN(IF($Y36<>"",$Y36,$S36),BC$1)-MAX($R36,EOMONTH(BC$1,-1)+1)+1) -> 31 | BD36: =ROUND(IF($Z36="",$T36,$Z36)*(BC36/IF($W36="",$Q36,$W36)),2) -> 1871.8 | BE36: =+ROUND(BD36*0.1,2) -> 187.18 | BF36: =+SUM(BD36:BE36) -> 2058.98 | BH36: =MAX(0,MIN(IF($Y36<>"",$Y36,$S36),BH$1)-MAX($R36,EOMONTH(BH$1,-1)+1)+1) -> 30 | BI36: =ROUND(IF($Z36="",$T36,$Z36)*(BH36/IF($W36="",$Q36,$W36)),2) -> 1811.42 | BJ36: =+ROUND(BI36*0.1,2) -> 181.14 | BK36: =+SUM(BI36:BJ36) -> 1992.56 | BM36: =MAX(0,MIN(IF($Y36<>"",$Y36,$S36),BM$1)-MAX($R36,EOMONTH(BM$1,-1)+1)+1) -> 31 | BN36: =ROUND(IF($Z36="",$T36,$Z36)*(BM36/IF($W36="",$Q36,$W36)),2) -> 1871.8 | BO36: =+ROUND(BN36*0.1,2) -> 187.18 | BP36: =+SUM(BN36:BO36) -> 2058.98 | BR36: =MAX(0,MIN(IF($Y36<>"",$Y36,$S36),BR$1)-MAX($R36,EOMONTH(BR$1,-1)+1)+1) -> 30 | BS36: =ROUND(IF($Z36="",$T36,$Z36)*(BR36/IF($W36="",$Q36,$W36)),2) -> 1811.42 | BT36: =+ROUND(BS36*0.1,2) -> 181.14 | BU36: =+SUM(BS36:BT36) -> 1992.56 | BW36: =MAX(0,MIN(IF($Y36<>"",$Y36,$S36),BW$1)-MAX($R36,EOMONTH(BW$1,-1)+1)+1) -> 2 | BX36: =ROUND(IF($Z36="",$T36,$Z36)*(BW36/IF($W36="",$Q36,$W36)),2) -> 120.76 | BY36: =+ROUND(BX36*0.1,2) -> 12.08 | BZ36: =+SUM(BX36:BY36) -> 132.84 | CA36: =+AD36+AI36+AN36+AS36+AX36+BC36+BH36+BM36+BR36+BW36 -> 260 | CB36: =+AE36+AJ36+AO36+AT36+AY36+BD36+BI36+BN36+BS36+BX36 -> 15698.97 | CC36: =+AF36+AK36+AP36+AU36+AZ36+BE36+BJ36+BO36+BT36+BY36 -> 1569.89 | CD36: =+SUM(CB36:CC36) -> 17268.86 | CE36: =ROUND(IF($Y36<>"",$Z36,$T36)-CB36,2) -> 0.03 | CF36: =ROUND(IF($Y36<>"",$AA36,$U36)-CC36,2) -> 0.01 | CG36: IVP JORGE BASADRE | CH36: Walter Vidal Quispe Cutipa | CI36: Gerente | CJ36: 930 925 020 | CK36: Walter Vidal Quispe Cutipa | CL36: Memorándum N° 017-2026-CGG-G.G./IVPM-JB | CM36: 46098 | CN36: 930 925 020
A37: 36 | B37: 52 | C37: TACNA | D37: JORGE BASADRE | E37: ITE | F37: TA-583 | G37: EMP. TA-101 (PAMPA BAJA) - PTE. SAN ISIDRO - SAN ISIDRO - EMP. TA-581 (ALFARILLO) | H37: 2.959 | I37: PAVIMENTADO | J37: 808 | K37: 261 | L37: 20800 | M37: 2080 | N37: 22880 | O37: 008-2026-IVPMJB | P37: DARLY ROXANA COTRINA SANTISTEBAN | Q37: =+$K37 -> 261 | R37: 46099 | S37: =IF(Q37+R37=0,"",Q37+R37-1) -> 46359 | T37: 20800 | U37: =+ROUND(T37*0.1,2) -> 2080 | V37: =+SUM(T37:U37) -> 22880 | X37: =+$R37 -> 46099 | Y37: =IF(W37>0,X37+W37-1,"") | AA37: =+ROUND(Z37*0.1,2) -> 0 | AB37: =+SUM(Z37:AA37) -> 0 | AD37: =MAX(0,MIN(IF($Y37<>"",$Y37,$S37),AD$1)-MAX($R37,EOMONTH(AD$1,-1)+1)+1) -> 14 | AE37: =ROUND(IF($Z37="",$T37,$Z37)*(AD37/IF($W37="",$Q37,$W37)),2) -> 1115.71 | AF37: =+ROUND(AE37*0.1,2) -> 111.57 | AG37: =+SUM(AE37:AF37) -> 1227.28 | AI37: =MAX(0,MIN(IF($Y37<>"",$Y37,$S37),AI$1)-MAX($R37,EOMONTH(AI$1,-1)+1)+1) -> 30 | AJ37: =ROUND(IF($Z37="",$T37,$Z37)*(AI37/IF($W37="",$Q37,$W37)),2) -> 2390.8 | AK37: =+ROUND(AJ37*0.1,2) -> 239.08 | AL37: =+SUM(AJ37:AK37) -> 2629.88 | AN37: =MAX(0,MIN(IF($Y37<>"",$Y37,$S37),AN$1)-MAX($R37,EOMONTH(AN$1,-1)+1)+1) -> 31 | AO37: =ROUND(IF($Z37="",$T37,$Z37)*(AN37/IF($W37="",$Q37,$W37)),2) -> 2470.5 | AP37: =+ROUND(AO37*0.1,2) -> 247.05 | AQ37: =+SUM(AO37:AP37) -> 2717.55 | AS37: =MAX(0,MIN(IF($Y37<>"",$Y37,$S37),AS$1)-MAX($R37,EOMONTH(AS$1,-1)+1)+1) -> 30 | AT37: =ROUND(IF($Z37="",$T37,$Z37)*(AS37/IF($W37="",$Q37,$W37)),2) -> 2390.8 | AU37: =+ROUND(AT37*0.1,2) -> 239.08 | AV37: =+SUM(AT37:AU37) -> 2629.88 | AX37: =MAX(0,MIN(IF($Y37<>"",$Y37,$S37),AX$1)-MAX($R37,EOMONTH(AX$1,-1)+1)+1) -> 31 | AY37: =ROUND(IF($Z37="",$T37,$Z37)*(AX37/IF($W37="",$Q37,$W37)),2) -> 2470.5 | AZ37: =+ROUND(AY37*0.1,2) -> 247.05 | BA37: =+SUM(AY37:AZ37) -> 2717.55 | BC37: =MAX(0,MIN(IF($Y37<>"",$Y37,$S37),BC$1)-MAX($R37,EOMONTH(BC$1,-1)+1)+1) -> 31 | BD37: =ROUND(IF($Z37="",$T37,$Z37)*(BC37/IF($W37="",$Q37,$W37)),2) -> 2470.5 | BE37: =+ROUND(BD37*0.1,2) -> 247.05 | BF37: =+SUM(BD37:BE37) -> 2717.55 | BH37: =MAX(0,MIN(IF($Y37<>"",$Y37,$S37),BH$1)-MAX($R37,EOMONTH(BH$1,-1)+1)+1) -> 30 | BI37: =ROUND(IF($Z37="",$T37,$Z37)*(BH37/IF($W37="",$Q37,$W37)),2) -> 2390.8 | BJ37: =+ROUND(BI37*0.1,2) -> 239.08 | BK37: =+SUM(BI37:BJ37) -> 2629.88 | BM37: =MAX(0,MIN(IF($Y37<>"",$Y37,$S37),BM$1)-MAX($R37,EOMONTH(BM$1,-1)+1)+1) -> 31 | BN37: =ROUND(IF($Z37="",$T37,$Z37)*(BM37/IF($W37="",$Q37,$W37)),2) -> 2470.5 | BO37: =+ROUND(BN37*0.1,2) -> 247.05 | BP37: =+SUM(BN37:BO37) -> 2717.55 | BR37: =MAX(0,MIN(IF($Y37<>"",$Y37,$S37),BR$1)-MAX($R37,EOMONTH(BR$1,-1)+1)+1) -> 30 | BS37: =ROUND(IF($Z37="",$T37,$Z37)*(BR37/IF($W37="",$Q37,$W37)),2) -> 2390.8 | BT37: =+ROUND(BS37*0.1,2) -> 239.08 | BU37: =+SUM(BS37:BT37) -> 2629.88 | BW37: =MAX(0,MIN(IF($Y37<>"",$Y37,$S37),BW$1)-MAX($R37,EOMONTH(BW$1,-1)+1)+1) -> 3 | BX37: =ROUND(IF($Z37="",$T37,$Z37)*(BW37/IF($W37="",$Q37,$W37)),2) -> 239.08 | BY37: =+ROUND(BX37*0.1,2) -> 23.91 | BZ37: =+SUM(BX37:BY37) -> 262.99 | CA37: =+AD37+AI37+AN37+AS37+AX37+BC37+BH37+BM37+BR37+BW37 -> 261 | CB37: =+AE37+AJ37+AO37+AT37+AY37+BD37+BI37+BN37+BS37+BX37 -> 20799.99 | CC37: =+AF37+AK37+AP37+AU37+AZ37+BE37+BJ37+BO37+BT37+BY37 -> 2080 | CD37: =+SUM(CB37:CC37) -> 22879.99 | CE37: =ROUND(IF($Y37<>"",$Z37,$T37)-CB37,2) -> 0.01 | CF37: =ROUND(IF($Y37<>"",$AA37,$U37)-CC37,2) -> 0 | CG37: IVP JORGE BASADRE | CH37: Walter Vidal Quispe Cutipa | CI37: Gerente | CJ37: 930 925 020 | CK37: Walter Vidal Quispe Cutipa | CL37: Memorándum N° 017-2026-CGG-G.G./IVPM-JB | CM37: 46098 | CN37: 930 925 020
A38: 37 | B38: 204 | C38: TACNA | D38: TACNA | E38: INCLAN | F38: TA-606 | G38: EMP. TA-604-DV. TA-607-EMP.TA-605 (ALTO RAYO) | H38: 5.498 | I38: AFIRMADO | J38: 735 | K38: 240 | L38: 32328 | M38: 3233 | N38: 35561 | O38: 0001-2026-IVPT | P38: COMERCIAL CYJSA E.I.R.L | Q38: =+$K38 -> 240 | R38: 46144 | S38: =IF(Q38+R38=0,"",Q38+R38-1) -> 46383 | T38: 30710.34 | U38: =+ROUND(T38*0.1,2) -> 3071.03 | V38: =+SUM(T38:U38) -> 33781.37 | X38: =+$R38 -> 46144 | Y38: =IF(W38>0,X38+W38-1,"") | AA38: =+ROUND(Z38*0.1,2) -> 0 | AB38: =+SUM(Z38:AA38) -> 0 | AD38: =MAX(0,MIN(IF($Y38<>"",$Y38,$S38),AD$1)-MAX($R38,EOMONTH(AD$1,-1)+1)+1) -> 0 | AE38: =ROUND(IF($Z38="",$T38,$Z38)*(AD38/IF($W38="",$Q38,$W38)),2) -> 0 | AF38: =+ROUND(AE38*0.1,2) -> 0 | AG38: =+SUM(AE38:AF38) -> 0 | AI38: =MAX(0,MIN(IF($Y38<>"",$Y38,$S38),AI$1)-MAX($R38,EOMONTH(AI$1,-1)+1)+1) -> 0 | AJ38: =ROUND(IF($Z38="",$T38,$Z38)*(AI38/IF($W38="",$Q38,$W38)),2) -> 0 | AK38: =+ROUND(AJ38*0.1,2) -> 0 | AL38: =+SUM(AJ38:AK38) -> 0 | AN38: =MAX(0,MIN(IF($Y38<>"",$Y38,$S38),AN$1)-MAX($R38,EOMONTH(AN$1,-1)+1)+1) -> 30 | AO38: =ROUND(IF($Z38="",$T38,$Z38)*(AN38/IF($W38="",$Q38,$W38)),2) -> 3838.79 | AP38: =+ROUND(AO38*0.1,2) -> 383.88 | AQ38: =+SUM(AO38:AP38) -> 4222.67 | AS38: =MAX(0,MIN(IF($Y38<>"",$Y38,$S38),AS$1)-MAX($R38,EOMONTH(AS$1,-1)+1)+1) -> 30 | AT38: =ROUND(IF($Z38="",$T38,$Z38)*(AS38/IF($W38="",$Q38,$W38)),2) -> 3838.79 | AU38: =+ROUND(AT38*0.1,2) -> 383.88 | AV38: =+SUM(AT38:AU38) -> 4222.67 | AX38: =MAX(0,MIN(IF($Y38<>"",$Y38,$S38),AX$1)-MAX($R38,EOMONTH(AX$1,-1)+1)+1) -> 31 | AY38: =ROUND(IF($Z38="",$T38,$Z38)*(AX38/IF($W38="",$Q38,$W38)),2) -> 3966.75 | AZ38: =+ROUND(AY38*0.1,2) -> 396.68 | BA38: =+SUM(AY38:AZ38) -> 4363.43 | BC38: =MAX(0,MIN(IF($Y38<>"",$Y38,$S38),BC$1)-MAX($R38,EOMONTH(BC$1,-1)+1)+1) -> 31 | BD38: =ROUND(IF($Z38="",$T38,$Z38)*(BC38/IF($W38="",$Q38,$W38)),2) -> 3966.75 | BE38: =+ROUND(BD38*0.1,2) -> 396.68 | BF38: =+SUM(BD38:BE38) -> 4363.43 | BH38: =MAX(0,MIN(IF($Y38<>"",$Y38,$S38),BH$1)-MAX($R38,EOMONTH(BH$1,-1)+1)+1) -> 30 | BI38: =ROUND(IF($Z38="",$T38,$Z38)*(BH38/IF($W38="",$Q38,$W38)),2) -> 3838.79 | BJ38: =+ROUND(BI38*0.1,2) -> 383.88 | BK38: =+SUM(BI38:BJ38) -> 4222.67 | BM38: =MAX(0,MIN(IF($Y38<>"",$Y38,$S38),BM$1)-MAX($R38,EOMONTH(BM$1,-1)+1)+1) -> 31 | BN38: =ROUND(IF($Z38="",$T38,$Z38)*(BM38/IF($W38="",$Q38,$W38)),2) -> 3966.75 | BO38: =+ROUND(BN38*0.1,2) -> 396.68 | BP38: =+SUM(BN38:BO38) -> 4363.43 | BR38: =MAX(0,MIN(IF($Y38<>"",$Y38,$S38),BR$1)-MAX($R38,EOMONTH(BR$1,-1)+1)+1) -> 30 | BS38: =ROUND(IF($Z38="",$T38,$Z38)*(BR38/IF($W38="",$Q38,$W38)),2) -> 3838.79 | BT38: =+ROUND(BS38*0.1,2) -> 383.88 | BU38: =+SUM(BS38:BT38) -> 4222.67 | BW38: =MAX(0,MIN(IF($Y38<>"",$Y38,$S38),BW$1)-MAX($R38,EOMONTH(BW$1,-1)+1)+1) -> 27 | BX38: =ROUND(IF($Z38="",$T38,$Z38)*(BW38/IF($W38="",$Q38,$W38)),2) -> 3454.91 | BY38: =+ROUND(BX38*0.1,2) -> 345.49 | BZ38: =+SUM(BX38:BY38) -> 3800.4 | CA38: =+AD38+AI38+AN38+AS38+AX38+BC38+BH38+BM38+BR38+BW38 -> 240 | CB38: =+AE38+AJ38+AO38+AT38+AY38+BD38+BI38+BN38+BS38+BX38 -> 30710.32 | CC38: =+AF38+AK38+AP38+AU38+AZ38+BE38+BJ38+BO38+BT38+BY38 -> 3071.05 | CD38: =+SUM(CB38:CC38) -> 33781.37 | CE38: =ROUND(IF($Y38<>"",$Z38,$T38)-CB38,2) -> 0.02 | CF38: =ROUND(IF($Y38<>"",$AA38,$U38)-CC38,2) -> -0.02 | CG38: IVP TACNA | CH38: John Lucero Vargas | CI38: Gerente | CJ38: 988 801 839 | CK38: Eddy Frank Coronado Choquecahua | CL38: Memorandum N° 007-2026-GG-IVPT | CM38: 46140 | CN38: 931 994 396
A39: 38 | B39: 204 | C39: TACNA | D39: TACNA | E39: INCLAN | F39: TA-607 | G39: EMP. TA-604 - EMP.TA-606 | H39: 3.012 | I39: AFIRMADO | J39: 735 | K39: 240 | L39: 17711 | M39: 1771 | N39: 19482 | O39: 0001-2026-IVPT | P39: COMERCIAL CYJSA E.I.R.L | Q39: =+$K39 -> 240 | R39: 46144 | S39: =IF(Q39+R39=0,"",Q39+R39-1) -> 46383 | T39: 16824.5 | U39: =+ROUND(T39*0.1,2) -> 1682.45 | V39: =+SUM(T39:U39) -> 18506.95 | X39: =+$R39 -> 46144 | Y39: =IF(W39>0,X39+W39-1,"") | AA39: =+ROUND(Z39*0.1,2) -> 0 | AB39: =+SUM(Z39:AA39) -> 0 | AD39: =MAX(0,MIN(IF($Y39<>"",$Y39,$S39),AD$1)-MAX($R39,EOMONTH(AD$1,-1)+1)+1) -> 0 | AE39: =ROUND(IF($Z39="",$T39,$Z39)*(AD39/IF($W39="",$Q39,$W39)),2) -> 0 | AF39: =+ROUND(AE39*0.1,2) -> 0 | AG39: =+SUM(AE39:AF39) -> 0 | AI39: =MAX(0,MIN(IF($Y39<>"",$Y39,$S39),AI$1)-MAX($R39,EOMONTH(AI$1,-1)+1)+1) -> 0 | AJ39: =ROUND(IF($Z39="",$T39,$Z39)*(AI39/IF($W39="",$Q39,$W39)),2) -> 0 | AK39: =+ROUND(AJ39*0.1,2) -> 0 | AL39: =+SUM(AJ39:AK39) -> 0 | AN39: =MAX(0,MIN(IF($Y39<>"",$Y39,$S39),AN$1)-MAX($R39,EOMONTH(AN$1,-1)+1)+1) -> 30 | AO39: =ROUND(IF($Z39="",$T39,$Z39)*(AN39/IF($W39="",$Q39,$W39)),2) -> 2103.06 | AP39: =+ROUND(AO39*0.1,2) -> 210.31 | AQ39: =+SUM(AO39:AP39) -> 2313.37 | AS39: =MAX(0,MIN(IF($Y39<>"",$Y39,$S39),AS$1)-MAX($R39,EOMONTH(AS$1,-1)+1)+1) -> 30 | AT39: =ROUND(IF($Z39="",$T39,$Z39)*(AS39/IF($W39="",$Q39,$W39)),2) -> 2103.06 | AU39: =+ROUND(AT39*0.1,2) -> 210.31 | AV39: =+SUM(AT39:AU39) -> 2313.37 | AX39: =MAX(0,MIN(IF($Y39<>"",$Y39,$S39),AX$1)-MAX($R39,EOMONTH(AX$1,-1)+1)+1) -> 31 | AY39: =ROUND(IF($Z39="",$T39,$Z39)*(AX39/IF($W39="",$Q39,$W39)),2) -> 2173.16 | AZ39: =+ROUND(AY39*0.1,2) -> 217.32 | BA39: =+SUM(AY39:AZ39) -> 2390.48 | BC39: =MAX(0,MIN(IF($Y39<>"",$Y39,$S39),BC$1)-MAX($R39,EOMONTH(BC$1,-1)+1)+1) -> 31 | BD39: =ROUND(IF($Z39="",$T39,$Z39)*(BC39/IF($W39="",$Q39,$W39)),2) -> 2173.16 | BE39: =+ROUND(BD39*0.1,2) -> 217.32 | BF39: =+SUM(BD39:BE39) -> 2390.48 | BH39: =MAX(0,MIN(IF($Y39<>"",$Y39,$S39),BH$1)-MAX($R39,EOMONTH(BH$1,-1)+1)+1) -> 30 | BI39: =ROUND(IF($Z39="",$T39,$Z39)*(BH39/IF($W39="",$Q39,$W39)),2) -> 2103.06 | BJ39: =+ROUND(BI39*0.1,2) -> 210.31 | BK39: =+SUM(BI39:BJ39) -> 2313.37 | BM39: =MAX(0,MIN(IF($Y39<>"",$Y39,$S39),BM$1)-MAX($R39,EOMONTH(BM$1,-1)+1)+1) -> 31 | BN39: =ROUND(IF($Z39="",$T39,$Z39)*(BM39/IF($W39="",$Q39,$W39)),2) -> 2173.16 | BO39: =+ROUND(BN39*0.1,2) -> 217.32 | BP39: =+SUM(BN39:BO39) -> 2390.48 | BR39: =MAX(0,MIN(IF($Y39<>"",$Y39,$S39),BR$1)-MAX($R39,EOMONTH(BR$1,-1)+1)+1) -> 30 | BS39: =ROUND(IF($Z39="",$T39,$Z39)*(BR39/IF($W39="",$Q39,$W39)),2) -> 2103.06 | BT39: =+ROUND(BS39*0.1,2) -> 210.31 | BU39: =+SUM(BS39:BT39) -> 2313.37 | BW39: =MAX(0,MIN(IF($Y39<>"",$Y39,$S39),BW$1)-MAX($R39,EOMONTH(BW$1,-1)+1)+1) -> 27 | BX39: =ROUND(IF($Z39="",$T39,$Z39)*(BW39/IF($W39="",$Q39,$W39)),2) -> 1892.76 | BY39: =+ROUND(BX39*0.1,2) -> 189.28 | BZ39: =+SUM(BX39:BY39) -> 2082.04 | CA39: =+AD39+AI39+AN39+AS39+AX39+BC39+BH39+BM39+BR39+BW39 -> 240 | CB39: =+AE39+AJ39+AO39+AT39+AY39+BD39+BI39+BN39+BS39+BX39 -> 16824.48 | CC39: =+AF39+AK39+AP39+AU39+AZ39+BE39+BJ39+BO39+BT39+BY39 -> 1682.48 | CD39: =+SUM(CB39:CC39) -> 18506.96 | CE39: =ROUND(IF($Y39<>"",$Z39,$T39)-CB39,2) -> 0.02 | CF39: =ROUND(IF($Y39<>"",$AA39,$U39)-CC39,2) -> -0.03 | CG39: IVP TACNA | CH39: John Lucero Vargas | CI39: Gerente | CJ39: 988 801 839 | CK39: Eddy Frank Coronado Choquecahua | CL39: Memorandum N° 007-2026-GG-IVPT | CM39: 46140 | CN39: 931 994 396
A40: 39 | B40: 204 | C40: TACNA | D40: TACNA | E40: INCLAN | F40: TA-604 | G40: EMP. PE-1S(KM 02+914)-PROTER-ALTO RAYO (KM 11+000) | H40: 8.086 | I40: PAVIMENTADO | J40: 887.5 | K40: 240 | L40: 57411 | M40: 5741 | N40: 63152 | O40: 0001-2026-IVPT | P40: COMERCIAL CYJSA E.I.R.L | Q40: =+$K40 -> 240 | R40: 46144 | S40: =IF(Q40+R40=0,"",Q40+R40-1) -> 46383 | T40: 54530 | U40: =+ROUND(T40*0.1,2) -> 5453 | V40: =+SUM(T40:U40) -> 59983 | X40: =+$R40 -> 46144 | Y40: =IF(W40>0,X40+W40-1,"") | AA40: =+ROUND(Z40*0.1,2) -> 0 | AB40: =+SUM(Z40:AA40) -> 0 | AD40: =MAX(0,MIN(IF($Y40<>"",$Y40,$S40),AD$1)-MAX($R40,EOMONTH(AD$1,-1)+1)+1) -> 0 | AE40: =ROUND(IF($Z40="",$T40,$Z40)*(AD40/IF($W40="",$Q40,$W40)),2) -> 0 | AF40: =+ROUND(AE40*0.1,2) -> 0 | AG40: =+SUM(AE40:AF40) -> 0 | AI40: =MAX(0,MIN(IF($Y40<>"",$Y40,$S40),AI$1)-MAX($R40,EOMONTH(AI$1,-1)+1)+1) -> 0 | AJ40: =ROUND(IF($Z40="",$T40,$Z40)*(AI40/IF($W40="",$Q40,$W40)),2) -> 0 | AK40: =+ROUND(AJ40*0.1,2) -> 0 | AL40: =+SUM(AJ40:AK40) -> 0 | AN40: =MAX(0,MIN(IF($Y40<>"",$Y40,$S40),AN$1)-MAX($R40,EOMONTH(AN$1,-1)+1)+1) -> 30 | AO40: =ROUND(IF($Z40="",$T40,$Z40)*(AN40/IF($W40="",$Q40,$W40)),2) -> 6816.25 | AP40: =+ROUND(AO40*0.1,2) -> 681.63 | AQ40: =+SUM(AO40:AP40) -> 7497.88 | AS40: =MAX(0,MIN(IF($Y40<>"",$Y40,$S40),AS$1)-MAX($R40,EOMONTH(AS$1,-1)+1)+1) -> 30 | AT40: =ROUND(IF($Z40="",$T40,$Z40)*(AS40/IF($W40="",$Q40,$W40)),2) -> 6816.25 | AU40: =+ROUND(AT40*0.1,2) -> 681.63 | AV40: =+SUM(AT40:AU40) -> 7497.88 | AX40: =MAX(0,MIN(IF($Y40<>"",$Y40,$S40),AX$1)-MAX($R40,EOMONTH(AX$1,-1)+1)+1) -> 31 | AY40: =ROUND(IF($Z40="",$T40,$Z40)*(AX40/IF($W40="",$Q40,$W40)),2) -> 7043.46 | AZ40: =+ROUND(AY40*0.1,2) -> 704.35 | BA40: =+SUM(AY40:AZ40) -> 7747.81 | BC40: =MAX(0,MIN(IF($Y40<>"",$Y40,$S40),BC$1)-MAX($R40,EOMONTH(BC$1,-1)+1)+1) -> 31 | BD40: =ROUND(IF($Z40="",$T40,$Z40)*(BC40/IF($W40="",$Q40,$W40)),2) -> 7043.46 | BE40: =+ROUND(BD40*0.1,2) -> 704.35 | BF40: =+SUM(BD40:BE40) -> 7747.81 | BH40: =MAX(0,MIN(IF($Y40<>"",$Y40,$S40),BH$1)-MAX($R40,EOMONTH(BH$1,-1)+1)+1) -> 30 | BI40: =ROUND(IF($Z40="",$T40,$Z40)*(BH40/IF($W40="",$Q40,$W40)),2) -> 6816.25 | BJ40: =+ROUND(BI40*0.1,2) -> 681.63 | BK40: =+SUM(BI40:BJ40) -> 7497.88 | BM40: =MAX(0,MIN(IF($Y40<>"",$Y40,$S40),BM$1)-MAX($R40,EOMONTH(BM$1,-1)+1)+1) -> 31 | BN40: =ROUND(IF($Z40="",$T40,$Z40)*(BM40/IF($W40="",$Q40,$W40)),2) -> 7043.46 | BO40: =+ROUND(BN40*0.1,2) -> 704.35 | BP40: =+SUM(BN40:BO40) -> 7747.81 | BR40: =MAX(0,MIN(IF($Y40<>"",$Y40,$S40),BR$1)-MAX($R40,EOMONTH(BR$1,-1)+1)+1) -> 30 | BS40: =ROUND(IF($Z40="",$T40,$Z40)*(BR40/IF($W40="",$Q40,$W40)),2) -> 6816.25 | BT40: =+ROUND(BS40*0.1,2) -> 681.63 | BU40: =+SUM(BS40:BT40) -> 7497.88 | BW40: =MAX(0,MIN(IF($Y40<>"",$Y40,$S40),BW$1)-MAX($R40,EOMONTH(BW$1,-1)+1)+1) -> 27 | BX40: =ROUND(IF($Z40="",$T40,$Z40)*(BW40/IF($W40="",$Q40,$W40)),2) -> 6134.63 | BY40: =+ROUND(BX40*0.1,2) -> 613.46 | BZ40: =+SUM(BX40:BY40) -> 6748.09 | CA40: =+AD40+AI40+AN40+AS40+AX40+BC40+BH40+BM40+BR40+BW40 -> 240 | CB40: =+AE40+AJ40+AO40+AT40+AY40+BD40+BI40+BN40+BS40+BX40 -> 54530.01 | CC40: =+AF40+AK40+AP40+AU40+AZ40+BE40+BJ40+BO40+BT40+BY40 -> 5453.03 | CD40: =+SUM(CB40:CC40) -> 59983.04 | CE40: =ROUND(IF($Y40<>"",$Z40,$T40)-CB40,2) -> -0.01 | CF40: =ROUND(IF($Y40<>"",$AA40,$U40)-CC40,2) -> -0.03 | CG40: IVP TACNA | CH40: John Lucero Vargas | CI40: Gerente | CJ40: 988 801 839 | CK40: Eddy Frank Coronado Choquecahua | CL40: Memorandum N° 007-2026-GG-IVPT | CM40: 46140 | CN40: 931 994 396
A41: 40 | B41: 204 | C41: TACNA | D41: TACNA | E41: LA YARADA Y LOS PALOS | F41: TA-642 | G41: EMP. PE-1SD - ASENTAMIENTO 5 Y 6 – EMP. TA-644 | H41: 12.884 | I41: PAVIMENTADO | J41: 887.5 | K41: 240 | L41: 91476 | M41: 9148 | N41: 100624 | O41: 0002-2026-IVPT | P41: COMERCIAL CYJSA E.I.R.L | Q41: =+$K41 -> 240 | R41: 46144 | S41: =IF(Q41+R41=0,"",Q41+R41-1) -> 46383 | T41: 86896.5 | U41: =+ROUND(T41*0.1,2) -> 8689.65 | V41: =+SUM(T41:U41) -> 95586.15 | X41: =+$R41 -> 46144 | Y41: =IF(W41>0,X41+W41-1,"") | AA41: =+ROUND(Z41*0.1,2) -> 0 | AB41: =+SUM(Z41:AA41) -> 0 | AD41: =MAX(0,MIN(IF($Y41<>"",$Y41,$S41),AD$1)-MAX($R41,EOMONTH(AD$1,-1)+1)+1) -> 0 | AE41: =ROUND(IF($Z41="",$T41,$Z41)*(AD41/IF($W41="",$Q41,$W41)),2) -> 0 | AF41: =+ROUND(AE41*0.1,2) -> 0 | AG41: =+SUM(AE41:AF41) -> 0 | AI41: =MAX(0,MIN(IF($Y41<>"",$Y41,$S41),AI$1)-MAX($R41,EOMONTH(AI$1,-1)+1)+1) -> 0 | AJ41: =ROUND(IF($Z41="",$T41,$Z41)*(AI41/IF($W41="",$Q41,$W41)),2) -> 0 | AK41: =+ROUND(AJ41*0.1,2) -> 0 | AL41: =+SUM(AJ41:AK41) -> 0 | AN41: =MAX(0,MIN(IF($Y41<>"",$Y41,$S41),AN$1)-MAX($R41,EOMONTH(AN$1,-1)+1)+1) -> 30 | AO41: =ROUND(IF($Z41="",$T41,$Z41)*(AN41/IF($W41="",$Q41,$W41)),2) -> 10862.06 | AP41: =+ROUND(AO41*0.1,2) -> 1086.21 | AQ41: =+SUM(AO41:AP41) -> 11948.27 | AS41: =MAX(0,MIN(IF($Y41<>"",$Y41,$S41),AS$1)-MAX($R41,EOMONTH(AS$1,-1)+1)+1) -> 30 | AT41: =ROUND(IF($Z41="",$T41,$Z41)*(AS41/IF($W41="",$Q41,$W41)),2) -> 10862.06 | AU41: =+ROUND(AT41*0.1,2) -> 1086.21 | AV41: =+SUM(AT41:AU41) -> 11948.27 | AX41: =MAX(0,MIN(IF($Y41<>"",$Y41,$S41),AX$1)-MAX($R41,EOMONTH(AX$1,-1)+1)+1) -> 31 | AY41: =ROUND(IF($Z41="",$T41,$Z41)*(AX41/IF($W41="",$Q41,$W41)),2) -> 11224.13 | AZ41: =+ROUND(AY41*0.1,2) -> 1122.41 | BA41: =+SUM(AY41:AZ41) -> 12346.54 | BC41: =MAX(0,MIN(IF($Y41<>"",$Y41,$S41),BC$1)-MAX($R41,EOMONTH(BC$1,-1)+1)+1) -> 31 | BD41: =ROUND(IF($Z41="",$T41,$Z41)*(BC41/IF($W41="",$Q41,$W41)),2) -> 11224.13 | BE41: =+ROUND(BD41*0.1,2) -> 1122.41 | BF41: =+SUM(BD41:BE41) -> 12346.54 | BH41: =MAX(0,MIN(IF($Y41<>"",$Y41,$S41),BH$1)-MAX($R41,EOMONTH(BH$1,-1)+1)+1) -> 30 | BI41: =ROUND(IF($Z41="",$T41,$Z41)*(BH41/IF($W41="",$Q41,$W41)),2) -> 10862.06 | BJ41: =+ROUND(BI41*0.1,2) -> 1086.21 | BK41: =+SUM(BI41:BJ41) -> 11948.27 | BM41: =MAX(0,MIN(IF($Y41<>"",$Y41,$S41),BM$1)-MAX($R41,EOMONTH(BM$1,-1)+1)+1) -> 31 | BN41: =ROUND(IF($Z41="",$T41,$Z41)*(BM41/IF($W41="",$Q41,$W41)),2) -> 11224.13 | BO41: =+ROUND(BN41*0.1,2) -> 1122.41 | BP41: =+SUM(BN41:BO41) -> 12346.54 | BR41: =MAX(0,MIN(IF($Y41<>"",$Y41,$S41),BR$1)-MAX($R41,EOMONTH(BR$1,-1)+1)+1) -> 30 | BS41: =ROUND(IF($Z41="",$T41,$Z41)*(BR41/IF($W41="",$Q41,$W41)),2) -> 10862.06 | BT41: =+ROUND(BS41*0.1,2) -> 1086.21 | BU41: =+SUM(BS41:BT41) -> 11948.27 | BW41: =MAX(0,MIN(IF($Y41<>"",$Y41,$S41),BW$1)-MAX($R41,EOMONTH(BW$1,-1)+1)+1) -> 27 | BX41: =ROUND(IF($Z41="",$T41,$Z41)*(BW41/IF($W41="",$Q41,$W41)),2) -> 9775.86 | BY41: =+ROUND(BX41*0.1,2) -> 977.59 | BZ41: =+SUM(BX41:BY41) -> 10753.45 | CA41: =+AD41+AI41+AN41+AS41+AX41+BC41+BH41+BM41+BR41+BW41 -> 240 | CB41: =+AE41+AJ41+AO41+AT41+AY41+BD41+BI41+BN41+BS41+BX41 -> 86896.49 | CC41: =+AF41+AK41+AP41+AU41+AZ41+BE41+BJ41+BO41+BT41+BY41 -> 8689.66 | CD41: =+SUM(CB41:CC41) -> 95586.15 | CE41: =ROUND(IF($Y41<>"",$Z41,$T41)-CB41,2) -> 0.01 | CF41: =ROUND(IF($Y41<>"",$AA41,$U41)-CC41,2) -> -0.01 | CG41: IVP TACNA | CH41: John Lucero Vargas | CI41: Gerente | CJ41: 988 801 839 | CK41: Eddy Frank Coronado Choquecahua | CL41: Memorandum N° 007-2026-GG-IVPT | CM41: 46140 | CN41: 931 994 396
A42: 41 | B42: 204 | C42: TACNA | D42: TACNA | E42: LA YARADA Y LOS PALOS | F42: TA-643 | G42: EMP. PE-1SD - RANCHO GRANDE - PERPETUO SOCORRO - SAN PEDRO Y SAN PABLO - EMP. TA-644 (LOS PALOS) | H42: 17.52 | I42: PAVIMENTADO | J42: 887.5 | K42: 240 | L42: 124392 | M42: 12439 | N42: 136831 | O42: 0002-2026-IVPT | P42: COMERCIAL CYJSA E.I.R.L | Q42: =+$K42 -> 240 | R42: 46144 | S42: =IF(Q42+R42=0,"",Q42+R42-1) -> 46383 | T42: 118149.6 | U42: =+ROUND(T42*0.1,2) -> 11814.96 | V42: =+SUM(T42:U42) -> 129964.56 | X42: =+$R42 -> 46144 | Y42: =IF(W42>0,X42+W42-1,"") | AA42: =+ROUND(Z42*0.1,2) -> 0 | AB42: =+SUM(Z42:AA42) -> 0 | AD42: =MAX(0,MIN(IF($Y42<>"",$Y42,$S42),AD$1)-MAX($R42,EOMONTH(AD$1,-1)+1)+1) -> 0 | AE42: =ROUND(IF($Z42="",$T42,$Z42)*(AD42/IF($W42="",$Q42,$W42)),2) -> 0 | AF42: =+ROUND(AE42*0.1,2) -> 0 | AG42: =+SUM(AE42:AF42) -> 0 | AI42: =MAX(0,MIN(IF($Y42<>"",$Y42,$S42),AI$1)-MAX($R42,EOMONTH(AI$1,-1)+1)+1) -> 0 | AJ42: =ROUND(IF($Z42="",$T42,$Z42)*(AI42/IF($W42="",$Q42,$W42)),2) -> 0 | AK42: =+ROUND(AJ42*0.1,2) -> 0 | AL42: =+SUM(AJ42:AK42) -> 0 | AN42: =MAX(0,MIN(IF($Y42<>"",$Y42,$S42),AN$1)-MAX($R42,EOMONTH(AN$1,-1)+1)+1) -> 30 | AO42: =ROUND(IF($Z42="",$T42,$Z42)*(AN42/IF($W42="",$Q42,$W42)),2) -> 14768.7 | AP42: =+ROUND(AO42*0.1,2) -> 1476.87 | AQ42: =+SUM(AO42:AP42) -> 16245.57 | AS42: =MAX(0,MIN(IF($Y42<>"",$Y42,$S42),AS$1)-MAX($R42,EOMONTH(AS$1,-1)+1)+1) -> 30 | AT42: =ROUND(IF($Z42="",$T42,$Z42)*(AS42/IF($W42="",$Q42,$W42)),2) -> 14768.7 | AU42: =+ROUND(AT42*0.1,2) -> 1476.87 | AV42: =+SUM(AT42:AU42) -> 16245.57 | AX42: =MAX(0,MIN(IF($Y42<>"",$Y42,$S42),AX$1)-MAX($R42,EOMONTH(AX$1,-1)+1)+1) -> 31 | AY42: =ROUND(IF($Z42="",$T42,$Z42)*(AX42/IF($W42="",$Q42,$W42)),2) -> 15260.99 | AZ42: =+ROUND(AY42*0.1,2) -> 1526.1 | BA42: =+SUM(AY42:AZ42) -> 16787.09 | BC42: =MAX(0,MIN(IF($Y42<>"",$Y42,$S42),BC$1)-MAX($R42,EOMONTH(BC$1,-1)+1)+1) -> 31 | BD42: =ROUND(IF($Z42="",$T42,$Z42)*(BC42/IF($W42="",$Q42,$W42)),2) -> 15260.99 | BE42: =+ROUND(BD42*0.1,2) -> 1526.1 | BF42: =+SUM(BD42:BE42) -> 16787.09 | BH42: =MAX(0,MIN(IF($Y42<>"",$Y42,$S42),BH$1)-MAX($R42,EOMONTH(BH$1,-1)+1)+1) -> 30 | BI42: =ROUND(IF($Z42="",$T42,$Z42)*(BH42/IF($W42="",$Q42,$W42)),2) -> 14768.7 | BJ42: =+ROUND(BI42*0.1,2) -> 1476.87 | BK42: =+SUM(BI42:BJ42) -> 16245.57 | BM42: =MAX(0,MIN(IF($Y42<>"",$Y42,$S42),BM$1)-MAX($R42,EOMONTH(BM$1,-1)+1)+1) -> 31 | BN42: =ROUND(IF($Z42="",$T42,$Z42)*(BM42/IF($W42="",$Q42,$W42)),2) -> 15260.99 | BO42: =+ROUND(BN42*0.1,2) -> 1526.1 | BP42: =+SUM(BN42:BO42) -> 16787.09 | BR42: =MAX(0,MIN(IF($Y42<>"",$Y42,$S42),BR$1)-MAX($R42,EOMONTH(BR$1,-1)+1)+1) -> 30 | BS42: =ROUND(IF($Z42="",$T42,$Z42)*(BR42/IF($W42="",$Q42,$W42)),2) -> 14768.7 | BT42: =+ROUND(BS42*0.1,2) -> 1476.87 | BU42: =+SUM(BS42:BT42) -> 16245.57 | BW42: =MAX(0,MIN(IF($Y42<>"",$Y42,$S42),BW$1)-MAX($R42,EOMONTH(BW$1,-1)+1)+1) -> 27 | BX42: =ROUND(IF($Z42="",$T42,$Z42)*(BW42/IF($W42="",$Q42,$W42)),2) -> 13291.83 | BY42: =+ROUND(BX42*0.1,2) -> 1329.18 | BZ42: =+SUM(BX42:BY42) -> 14621.01 | CA42: =+AD42+AI42+AN42+AS42+AX42+BC42+BH42+BM42+BR42+BW42 -> 240 | CB42: =+AE42+AJ42+AO42+AT42+AY42+BD42+BI42+BN42+BS42+BX42 -> 118149.6 | CC42: =+AF42+AK42+AP42+AU42+AZ42+BE42+BJ42+BO42+BT42+BY42 -> 11814.96 | CD42: =+SUM(CB42:CC42) -> 129964.56 | CE42: =ROUND(IF($Y42<>"",$Z42,$T42)-CB42,2) -> 0 | CF42: =ROUND(IF($Y42<>"",$AA42,$U42)-CC42,2) -> 0 | CG42: IVP TACNA | CH42: John Lucero Vargas | CI42: Gerente | CJ42: 988 801 839 | CK42: Eddy Frank Coronado Choquecahua | CL42: Memorandum N° 007-2026-GG-IVPT | CM42: 46140 | CN42: 931 994 396
A43: 42 | B43: 204 | C43: TACNA | D43: TACNA | E43: LA YARADA Y LOS PALOS | F43: TA-644 | G43: ASOC. DE TRABAJADORES BIOHUERTO LOS PALOS (KM 09+450) - LAS LAGUNAS- PTE. LOS PALOS - EMP. TA-645 | H43: 14.4 | I43: PAVIMENTADO | J43: 887.5 | K43: 240 | L43: 102240 | M43: 10225 | N43: 112465 | O43: 0002-2026-IVPT | P43: COMERCIAL CYJSA E.I.R.L | Q43: =+$K43 -> 240 | R43: 46144 | S43: =IF(Q43+R43=0,"",Q43+R43-1) -> 46383 | T43: 97128 | U43: =+ROUND(T43*0.1,2) -> 9712.8 | V43: =+SUM(T43:U43) -> 106840.8 | X43: =+$R43 -> 46144 | Y43: =IF(W43>0,X43+W43-1,"") | AA43: =+ROUND(Z43*0.1,2) -> 0 | AB43: =+SUM(Z43:AA43) -> 0 | AD43: =MAX(0,MIN(IF($Y43<>"",$Y43,$S43),AD$1)-MAX($R43,EOMONTH(AD$1,-1)+1)+1) -> 0 | AE43: =ROUND(IF($Z43="",$T43,$Z43)*(AD43/IF($W43="",$Q43,$W43)),2) -> 0 | AF43: =+ROUND(AE43*0.1,2) -> 0 | AG43: =+SUM(AE43:AF43) -> 0 | AI43: =MAX(0,MIN(IF($Y43<>"",$Y43,$S43),AI$1)-MAX($R43,EOMONTH(AI$1,-1)+1)+1) -> 0 | AJ43: =ROUND(IF($Z43="",$T43,$Z43)*(AI43/IF($W43="",$Q43,$W43)),2) -> 0 | AK43: =+ROUND(AJ43*0.1,2) -> 0 | AL43: =+SUM(AJ43:AK43) -> 0 | AN43: =MAX(0,MIN(IF($Y43<>"",$Y43,$S43),AN$1)-MAX($R43,EOMONTH(AN$1,-1)+1)+1) -> 30 | AO43: =ROUND(IF($Z43="",$T43,$Z43)*(AN43/IF($W43="",$Q43,$W43)),2) -> 12141 | AP43: =+ROUND(AO43*0.1,2) -> 1214.1 | AQ43: =+SUM(AO43:AP43) -> 13355.1 | AS43: =MAX(0,MIN(IF($Y43<>"",$Y43,$S43),AS$1)-MAX($R43,EOMONTH(AS$1,-1)+1)+1) -> 30 | AT43: =ROUND(IF($Z43="",$T43,$Z43)*(AS43/IF($W43="",$Q43,$W43)),2) -> 12141 | AU43: =+ROUND(AT43*0.1,2) -> 1214.1 | AV43: =+SUM(AT43:AU43) -> 13355.1 | AX43: =MAX(0,MIN(IF($Y43<>"",$Y43,$S43),AX$1)-MAX($R43,EOMONTH(AX$1,-1)+1)+1) -> 31 | AY43: =ROUND(IF($Z43="",$T43,$Z43)*(AX43/IF($W43="",$Q43,$W43)),2) -> 12545.7 | AZ43: =+ROUND(AY43*0.1,2) -> 1254.57 | BA43: =+SUM(AY43:AZ43) -> 13800.27 | BC43: =MAX(0,MIN(IF($Y43<>"",$Y43,$S43),BC$1)-MAX($R43,EOMONTH(BC$1,-1)+1)+1) -> 31 | BD43: =ROUND(IF($Z43="",$T43,$Z43)*(BC43/IF($W43="",$Q43,$W43)),2) -> 12545.7 | BE43: =+ROUND(BD43*0.1,2) -> 1254.57 | BF43: =+SUM(BD43:BE43) -> 13800.27 | BH43: =MAX(0,MIN(IF($Y43<>"",$Y43,$S43),BH$1)-MAX($R43,EOMONTH(BH$1,-1)+1)+1) -> 30 | BI43: =ROUND(IF($Z43="",$T43,$Z43)*(BH43/IF($W43="",$Q43,$W43)),2) -> 12141 | BJ43: =+ROUND(BI43*0.1,2) -> 1214.1 | BK43: =+SUM(BI43:BJ43) -> 13355.1 | BM43: =MAX(0,MIN(IF($Y43<>"",$Y43,$S43),BM$1)-MAX($R43,EOMONTH(BM$1,-1)+1)+1) -> 31 | BN43: =ROUND(IF($Z43="",$T43,$Z43)*(BM43/IF($W43="",$Q43,$W43)),2) -> 12545.7 | BO43: =+ROUND(BN43*0.1,2) -> 1254.57 | BP43: =+SUM(BN43:BO43) -> 13800.27 | BR43: =MAX(0,MIN(IF($Y43<>"",$Y43,$S43),BR$1)-MAX($R43,EOMONTH(BR$1,-1)+1)+1) -> 30 | BS43: =ROUND(IF($Z43="",$T43,$Z43)*(BR43/IF($W43="",$Q43,$W43)),2) -> 12141 | BT43: =+ROUND(BS43*0.1,2) -> 1214.1 | BU43: =+SUM(BS43:BT43) -> 13355.1 | BW43: =MAX(0,MIN(IF($Y43<>"",$Y43,$S43),BW$1)-MAX($R43,EOMONTH(BW$1,-1)+1)+1) -> 27 | BX43: =ROUND(IF($Z43="",$T43,$Z43)*(BW43/IF($W43="",$Q43,$W43)),2) -> 10926.9 | BY43: =+ROUND(BX43*0.1,2) -> 1092.69 | BZ43: =+SUM(BX43:BY43) -> 12019.59 | CA43: =+AD43+AI43+AN43+AS43+AX43+BC43+BH43+BM43+BR43+BW43 -> 240 | CB43: =+AE43+AJ43+AO43+AT43+AY43+BD43+BI43+BN43+BS43+BX43 -> 97128 | CC43: =+AF43+AK43+AP43+AU43+AZ43+BE43+BJ43+BO43+BT43+BY43 -> 9712.8 | CD43: =+SUM(CB43:CC43) -> 106840.8 | CE43: =ROUND(IF($Y43<>"",$Z43,$T43)-CB43,2) -> 0 | CF43: =ROUND(IF($Y43<>"",$AA43,$U43)-CC43,2) -> 0 | CG43: IVP TACNA | CH43: John Lucero Vargas | CI43: Gerente | CJ43: 988 801 839 | CK43: Eddy Frank Coronado Choquecahua | CL43: Memorandum N° 007-2026-GG-IVPT | CM43: 46140 | CN43: 931 994 396
A44: 43 | B44: 204 | C44: TACNA | D44: TACNA | E44: LA YARADA Y LOS PALOS | F44: TA-645 | G44: EMP. PE-1S (COMPLEJO SANTA ROSA) - LAS PALMERAS - PTA. CARRETERA (KM 09+030) | H44: 9.03 | I44: PAVIMENTADO | J44: 887.5 | K44: 240 | L44: 64113 | M44: 6411 | N44: 70524 | O44: 0002-2026-IVPT | P44: COMERCIAL CYJSA E.I.R.L | Q44: =+$K44 -> 240 | R44: 46144 | S44: =IF(Q44+R44=0,"",Q44+R44-1) -> 46383 | T44: 60907.04 | U44: =+ROUND(T44*0.1,2) -> 6090.7 | V44: =+SUM(T44:U44) -> 66997.74 | X44: =+$R44 -> 46144 | Y44: =IF(W44>0,X44+W44-1,"") | AA44: =+ROUND(Z44*0.1,2) -> 0 | AB44: =+SUM(Z44:AA44) -> 0 | AD44: =MAX(0,MIN(IF($Y44<>"",$Y44,$S44),AD$1)-MAX($R44,EOMONTH(AD$1,-1)+1)+1) -> 0 | AE44: =ROUND(IF($Z44="",$T44,$Z44)*(AD44/IF($W44="",$Q44,$W44)),2) -> 0 | AF44: =+ROUND(AE44*0.1,2) -> 0 | AG44: =+SUM(AE44:AF44) -> 0 | AI44: =MAX(0,MIN(IF($Y44<>"",$Y44,$S44),AI$1)-MAX($R44,EOMONTH(AI$1,-1)+1)+1) -> 0 | AJ44: =ROUND(IF($Z44="",$T44,$Z44)*(AI44/IF($W44="",$Q44,$W44)),2) -> 0 | AK44: =+ROUND(AJ44*0.1,2) -> 0 | AL44: =+SUM(AJ44:AK44) -> 0 | AN44: =MAX(0,MIN(IF($Y44<>"",$Y44,$S44),AN$1)-MAX($R44,EOMONTH(AN$1,-1)+1)+1) -> 30 | AO44: =ROUND(IF($Z44="",$T44,$Z44)*(AN44/IF($W44="",$Q44,$W44)),2) -> 7613.38 | AP44: =+ROUND(AO44*0.1,2) -> 761.34 | AQ44: =+SUM(AO44:AP44) -> 8374.72 | AS44: =MAX(0,MIN(IF($Y44<>"",$Y44,$S44),AS$1)-MAX($R44,EOMONTH(AS$1,-1)+1)+1) -> 30 | AT44: =ROUND(IF($Z44="",$T44,$Z44)*(AS44/IF($W44="",$Q44,$W44)),2) -> 7613.38 | AU44: =+ROUND(AT44*0.1,2) -> 761.34 | AV44: =+SUM(AT44:AU44) -> 8374.72 | AX44: =MAX(0,MIN(IF($Y44<>"",$Y44,$S44),AX$1)-MAX($R44,EOMONTH(AX$1,-1)+1)+1) -> 31 | AY44: =ROUND(IF($Z44="",$T44,$Z44)*(AX44/IF($W44="",$Q44,$W44)),2) -> 7867.16 | AZ44: =+ROUND(AY44*0.1,2) -> 786.72 | BA44: =+SUM(AY44:AZ44) -> 8653.88 | BC44: =MAX(0,MIN(IF($Y44<>"",$Y44,$S44),BC$1)-MAX($R44,EOMONTH(BC$1,-1)+1)+1) -> 31 | BD44: =ROUND(IF($Z44="",$T44,$Z44)*(BC44/IF($W44="",$Q44,$W44)),2) -> 7867.16 | BE44: =+ROUND(BD44*0.1,2) -> 786.72 | BF44: =+SUM(BD44:BE44) -> 8653.88 | BH44: =MAX(0,MIN(IF($Y44<>"",$Y44,$S44),BH$1)-MAX($R44,EOMONTH(BH$1,-1)+1)+1) -> 30 | BI44: =ROUND(IF($Z44="",$T44,$Z44)*(BH44/IF($W44="",$Q44,$W44)),2) -> 7613.38 | BJ44: =+ROUND(BI44*0.1,2) -> 761.34 | BK44: =+SUM(BI44:BJ44) -> 8374.72 | BM44: =MAX(0,MIN(IF($Y44<>"",$Y44,$S44),BM$1)-MAX($R44,EOMONTH(BM$1,-1)+1)+1) -> 31 | BN44: =ROUND(IF($Z44="",$T44,$Z44)*(BM44/IF($W44="",$Q44,$W44)),2) -> 7867.16 | BO44: =+ROUND(BN44*0.1,2) -> 786.72 | BP44: =+SUM(BN44:BO44) -> 8653.88 | BR44: =MAX(0,MIN(IF($Y44<>"",$Y44,$S44),BR$1)-MAX($R44,EOMONTH(BR$1,-1)+1)+1) -> 30 | BS44: =ROUND(IF($Z44="",$T44,$Z44)*(BR44/IF($W44="",$Q44,$W44)),2) -> 7613.38 | BT44: =+ROUND(BS44*0.1,2) -> 761.34 | BU44: =+SUM(BS44:BT44) -> 8374.72 | BW44: =MAX(0,MIN(IF($Y44<>"",$Y44,$S44),BW$1)-MAX($R44,EOMONTH(BW$1,-1)+1)+1) -> 27 | BX44: =ROUND(IF($Z44="",$T44,$Z44)*(BW44/IF($W44="",$Q44,$W44)),2) -> 6852.04 | BY44: =+ROUND(BX44*0.1,2) -> 685.2 | BZ44: =+SUM(BX44:BY44) -> 7537.24 | CA44: =+AD44+AI44+AN44+AS44+AX44+BC44+BH44+BM44+BR44+BW44 -> 240 | CB44: =+AE44+AJ44+AO44+AT44+AY44+BD44+BI44+BN44+BS44+BX44 -> 60907.04 | CC44: =+AF44+AK44+AP44+AU44+AZ44+BE44+BJ44+BO44+BT44+BY44 -> 6090.72 | CD44: =+SUM(CB44:CC44) -> 66997.76 | CE44: =ROUND(IF($Y44<>"",$Z44,$T44)-CB44,2) -> 0 | CF44: =ROUND(IF($Y44<>"",$AA44,$U44)-CC44,2) -> -0.02 | CG44: IVP TACNA | CH44: John Lucero Vargas | CI44: Gerente | CJ44: 988 801 839 | CK44: Eddy Frank Coronado Choquecahua | CL44: Memorandum N° 007-2026-GG-IVPT | CM44: 46140 | CN44: 931 994 396
A45: 44 | B45: 204 | C45: TACNA | D45: TACNA | E45: LA YARADA Y LOS PALOS | F45: R230145 | G45: EMP. PE-1SD-ANDAMARCA - ZONA Z -EMP.TA-642 | H45: 12.56 | I45: PAVIMENTADO | J45: 887.5 | K45: 240 | L45: 89176 | M45: 8918 | N45: 98094 | O45: 0002-2026-IVPT | P45: COMERCIAL CYJSA E.I.R.L | Q45: =+$K45 -> 240 | R45: 46144 | S45: =IF(Q45+R45=0,"",Q45+R45-1) -> 46383 | T45: 84711.5 | U45: =+ROUND(T45*0.1,2) -> 8471.15 | V45: =+SUM(T45:U45) -> 93182.65 | X45: =+$R45 -> 46144 | Y45: =IF(W45>0,X45+W45-1,"") | AA45: =+ROUND(Z45*0.1,2) -> 0 | AB45: =+SUM(Z45:AA45) -> 0 | AD45: =MAX(0,MIN(IF($Y45<>"",$Y45,$S45),AD$1)-MAX($R45,EOMONTH(AD$1,-1)+1)+1) -> 0 | AE45: =ROUND(IF($Z45="",$T45,$Z45)*(AD45/IF($W45="",$Q45,$W45)),2) -> 0 | AF45: =+ROUND(AE45*0.1,2) -> 0 | AG45: =+SUM(AE45:AF45) -> 0 | AI45: =MAX(0,MIN(IF($Y45<>"",$Y45,$S45),AI$1)-MAX($R45,EOMONTH(AI$1,-1)+1)+1) -> 0 | AJ45: =ROUND(IF($Z45="",$T45,$Z45)*(AI45/IF($W45="",$Q45,$W45)),2) -> 0 | AK45: =+ROUND(AJ45*0.1,2) -> 0 | AL45: =+SUM(AJ45:AK45) -> 0 | AN45: =MAX(0,MIN(IF($Y45<>"",$Y45,$S45),AN$1)-MAX($R45,EOMONTH(AN$1,-1)+1)+1) -> 30 | AO45: =ROUND(IF($Z45="",$T45,$Z45)*(AN45/IF($W45="",$Q45,$W45)),2) -> 10588.94 | AP45: =+ROUND(AO45*0.1,2) -> 1058.89 | AQ45: =+SUM(AO45:AP45) -> 11647.83 | AS45: =MAX(0,MIN(IF($Y45<>"",$Y45,$S45),AS$1)-MAX($R45,EOMONTH(AS$1,-1)+1)+1) -> 30 | AT45: =ROUND(IF($Z45="",$T45,$Z45)*(AS45/IF($W45="",$Q45,$W45)),2) -> 10588.94 | AU45: =+ROUND(AT45*0.1,2) -> 1058.89 | AV45: =+SUM(AT45:AU45) -> 11647.83 | AX45: =MAX(0,MIN(IF($Y45<>"",$Y45,$S45),AX$1)-MAX($R45,EOMONTH(AX$1,-1)+1)+1) -> 31 | AY45: =ROUND(IF($Z45="",$T45,$Z45)*(AX45/IF($W45="",$Q45,$W45)),2) -> 10941.9 | AZ45: =+ROUND(AY45*0.1,2) -> 1094.19 | BA45: =+SUM(AY45:AZ45) -> 12036.09 | BC45: =MAX(0,MIN(IF($Y45<>"",$Y45,$S45),BC$1)-MAX($R45,EOMONTH(BC$1,-1)+1)+1) -> 31 | BD45: =ROUND(IF($Z45="",$T45,$Z45)*(BC45/IF($W45="",$Q45,$W45)),2) -> 10941.9 | BE45: =+ROUND(BD45*0.1,2) -> 1094.19 | BF45: =+SUM(BD45:BE45) -> 12036.09 | BH45: =MAX(0,MIN(IF($Y45<>"",$Y45,$S45),BH$1)-MAX($R45,EOMONTH(BH$1,-1)+1)+1) -> 30 | BI45: =ROUND(IF($Z45="",$T45,$Z45)*(BH45/IF($W45="",$Q45,$W45)),2) -> 10588.94 | BJ45: =+ROUND(BI45*0.1,2) -> 1058.89 | BK45: =+SUM(BI45:BJ45) -> 11647.83 | BM45: =MAX(0,MIN(IF($Y45<>"",$Y45,$S45),BM$1)-MAX($R45,EOMONTH(BM$1,-1)+1)+1) -> 31 | BN45: =ROUND(IF($Z45="",$T45,$Z45)*(BM45/IF($W45="",$Q45,$W45)),2) -> 10941.9 | BO45: =+ROUND(BN45*0.1,2) -> 1094.19 | BP45: =+SUM(BN45:BO45) -> 12036.09 | BR45: =MAX(0,MIN(IF($Y45<>"",$Y45,$S45),BR$1)-MAX($R45,EOMONTH(BR$1,-1)+1)+1) -> 30 | BS45: =ROUND(IF($Z45="",$T45,$Z45)*(BR45/IF($W45="",$Q45,$W45)),2) -> 10588.94 | BT45: =+ROUND(BS45*0.1,2) -> 1058.89 | BU45: =+SUM(BS45:BT45) -> 11647.83 | BW45: =MAX(0,MIN(IF($Y45<>"",$Y45,$S45),BW$1)-MAX($R45,EOMONTH(BW$1,-1)+1)+1) -> 27 | BX45: =ROUND(IF($Z45="",$T45,$Z45)*(BW45/IF($W45="",$Q45,$W45)),2) -> 9530.04 | BY45: =+ROUND(BX45*0.1,2) -> 953 | BZ45: =+SUM(BX45:BY45) -> 10483.04 | CA45: =+AD45+AI45+AN45+AS45+AX45+BC45+BH45+BM45+BR45+BW45 -> 240 | CB45: =+AE45+AJ45+AO45+AT45+AY45+BD45+BI45+BN45+BS45+BX45 -> 84711.5 | CC45: =+AF45+AK45+AP45+AU45+AZ45+BE45+BJ45+BO45+BT45+BY45 -> 8471.13 | CD45: =+SUM(CB45:CC45) -> 93182.63 | CE45: =ROUND(IF($Y45<>"",$Z45,$T45)-CB45,2) -> 0 | CF45: =ROUND(IF($Y45<>"",$AA45,$U45)-CC45,2) -> 0.02 | CG45: IVP TACNA | CH45: John Lucero Vargas | CI45: Gerente | CJ45: 988 801 839 | CK45: Eddy Frank Coronado Choquecahua | CL45: Memorandum N° 007-2026-GG-IVPT | CM45: 46140 | CN45: 931 994 396
A46: 45 | B46: 203 | C46: TACNA | D46: TARATA | E46: SUSAPAYA TARATA TICACO | F46: TA-557 | G46: EMP. PE-38 -DV.SANTA LUCIA - JARUMAS - CULLCO - ANCOYANE- EMP. TA-556 (CANO). | H46: 26.9 | I46: AFIRMADO | J46: 735 | K46: 240 | L46: 158172 | M46: 15817 | N46: 173989 | O46: 001-2026-MPT | P46: MF SOLUCIONES VIALES E.I.R.L | Q46: =+$K46 -> 240 | R46: 46162 | S46: =IF(Q46+R46=0,"",Q46+R46-1) -> 46401 | T46: 150263.4 | U46: =+ROUND(T46*0.1,2) -> 15026.34 | V46: =+SUM(T46:U46) -> 165289.74 | W46: 222 | X46: =+$R46 -> 46162 | Y46: =IF(W46>0,X46+W46-1,"") -> 46383 | Z46: 138993.65 | AA46: =+ROUND(Z46*0.1,2) -> 13899.37 | AB46: =+SUM(Z46:AA46) -> 152893.02 | AD46: =MAX(0,MIN(IF($Y46<>"",$Y46,$S46),AD$1)-MAX($R46,EOMONTH(AD$1,-1)+1)+1) -> 0 | AE46: =ROUND(IF($Z46="",$T46,$Z46)*(AD46/IF($W46="",$Q46,$W46)),2) -> 0 | AF46: =+ROUND(AE46*0.1,2) -> 0 | AG46: =+SUM(AE46:AF46) -> 0 | AI46: =MAX(0,MIN(IF($Y46<>"",$Y46,$S46),AI$1)-MAX($R46,EOMONTH(AI$1,-1)+1)+1) -> 0 | AJ46: =ROUND(IF($Z46="",$T46,$Z46)*(AI46/IF($W46="",$Q46,$W46)),2) -> 0 | AK46: =+ROUND(AJ46*0.1,2) -> 0 | AL46: =+SUM(AJ46:AK46) -> 0 | AN46: =MAX(0,MIN(IF($Y46<>"",$Y46,$S46),AN$1)-MAX($R46,EOMONTH(AN$1,-1)+1)+1) -> 12 | AO46: =ROUND(IF($Z46="",$T46,$Z46)*(AN46/IF($W46="",$Q46,$W46)),2) -> 7513.17 | AP46: =+ROUND(AO46*0.1,2) -> 751.32 | AQ46: =+SUM(AO46:AP46) -> 8264.49 | AS46: =MAX(0,MIN(IF($Y46<>"",$Y46,$S46),AS$1)-MAX($R46,EOMONTH(AS$1,-1)+1)+1) -> 30 | AT46: =ROUND(IF($Z46="",$T46,$Z46)*(AS46/IF($W46="",$Q46,$W46)),2) -> 18782.93 | AU46: =+ROUND(AT46*0.1,2) -> 1878.29 | AV46: =+SUM(AT46:AU46) -> 20661.22 | AX46: =MAX(0,MIN(IF($Y46<>"",$Y46,$S46),AX$1)-MAX($R46,EOMONTH(AX$1,-1)+1)+1) -> 31 | AY46: =ROUND(IF($Z46="",$T46,$Z46)*(AX46/IF($W46="",$Q46,$W46)),2) -> 19409.02 | AZ46: =+ROUND(AY46*0.1,2) -> 1940.9 | BA46: =+SUM(AY46:AZ46) -> 21349.92 | BC46: =MAX(0,MIN(IF($Y46<>"",$Y46,$S46),BC$1)-MAX($R46,EOMONTH(BC$1,-1)+1)+1) -> 31 | BD46: =ROUND(IF($Z46="",$T46,$Z46)*(BC46/IF($W46="",$Q46,$W46)),2) -> 19409.02 | BE46: =+ROUND(BD46*0.1,2) -> 1940.9 | BF46: =+SUM(BD46:BE46) -> 21349.92 | BH46: =MAX(0,MIN(IF($Y46<>"",$Y46,$S46),BH$1)-MAX($R46,EOMONTH(BH$1,-1)+1)+1) -> 30 | BI46: =ROUND(IF($Z46="",$T46,$Z46)*(BH46/IF($W46="",$Q46,$W46)),2) -> 18782.93 | BJ46: =+ROUND(BI46*0.1,2) -> 1878.29 | BK46: =+SUM(BI46:BJ46) -> 20661.22 | BM46: =MAX(0,MIN(IF($Y46<>"",$Y46,$S46),BM$1)-MAX($R46,EOMONTH(BM$1,-1)+1)+1) -> 31 | BN46: =ROUND(IF($Z46="",$T46,$Z46)*(BM46/IF($W46="",$Q46,$W46)),2) -> 19409.02 | BO46: =+ROUND(BN46*0.1,2) -> 1940.9 | BP46: =+SUM(BN46:BO46) -> 21349.92 | BR46: =MAX(0,MIN(IF($Y46<>"",$Y46,$S46),BR$1)-MAX($R46,EOMONTH(BR$1,-1)+1)+1) -> 30 | BS46: =ROUND(IF($Z46="",$T46,$Z46)*(BR46/IF($W46="",$Q46,$W46)),2) -> 18782.93 | BT46: =+ROUND(BS46*0.1,2) -> 1878.29 | BU46: =+SUM(BS46:BT46) -> 20661.22 | BW46: =MAX(0,MIN(IF($Y46<>"",$Y46,$S46),BW$1)-MAX($R46,EOMONTH(BW$1,-1)+1)+1) -> 27 | BX46: =ROUND(IF($Z46="",$T46,$Z46)*(BW46/IF($W46="",$Q46,$W46)),2) -> 16904.63 | BY46: =+ROUND(BX46*0.1,2) -> 1690.46 | BZ46: =+SUM(BX46:BY46) -> 18595.09 | CA46: =+AD46+AI46+AN46+AS46+AX46+BC46+BH46+BM46+BR46+BW46 -> 222 | CB46: =+AE46+AJ46+AO46+AT46+AY46+BD46+BI46+BN46+BS46+BX46 -> 138993.65 | CC46: =+AF46+AK46+AP46+AU46+AZ46+BE46+BJ46+BO46+BT46+BY46 -> 13899.35 | CD46: =+SUM(CB46:CC46) -> 152893 | CE46: =ROUND(IF($Y46<>"",$Z46,$T46)-CB46,2) -> 0 | CF46: =ROUND(IF($Y46<>"",$AA46,$U46)-CC46,2) -> 0.02 | CG46: IVP TARATA | CH46: Hugo Wilfredo Pilco Pari | CI46: Gerente | CJ46: 952 659 584 | CK46: Renzo Francisco Alave Alarcon | CL46: RGM N° 123-2026-GM/MPT | CM46: 46175 | CN46: 993 867 336
A47: 46 | B47: 203 | C47: TACNA | D47: TARATA | E47: SUSAPAYA | F47: R230450 | G47: EMP. TA-556 - SECTOR HUANUNE - SECTOR HUAILLAVIRA (KM 05+150) | H47: 5.15 | I47: AFIRMADO | J47: 735 | K47: 240 | L47: 30282 | M47: 3028 | N47: 33310 | O47: 0000207-2026 | P47: MF SOLUCIONES VIALES E.I.R.L | Q47: =+$K47 -> 240 | R47: 46113 | S47: =IF(Q47+R47=0,"",Q47+R47-1) -> 46352 | T47: 30280 | U47: =+ROUND(T47*0.1,2) -> 3028 | V47: =+SUM(T47:U47) -> 33308 | X47: =+$R47 -> 46113 | Y47: =IF(W47>0,X47+W47-1,"") | AA47: =+ROUND(Z47*0.1,2) -> 0 | AB47: =+SUM(Z47:AA47) -> 0 | AD47: =MAX(0,MIN(IF($Y47<>"",$Y47,$S47),AD$1)-MAX($R47,EOMONTH(AD$1,-1)+1)+1) -> 0 | AE47: =ROUND(IF($Z47="",$T47,$Z47)*(AD47/IF($W47="",$Q47,$W47)),2) -> 0 | AF47: =+ROUND(AE47*0.1,2) -> 0 | AG47: =+SUM(AE47:AF47) -> 0 | AI47: =MAX(0,MIN(IF($Y47<>"",$Y47,$S47),AI$1)-MAX($R47,EOMONTH(AI$1,-1)+1)+1) -> 30 | AJ47: =ROUND(IF($Z47="",$T47,$Z47)*(AI47/IF($W47="",$Q47,$W47)),2) -> 3785 | AK47: =+ROUND(AJ47*0.1,2) -> 378.5 | AL47: =+SUM(AJ47:AK47) -> 4163.5 | AN47: =MAX(0,MIN(IF($Y47<>"",$Y47,$S47),AN$1)-MAX($R47,EOMONTH(AN$1,-1)+1)+1) -> 31 | AO47: =ROUND(IF($Z47="",$T47,$Z47)*(AN47/IF($W47="",$Q47,$W47)),2) -> 3911.17 | AP47: =+ROUND(AO47*0.1,2) -> 391.12 | AQ47: =+SUM(AO47:AP47) -> 4302.29 | AS47: =MAX(0,MIN(IF($Y47<>"",$Y47,$S47),AS$1)-MAX($R47,EOMONTH(AS$1,-1)+1)+1) -> 30 | AT47: =ROUND(IF($Z47="",$T47,$Z47)*(AS47/IF($W47="",$Q47,$W47)),2) -> 3785 | AU47: =+ROUND(AT47*0.1,2) -> 378.5 | AV47: =+SUM(AT47:AU47) -> 4163.5 | AX47: =MAX(0,MIN(IF($Y47<>"",$Y47,$S47),AX$1)-MAX($R47,EOMONTH(AX$1,-1)+1)+1) -> 31 | AY47: =ROUND(IF($Z47="",$T47,$Z47)*(AX47/IF($W47="",$Q47,$W47)),2) -> 3911.17 | AZ47: =+ROUND(AY47*0.1,2) -> 391.12 | BA47: =+SUM(AY47:AZ47) -> 4302.29 | BC47: =MAX(0,MIN(IF($Y47<>"",$Y47,$S47),BC$1)-MAX($R47,EOMONTH(BC$1,-1)+1)+1) -> 31 | BD47: =ROUND(IF($Z47="",$T47,$Z47)*(BC47/IF($W47="",$Q47,$W47)),2) -> 3911.17 | BE47: =+ROUND(BD47*0.1,2) -> 391.12 | BF47: =+SUM(BD47:BE47) -> 4302.29 | BH47: =MAX(0,MIN(IF($Y47<>"",$Y47,$S47),BH$1)-MAX($R47,EOMONTH(BH$1,-1)+1)+1) -> 30 | BI47: =ROUND(IF($Z47="",$T47,$Z47)*(BH47/IF($W47="",$Q47,$W47)),2) -> 3785 | BJ47: =+ROUND(BI47*0.1,2) -> 378.5 | BK47: =+SUM(BI47:BJ47) -> 4163.5 | BM47: =MAX(0,MIN(IF($Y47<>"",$Y47,$S47),BM$1)-MAX($R47,EOMONTH(BM$1,-1)+1)+1) -> 31 | BN47: =ROUND(IF($Z47="",$T47,$Z47)*(BM47/IF($W47="",$Q47,$W47)),2) -> 3911.17 | BO47: =+ROUND(BN47*0.1,2) -> 391.12 | BP47: =+SUM(BN47:BO47) -> 4302.29 | BR47: =MAX(0,MIN(IF($Y47<>"",$Y47,$S47),BR$1)-MAX($R47,EOMONTH(BR$1,-1)+1)+1) -> 26 | BS47: =ROUND(IF($Z47="",$T47,$Z47)*(BR47/IF($W47="",$Q47,$W47)),2) -> 3280.33 | BT47: =+ROUND(BS47*0.1,2) -> 328.03 | BU47: =+SUM(BS47:BT47) -> 3608.36 | BW47: =MAX(0,MIN(IF($Y47<>"",$Y47,$S47),BW$1)-MAX($R47,EOMONTH(BW$1,-1)+1)+1) -> 0 | BX47: =ROUND(IF($Z47="",$T47,$Z47)*(BW47/IF($W47="",$Q47,$W47)),2) -> 0 | BY47: =+ROUND(BX47*0.1,2) -> 0 | BZ47: =+SUM(BX47:BY47) -> 0 | CA47: =+AD47+AI47+AN47+AS47+AX47+BC47+BH47+BM47+BR47+BW47 -> 240 | CB47: =+AE47+AJ47+AO47+AT47+AY47+BD47+BI47+BN47+BS47+BX47 -> 30280.01 | CC47: =+AF47+AK47+AP47+AU47+AZ47+BE47+BJ47+BO47+BT47+BY47 -> 3028.01 | CD47: =+SUM(CB47:CC47) -> 33308.02 | CE47: =ROUND(IF($Y47<>"",$Z47,$T47)-CB47,2) -> -0.01 | CF47: =ROUND(IF($Y47<>"",$AA47,$U47)-CC47,2) -> -0.01 | CG47: IVP TARATA | CH47: Hugo Wilfredo Pilco Pari | CI47: Gerente | CJ47: 952 659 584 | CK47: Renzo Francisco Alave Alarcon | CL47: RGM N° 123-2026-GM/MPT | CM47: 46175 | CN47: 993 867 336
A48: 47 | B48: 203 | C48: TACNA | D48: TARATA | E48: TARATA | F48: TA-563 | G48: EMP. TA-107- CORACORANI | H48: 9.364 | I48: AFIRMADO | J48: 735 | K48: 240 | L48: 55060 | M48: 5506 | N48: 60566 | O48: 0000209-2026 | P48: MF SOLUCIONES VIALES E.I.R.L | Q48: =+$K48 -> 240 | R48: 46113 | S48: =IF(Q48+R48=0,"",Q48+R48-1) -> 46352 | T48: 44000 | U48: =+ROUND(T48*0.1,2) -> 4400 | V48: =+SUM(T48:U48) -> 48400 | X48: =+$R48 -> 46113 | Y48: =IF(W48>0,X48+W48-1,"") | AA48: =+ROUND(Z48*0.1,2) -> 0 | AB48: =+SUM(Z48:AA48) -> 0 | AD48: =MAX(0,MIN(IF($Y48<>"",$Y48,$S48),AD$1)-MAX($R48,EOMONTH(AD$1,-1)+1)+1) -> 0 | AE48: =ROUND(IF($Z48="",$T48,$Z48)*(AD48/IF($W48="",$Q48,$W48)),2) -> 0 | AF48: =+ROUND(AE48*0.1,2) -> 0 | AG48: =+SUM(AE48:AF48) -> 0 | AI48: =MAX(0,MIN(IF($Y48<>"",$Y48,$S48),AI$1)-MAX($R48,EOMONTH(AI$1,-1)+1)+1) -> 30 | AJ48: =ROUND(IF($Z48="",$T48,$Z48)*(AI48/IF($W48="",$Q48,$W48)),2) -> 5500 | AK48: =+ROUND(AJ48*0.1,2) -> 550 | AL48: =+SUM(AJ48:AK48) -> 6050 | AN48: =MAX(0,MIN(IF($Y48<>"",$Y48,$S48),AN$1)-MAX($R48,EOMONTH(AN$1,-1)+1)+1) -> 31 | AO48: =ROUND(IF($Z48="",$T48,$Z48)*(AN48/IF($W48="",$Q48,$W48)),2) -> 5683.33 | AP48: =+ROUND(AO48*0.1,2) -> 568.33 | AQ48: =+SUM(AO48:AP48) -> 6251.66 | AS48: =MAX(0,MIN(IF($Y48<>"",$Y48,$S48),AS$1)-MAX($R48,EOMONTH(AS$1,-1)+1)+1) -> 30 | AT48: =ROUND(IF($Z48="",$T48,$Z48)*(AS48/IF($W48="",$Q48,$W48)),2) -> 5500 | AU48: =+ROUND(AT48*0.1,2) -> 550 | AV48: =+SUM(AT48:AU48) -> 6050 | AX48: =MAX(0,MIN(IF($Y48<>"",$Y48,$S48),AX$1)-MAX($R48,EOMONTH(AX$1,-1)+1)+1) -> 31 | AY48: =ROUND(IF($Z48="",$T48,$Z48)*(AX48/IF($W48="",$Q48,$W48)),2) -> 5683.33 | AZ48: =+ROUND(AY48*0.1,2) -> 568.33 | BA48: =+SUM(AY48:AZ48) -> 6251.66 | BC48: =MAX(0,MIN(IF($Y48<>"",$Y48,$S48),BC$1)-MAX($R48,EOMONTH(BC$1,-1)+1)+1) -> 31 | BD48: =ROUND(IF($Z48="",$T48,$Z48)*(BC48/IF($W48="",$Q48,$W48)),2) -> 5683.33 | BE48: =+ROUND(BD48*0.1,2) -> 568.33 | BF48: =+SUM(BD48:BE48) -> 6251.66 | BH48: =MAX(0,MIN(IF($Y48<>"",$Y48,$S48),BH$1)-MAX($R48,EOMONTH(BH$1,-1)+1)+1) -> 30 | BI48: =ROUND(IF($Z48="",$T48,$Z48)*(BH48/IF($W48="",$Q48,$W48)),2) -> 5500 | BJ48: =+ROUND(BI48*0.1,2) -> 550 | BK48: =+SUM(BI48:BJ48) -> 6050 | BM48: =MAX(0,MIN(IF($Y48<>"",$Y48,$S48),BM$1)-MAX($R48,EOMONTH(BM$1,-1)+1)+1) -> 31 | BN48: =ROUND(IF($Z48="",$T48,$Z48)*(BM48/IF($W48="",$Q48,$W48)),2) -> 5683.33 | BO48: =+ROUND(BN48*0.1,2) -> 568.33 | BP48: =+SUM(BN48:BO48) -> 6251.66 | BR48: =MAX(0,MIN(IF($Y48<>"",$Y48,$S48),BR$1)-MAX($R48,EOMONTH(BR$1,-1)+1)+1) -> 26 | BS48: =ROUND(IF($Z48="",$T48,$Z48)*(BR48/IF($W48="",$Q48,$W48)),2) -> 4766.67 | BT48: =+ROUND(BS48*0.1,2) -> 476.67 | BU48: =+SUM(BS48:BT48) -> 5243.34 | BW48: =MAX(0,MIN(IF($Y48<>"",$Y48,$S48),BW$1)-MAX($R48,EOMONTH(BW$1,-1)+1)+1) -> 0 | BX48: =ROUND(IF($Z48="",$T48,$Z48)*(BW48/IF($W48="",$Q48,$W48)),2) -> 0 | BY48: =+ROUND(BX48*0.1,2) -> 0 | BZ48: =+SUM(BX48:BY48) -> 0 | CA48: =+AD48+AI48+AN48+AS48+AX48+BC48+BH48+BM48+BR48+BW48 -> 240 | CB48: =+AE48+AJ48+AO48+AT48+AY48+BD48+BI48+BN48+BS48+BX48 -> 43999.99 | CC48: =+AF48+AK48+AP48+AU48+AZ48+BE48+BJ48+BO48+BT48+BY48 -> 4399.99 | CD48: =+SUM(CB48:CC48) -> 48399.98 | CE48: =ROUND(IF($Y48<>"",$Z48,$T48)-CB48,2) -> 0.01 | CF48: =ROUND(IF($Y48<>"",$AA48,$U48)-CC48,2) -> 0.01 | CG48: IVP TARATA | CH48: Hugo Wilfredo Pilco Pari | CI48: Gerente | CJ48: 952 659 584 | CK48: Renzo Francisco Alave Alarcon | CL48: RGM N° 123-2026-GM/MPT | CM48: 46175 | CN48: 993 867 336
A49: 48 | B49: 203 | C49: TACNA | D49: TARATA | E49: SITAJARA | F49: R230411 | G49: CHALLAGUAYA (KM 0+334) - SITAJARA (KM 7+954) | H49: 7.62 | I49: AFIRMADO | J49: 735 | K49: 240 | L49: 44806 | M49: 4481 | N49: 49287 | O49: 0000208-2026 | P49: MF SOLUCIONES VIALES E.I.R.L | Q49: =+$K49 -> 240 | R49: 46113 | S49: =IF(Q49+R49=0,"",Q49+R49-1) -> 46352 | T49: 44000 | U49: =+ROUND(T49*0.1,2) -> 4400 | V49: =+SUM(T49:U49) -> 48400 | X49: =+$R49 -> 46113 | Y49: =IF(W49>0,X49+W49-1,"") | AA49: =+ROUND(Z49*0.1,2) -> 0 | AB49: =+SUM(Z49:AA49) -> 0 | AD49: =MAX(0,MIN(IF($Y49<>"",$Y49,$S49),AD$1)-MAX($R49,EOMONTH(AD$1,-1)+1)+1) -> 0 | AE49: =ROUND(IF($Z49="",$T49,$Z49)*(AD49/IF($W49="",$Q49,$W49)),2) -> 0 | AF49: =+ROUND(AE49*0.1,2) -> 0 | AG49: =+SUM(AE49:AF49) -> 0 | AI49: =MAX(0,MIN(IF($Y49<>"",$Y49,$S49),AI$1)-MAX($R49,EOMONTH(AI$1,-1)+1)+1) -> 30 | AJ49: =ROUND(IF($Z49="",$T49,$Z49)*(AI49/IF($W49="",$Q49,$W49)),2) -> 5500 | AK49: =+ROUND(AJ49*0.1,2) -> 550 | AL49: =+SUM(AJ49:AK49) -> 6050 | AN49: =MAX(0,MIN(IF($Y49<>"",$Y49,$S49),AN$1)-MAX($R49,EOMONTH(AN$1,-1)+1)+1) -> 31 | AO49: =ROUND(IF($Z49="",$T49,$Z49)*(AN49/IF($W49="",$Q49,$W49)),2) -> 5683.33 | AP49: =+ROUND(AO49*0.1,2) -> 568.33 | AQ49: =+SUM(AO49:AP49) -> 6251.66 | AS49: =MAX(0,MIN(IF($Y49<>"",$Y49,$S49),AS$1)-MAX($R49,EOMONTH(AS$1,-1)+1)+1) -> 30 | AT49: =ROUND(IF($Z49="",$T49,$Z49)*(AS49/IF($W49="",$Q49,$W49)),2) -> 5500 | AU49: =+ROUND(AT49*0.1,2) -> 550 | AV49: =+SUM(AT49:AU49) -> 6050 | AX49: =MAX(0,MIN(IF($Y49<>"",$Y49,$S49),AX$1)-MAX($R49,EOMONTH(AX$1,-1)+1)+1) -> 31 | AY49: =ROUND(IF($Z49="",$T49,$Z49)*(AX49/IF($W49="",$Q49,$W49)),2) -> 5683.33 | AZ49: =+ROUND(AY49*0.1,2) -> 568.33 | BA49: =+SUM(AY49:AZ49) -> 6251.66 | BC49: =MAX(0,MIN(IF($Y49<>"",$Y49,$S49),BC$1)-MAX($R49,EOMONTH(BC$1,-1)+1)+1) -> 31 | BD49: =ROUND(IF($Z49="",$T49,$Z49)*(BC49/IF($W49="",$Q49,$W49)),2) -> 5683.33 | BE49: =+ROUND(BD49*0.1,2) -> 568.33 | BF49: =+SUM(BD49:BE49) -> 6251.66 | BH49: =MAX(0,MIN(IF($Y49<>"",$Y49,$S49),BH$1)-MAX($R49,EOMONTH(BH$1,-1)+1)+1) -> 30 | BI49: =ROUND(IF($Z49="",$T49,$Z49)*(BH49/IF($W49="",$Q49,$W49)),2) -> 5500 | BJ49: =+ROUND(BI49*0.1,2) -> 550 | BK49: =+SUM(BI49:BJ49) -> 6050 | BM49: =MAX(0,MIN(IF($Y49<>"",$Y49,$S49),BM$1)-MAX($R49,EOMONTH(BM$1,-1)+1)+1) -> 31 | BN49: =ROUND(IF($Z49="",$T49,$Z49)*(BM49/IF($W49="",$Q49,$W49)),2) -> 5683.33 | BO49: =+ROUND(BN49*0.1,2) -> 568.33 | BP49: =+SUM(BN49:BO49) -> 6251.66 | BR49: =MAX(0,MIN(IF($Y49<>"",$Y49,$S49),BR$1)-MAX($R49,EOMONTH(BR$1,-1)+1)+1) -> 26 | BS49: =ROUND(IF($Z49="",$T49,$Z49)*(BR49/IF($W49="",$Q49,$W49)),2) -> 4766.67 | BT49: =+ROUND(BS49*0.1,2) -> 476.67 | BU49: =+SUM(BS49:BT49) -> 5243.34 | BW49: =MAX(0,MIN(IF($Y49<>"",$Y49,$S49),BW$1)-MAX($R49,EOMONTH(BW$1,-1)+1)+1) -> 0 | BX49: =ROUND(IF($Z49="",$T49,$Z49)*(BW49/IF($W49="",$Q49,$W49)),2) -> 0 | BY49: =+ROUND(BX49*0.1,2) -> 0 | BZ49: =+SUM(BX49:BY49) -> 0 | CA49: =+AD49+AI49+AN49+AS49+AX49+BC49+BH49+BM49+BR49+BW49 -> 240 | CB49: =+AE49+AJ49+AO49+AT49+AY49+BD49+BI49+BN49+BS49+BX49 -> 43999.99 | CC49: =+AF49+AK49+AP49+AU49+AZ49+BE49+BJ49+BO49+BT49+BY49 -> 4399.99 | CD49: =+SUM(CB49:CC49) -> 48399.98 | CE49: =ROUND(IF($Y49<>"",$Z49,$T49)-CB49,2) -> 0.01 | CF49: =ROUND(IF($Y49<>"",$AA49,$U49)-CC49,2) -> 0.01 | CG49: IVP TARATA | CH49: Hugo Wilfredo Pilco Pari | CI49: Gerente | CJ49: 952 659 584 | CK49: Renzo Francisco Alave Alarcon | CL49: RGM N° 123-2026-GM/MPT | CM49: 46175 | CN49: 993 867 336
A50: 49 | B50: 203 | C50: TACNA | D50: TARATA | E50: TICACO | F50: R230439 | G50: EMP. TA-103 (SECTOR TINTINI) - DESVIO SECTOR AGRICOLA PAJATA - SECTOR AGRICOLA CHURO (KM 08+240) | H50: 8.24 | I50: AFIRMADO | J50: 735 | K50: 240 | L50: 48451 | M50: 4845 | N50: 53296 | O50: 0000211-2026 | P50: MF SOLUCIONES VIALES E.I.R.L | Q50: =+$K50 -> 240 | R50: 46113 | S50: =IF(Q50+R50=0,"",Q50+R50-1) -> 46352 | T50: 44000 | U50: =+ROUND(T50*0.1,2) -> 4400 | V50: =+SUM(T50:U50) -> 48400 | X50: =+$R50 -> 46113 | Y50: =IF(W50>0,X50+W50-1,"") | AA50: =+ROUND(Z50*0.1,2) -> 0 | AB50: =+SUM(Z50:AA50) -> 0 | AD50: =MAX(0,MIN(IF($Y50<>"",$Y50,$S50),AD$1)-MAX($R50,EOMONTH(AD$1,-1)+1)+1) -> 0 | AE50: =ROUND(IF($Z50="",$T50,$Z50)*(AD50/IF($W50="",$Q50,$W50)),2) -> 0 | AF50: =+ROUND(AE50*0.1,2) -> 0 | AG50: =+SUM(AE50:AF50) -> 0 | AI50: =MAX(0,MIN(IF($Y50<>"",$Y50,$S50),AI$1)-MAX($R50,EOMONTH(AI$1,-1)+1)+1) -> 30 | AJ50: =ROUND(IF($Z50="",$T50,$Z50)*(AI50/IF($W50="",$Q50,$W50)),2) -> 5500 | AK50: =+ROUND(AJ50*0.1,2) -> 550 | AL50: =+SUM(AJ50:AK50) -> 6050 | AN50: =MAX(0,MIN(IF($Y50<>"",$Y50,$S50),AN$1)-MAX($R50,EOMONTH(AN$1,-1)+1)+1) -> 31 | AO50: =ROUND(IF($Z50="",$T50,$Z50)*(AN50/IF($W50="",$Q50,$W50)),2) -> 5683.33 | AP50: =+ROUND(AO50*0.1,2) -> 568.33 | AQ50: =+SUM(AO50:AP50) -> 6251.66 | AS50: =MAX(0,MIN(IF($Y50<>"",$Y50,$S50),AS$1)-MAX($R50,EOMONTH(AS$1,-1)+1)+1) -> 30 | AT50: =ROUND(IF($Z50="",$T50,$Z50)*(AS50/IF($W50="",$Q50,$W50)),2) -> 5500 | AU50: =+ROUND(AT50*0.1,2) -> 550 | AV50: =+SUM(AT50:AU50) -> 6050 | AX50: =MAX(0,MIN(IF($Y50<>"",$Y50,$S50),AX$1)-MAX($R50,EOMONTH(AX$1,-1)+1)+1) -> 31 | AY50: =ROUND(IF($Z50="",$T50,$Z50)*(AX50/IF($W50="",$Q50,$W50)),2) -> 5683.33 | AZ50: =+ROUND(AY50*0.1,2) -> 568.33 | BA50: =+SUM(AY50:AZ50) -> 6251.66 | BC50: =MAX(0,MIN(IF($Y50<>"",$Y50,$S50),BC$1)-MAX($R50,EOMONTH(BC$1,-1)+1)+1) -> 31 | BD50: =ROUND(IF($Z50="",$T50,$Z50)*(BC50/IF($W50="",$Q50,$W50)),2) -> 5683.33 | BE50: =+ROUND(BD50*0.1,2) -> 568.33 | BF50: =+SUM(BD50:BE50) -> 6251.66 | BH50: =MAX(0,MIN(IF($Y50<>"",$Y50,$S50),BH$1)-MAX($R50,EOMONTH(BH$1,-1)+1)+1) -> 30 | BI50: =ROUND(IF($Z50="",$T50,$Z50)*(BH50/IF($W50="",$Q50,$W50)),2) -> 5500 | BJ50: =+ROUND(BI50*0.1,2) -> 550 | BK50: =+SUM(BI50:BJ50) -> 6050 | BM50: =MAX(0,MIN(IF($Y50<>"",$Y50,$S50),BM$1)-MAX($R50,EOMONTH(BM$1,-1)+1)+1) -> 31 | BN50: =ROUND(IF($Z50="",$T50,$Z50)*(BM50/IF($W50="",$Q50,$W50)),2) -> 5683.33 | BO50: =+ROUND(BN50*0.1,2) -> 568.33 | BP50: =+SUM(BN50:BO50) -> 6251.66 | BR50: =MAX(0,MIN(IF($Y50<>"",$Y50,$S50),BR$1)-MAX($R50,EOMONTH(BR$1,-1)+1)+1) -> 26 | BS50: =ROUND(IF($Z50="",$T50,$Z50)*(BR50/IF($W50="",$Q50,$W50)),2) -> 4766.67 | BT50: =+ROUND(BS50*0.1,2) -> 476.67 | BU50: =+SUM(BS50:BT50) -> 5243.34 | BW50: =MAX(0,MIN(IF($Y50<>"",$Y50,$S50),BW$1)-MAX($R50,EOMONTH(BW$1,-1)+1)+1) -> 0 | BX50: =ROUND(IF($Z50="",$T50,$Z50)*(BW50/IF($W50="",$Q50,$W50)),2) -> 0 | BY50: =+ROUND(BX50*0.1,2) -> 0 | BZ50: =+SUM(BX50:BY50) -> 0 | CA50: =+AD50+AI50+AN50+AS50+AX50+BC50+BH50+BM50+BR50+BW50 -> 240 | CB50: =+AE50+AJ50+AO50+AT50+AY50+BD50+BI50+BN50+BS50+BX50 -> 43999.99 | CC50: =+AF50+AK50+AP50+AU50+AZ50+BE50+BJ50+BO50+BT50+BY50 -> 4399.99 | CD50: =+SUM(CB50:CC50) -> 48399.98 | CE50: =ROUND(IF($Y50<>"",$Z50,$T50)-CB50,2) -> 0.01 | CF50: =ROUND(IF($Y50<>"",$AA50,$U50)-CC50,2) -> 0.01 | CG50: IVP TARATA | CH50: Hugo Wilfredo Pilco Pari | CI50: Gerente | CJ50: 952 659 584 | CK50: Renzo Francisco Alave Alarcon | CL50: RGM N° 123-2026-GM/MPT | CM50: 46175 | CN50: 993 867 336
A51: 50 | B51: 203 | C51: TACNA | D51: TARATA | E51: ESTIQUE Y ESTIQUE PAMPA | F51: R230402 | G51: EMP. PE-38 (SECTOR QUEOQUELA)-EMPP. TA-567 | H51: 6.446 | I51: AFIRMADO | J51: 735 | K51: 240 | L51: 37902 | M51: 3790 | N51: 41692 | O51: 0000210-2026 | P51: MF SOLUCIONES VIALES E.I.R.L | Q51: =+$K51 -> 240 | R51: 46113 | S51: =IF(Q51+R51=0,"",Q51+R51-1) -> 46352 | T51: 37900 | U51: =+ROUND(T51*0.1,2) -> 3790 | V51: =+SUM(T51:U51) -> 41690 | X51: =+$R51 -> 46113 | Y51: =IF(W51>0,X51+W51-1,"") | AA51: =+ROUND(Z51*0.1,2) -> 0 | AB51: =+SUM(Z51:AA51) -> 0 | AD51: =MAX(0,MIN(IF($Y51<>"",$Y51,$S51),AD$1)-MAX($R51,EOMONTH(AD$1,-1)+1)+1) -> 0 | AE51: =ROUND(IF($Z51="",$T51,$Z51)*(AD51/IF($W51="",$Q51,$W51)),2) -> 0 | AF51: =+ROUND(AE51*0.1,2) -> 0 | AG51: =+SUM(AE51:AF51) -> 0 | AI51: =MAX(0,MIN(IF($Y51<>"",$Y51,$S51),AI$1)-MAX($R51,EOMONTH(AI$1,-1)+1)+1) -> 30 | AJ51: =ROUND(IF($Z51="",$T51,$Z51)*(AI51/IF($W51="",$Q51,$W51)),2) -> 4737.5 | AK51: =+ROUND(AJ51*0.1,2) -> 473.75 | AL51: =+SUM(AJ51:AK51) -> 5211.25 | AN51: =MAX(0,MIN(IF($Y51<>"",$Y51,$S51),AN$1)-MAX($R51,EOMONTH(AN$1,-1)+1)+1) -> 31 | AO51: =ROUND(IF($Z51="",$T51,$Z51)*(AN51/IF($W51="",$Q51,$W51)),2) -> 4895.42 | AP51: =+ROUND(AO51*0.1,2) -> 489.54 | AQ51: =+SUM(AO51:AP51) -> 5384.96 | AS51: =MAX(0,MIN(IF($Y51<>"",$Y51,$S51),AS$1)-MAX($R51,EOMONTH(AS$1,-1)+1)+1) -> 30 | AT51: =ROUND(IF($Z51="",$T51,$Z51)*(AS51/IF($W51="",$Q51,$W51)),2) -> 4737.5 | AU51: =+ROUND(AT51*0.1,2) -> 473.75 | AV51: =+SUM(AT51:AU51) -> 5211.25 | AX51: =MAX(0,MIN(IF($Y51<>"",$Y51,$S51),AX$1)-MAX($R51,EOMONTH(AX$1,-1)+1)+1) -> 31 | AY51: =ROUND(IF($Z51="",$T51,$Z51)*(AX51/IF($W51="",$Q51,$W51)),2) -> 4895.42 | AZ51: =+ROUND(AY51*0.1,2) -> 489.54 | BA51: =+SUM(AY51:AZ51) -> 5384.96 | BC51: =MAX(0,MIN(IF($Y51<>"",$Y51,$S51),BC$1)-MAX($R51,EOMONTH(BC$1,-1)+1)+1) -> 31 | BD51: =ROUND(IF($Z51="",$T51,$Z51)*(BC51/IF($W51="",$Q51,$W51)),2) -> 4895.42 | BE51: =+ROUND(BD51*0.1,2) -> 489.54 | BF51: =+SUM(BD51:BE51) -> 5384.96 | BH51: =MAX(0,MIN(IF($Y51<>"",$Y51,$S51),BH$1)-MAX($R51,EOMONTH(BH$1,-1)+1)+1) -> 30 | BI51: =ROUND(IF($Z51="",$T51,$Z51)*(BH51/IF($W51="",$Q51,$W51)),2) -> 4737.5 | BJ51: =+ROUND(BI51*0.1,2) -> 473.75 | BK51: =+SUM(BI51:BJ51) -> 5211.25 | BM51: =MAX(0,MIN(IF($Y51<>"",$Y51,$S51),BM$1)-MAX($R51,EOMONTH(BM$1,-1)+1)+1) -> 31 | BN51: =ROUND(IF($Z51="",$T51,$Z51)*(BM51/IF($W51="",$Q51,$W51)),2) -> 4895.42 | BO51: =+ROUND(BN51*0.1,2) -> 489.54 | BP51: =+SUM(BN51:BO51) -> 5384.96 | BR51: =MAX(0,MIN(IF($Y51<>"",$Y51,$S51),BR$1)-MAX($R51,EOMONTH(BR$1,-1)+1)+1) -> 26 | BS51: =ROUND(IF($Z51="",$T51,$Z51)*(BR51/IF($W51="",$Q51,$W51)),2) -> 4105.83 | BT51: =+ROUND(BS51*0.1,2) -> 410.58 | BU51: =+SUM(BS51:BT51) -> 4516.41 | BW51: =MAX(0,MIN(IF($Y51<>"",$Y51,$S51),BW$1)-MAX($R51,EOMONTH(BW$1,-1)+1)+1) -> 0 | BX51: =ROUND(IF($Z51="",$T51,$Z51)*(BW51/IF($W51="",$Q51,$W51)),2) -> 0 | BY51: =+ROUND(BX51*0.1,2) -> 0 | BZ51: =+SUM(BX51:BY51) -> 0 | CA51: =+AD51+AI51+AN51+AS51+AX51+BC51+BH51+BM51+BR51+BW51 -> 240 | CB51: =+AE51+AJ51+AO51+AT51+AY51+BD51+BI51+BN51+BS51+BX51 -> 37900.01 | CC51: =+AF51+AK51+AP51+AU51+AZ51+BE51+BJ51+BO51+BT51+BY51 -> 3789.99 | CD51: =+SUM(CB51:CC51) -> 41690 | CE51: =ROUND(IF($Y51<>"",$Z51,$T51)-CB51,2) -> -0.01 | CF51: =ROUND(IF($Y51<>"",$AA51,$U51)-CC51,2) -> 0.01 | CG51: IVP TARATA | CH51: Hugo Wilfredo Pilco Pari | CI51: Gerente | CJ51: 952 659 584 | CK51: Renzo Francisco Alave Alarcon | CL51: RGM N° 123-2026-GM/MPT | CM51: 46175 | CN51: 993 867 336

Sheet Hvca
A1: IDENTIFICADOR | B1: N° CONVENIO | C1: DEPARTAMENTO | D1: PROVINCIA | E1: DISTRITO | F1: CÓDIGO DE RUTA | G1: DENOMINACION DE INTERVENCION | H1: LONGITUD TOTAL (km) | I1: TIPO DE SUPERFICIE | J1: COSTO (km/mes) | K1: PLAZO (dc) | L1: EJECUCIÓN S/ | M1: GG.OO S/ | N1: TOTAL S/ | O1: N° DE CONTRATO | P1: CONTRATISTA | Q1: PLAZO CONTRACTUAL (dc) | R1: F. INICIO MANTENIMIENTO | S1: F. TERMINO MANTENIMIENTO | T1: MONTO CONTRATADO | U1: GASTOS OPERATIVOS (S/) | V1: TOTAL (S/) | W1: PLAZO DE ADENDA (dc) | X1: F. INICIO MANTENIMIENTO | Y1: F. TERMINO MANTENIMIENTO | Z1: MONTO DE ADENDA | AA1: GASTOS OPERATIVOS (S/) | AB1: TOTAL (S/) | AC1: N° TRAMITE | AD1: 46112 | AE1: MANTENIMIENTO S/ | AF1: GASTOS OPERATIVOS S/ | AG1: TOTAL S/ | AH1: N° TRAMITE | AI1: 46142 | AJ1: MANTENIMIENTO S/ | AK1: GASTOS OPERATIVOS S/ | AL1: TOTAL S/ | AM1: N° TRAMITE | AN1: 46173 | AO1: MANTENIMIENTO S/ | AP1: GASTOS OPERATIVOS S/ | AQ1: TOTAL S/ | AR1: N° TRAMITE | AS1: 46203 | AT1: MANTENIMIENTO S/ | AU1: GASTOS OPERATIVOS S/ | AV1: TOTAL S/ | AW1: N° TRAMITE | AX1: 46234 | AY1: MANTENIMIENTO S/ | AZ1: GASTOS OPERATIVOS S/ | BA1: TOTAL S/ | BB1: N° TRAMITE | BC1: 46265 | BD1: MANTENIMIENTO S/ | BE1: GASTOS OPERATIVOS S/ | BF1: TOTAL S/ | BG1: N° TRAMITE | BH1: 46295 | BI1: MANTENIMIENTO S/ | BJ1: GASTOS OPERATIVOS S/ | BK1: TOTAL S/ | BL1: N° TRAMITE | BM1: 46326 | BN1: MANTENIMIENTO S/ | BO1: GASTOS OPERATIVOS S/ | BP1: TOTAL S/ | BQ1: N° TRAMITE | BR1: 46356 | BS1: MANTENIMIENTO S/ | BT1: GASTOS OPERATIVOS S/ | BU1: TOTAL S/ | BV1: N° TRAMITE | BW1: 46387 | BX1: MANTENIMIENTO S/ | BY1: GASTOS OPERATIVOS S/ | BZ1: TOTAL S/ | CA1: TOTAL DIAS EJECUTADOS | CB1: MANTENIMIENTO S/ | CC1: GASTOS OPERATIVOS S/ | CD1: TOTAL S/ | CE1: ERROR MANTENIMIENTO | CF1: ERROR GASTOS OPERATIVOS | CG1: AREA USUARIA | CH1: RESPONSABLE DE AREA USUARIA | CI1: CARGO | CJ1: TELEFONO AU | CK1: INSPECTOR | CL1: DOC. DESIGNACIÓN | CM1: FECHA DESIGNACIÓN | CN1: TELEFONO INSPECTOR | CO1: MONITOR | CP1: TELEFONO MONITOR
A2: 51 | B2: 105 | C2: HUANCAVELICA | D2: ACOBAMBA | E2: ACOBAMBA; POMACOCHA | F2: HV-751; HV-755 | G2: EMP. PE-3S M (CHILLCAPITE) - CCARABAMBA (KM 5+823), SACHAORCCO (KM 7+974) - EMP. PE-3S M (TORORUMI); EMP. PE-3S M (VIRGEN DE LOURDES) - EMP. HV-751 (SUMACCLLACCTA) | H2: 17 | I2: AFIRMADO | J2: 804 | K2: 240 | L2: 109344 | M2: 10935 | N2: 120279 | O2: 026-2026-CHO-GG/IVP/A | P2: GRUPO ESCOBAR SERVICIOS GENERALES SOCIEDAD ANONIMA CERRADA - GRUGEN S.A.C | Q2: =+$K2 -> 240 | R2: 46119 | S2: =IF(Q2+R2=0,"",Q2+R2-1) -> 46358 | T2: 109344 | U2: =+ROUND(T2*0.1,2) -> 10934.4 | V2: =+SUM(T2:U2) -> 120278.4 | X2: =+$R2 -> 46119 | Y2: =IF(W2>0,X2+W2-1,"") | AA2: =+ROUND(Z2*0.1,2) -> 0 | AB2: =+SUM(Z2:AA2) -> 0 | AD2: =MAX(0,MIN(IF($Y2<>"",$Y2,$S2),AD$1)-MAX($R2,EOMONTH(AD$1,-1)+1)+1) -> 0 | AE2: =ROUND(IF($Z2="",$T2,$Z2)*(AD2/IF($W2="",$Q2,$W2)),2) -> 0 | AF2: =+ROUND(AE2*0.1,2) -> 0 | AG2: =+SUM(AE2:AF2) -> 0 | AI2: =MAX(0,MIN(IF($Y2<>"",$Y2,$S2),AI$1)-MAX($R2,EOMONTH(AI$1,-1)+1)+1) -> 24 | AJ2: =ROUND(IF($Z2="",$T2,$Z2)*(AI2/IF($W2="",$Q2,$W2)),2) -> 10934.4 | AK2: =+ROUND(AJ2*0.1,2) -> 1093.44 | AL2: =+SUM(AJ2:AK2) -> 12027.84 | AN2: =MAX(0,MIN(IF($Y2<>"",$Y2,$S2),AN$1)-MAX($R2,EOMONTH(AN$1,-1)+1)+1) -> 31 | AO2: =ROUND(IF($Z2="",$T2,$Z2)*(AN2/IF($W2="",$Q2,$W2)),2) -> 14123.6 | AP2: =+ROUND(AO2*0.1,2) -> 1412.36 | AQ2: =+SUM(AO2:AP2) -> 15535.96 | AS2: =MAX(0,MIN(IF($Y2<>"",$Y2,$S2),AS$1)-MAX($R2,EOMONTH(AS$1,-1)+1)+1) -> 30 | AT2: =ROUND(IF($Z2="",$T2,$Z2)*(AS2/IF($W2="",$Q2,$W2)),2) -> 13668 | AU2: =+ROUND(AT2*0.1,2) -> 1366.8 | AV2: =+SUM(AT2:AU2) -> 15034.8 | AX2: =MAX(0,MIN(IF($Y2<>"",$Y2,$S2),AX$1)-MAX($R2,EOMONTH(AX$1,-1)+1)+1) -> 31 | AY2: =ROUND(IF($Z2="",$T2,$Z2)*(AX2/IF($W2="",$Q2,$W2)),2) -> 14123.6 | AZ2: =+ROUND(AY2*0.1,2) -> 1412.36 | BA2: =+SUM(AY2:AZ2) -> 15535.96 | BC2: =MAX(0,MIN(IF($Y2<>"",$Y2,$S2),BC$1)-MAX($R2,EOMONTH(BC$1,-1)+1)+1) -> 31 | BD2: =ROUND(IF($Z2="",$T2,$Z2)*(BC2/IF($W2="",$Q2,$W2)),2) -> 14123.6 | BE2: =+ROUND(BD2*0.1,2) -> 1412.36 | BF2: =+SUM(BD2:BE2) -> 15535.96 | BH2: =MAX(0,MIN(IF($Y2<>"",$Y2,$S2),BH$1)-MAX($R2,EOMONTH(BH$1,-1)+1)+1) -> 30 | BI2: =ROUND(IF($Z2="",$T2,$Z2)*(BH2/IF($W2="",$Q2,$W2)),2) -> 13668 | BJ2: =+ROUND(BI2*0.1,2) -> 1366.8 | BK2: =+SUM(BI2:BJ2) -> 15034.8 | BM2: =MAX(0,MIN(IF($Y2<>"",$Y2,$S2),BM$1)-MAX($R2,EOMONTH(BM$1,-1)+1)+1) -> 31 | BN2: =ROUND(IF($Z2="",$T2,$Z2)*(BM2/IF($W2="",$Q2,$W2)),2) -> 14123.6 | BO2: =+ROUND(BN2*0.1,2) -> 1412.36 | BP2: =+SUM(BN2:BO2) -> 15535.96 | BR2: =MAX(0,MIN(IF($Y2<>"",$Y2,$S2),BR$1)-MAX($R2,EOMONTH(BR$1,-1)+1)+1) -> 30 | BS2: =ROUND(IF($Z2="",$T2,$Z2)*(BR2/IF($W2="",$Q2,$W2)),2) -> 13668 | BT2: =+ROUND(BS2*0.1,2) -> 1366.8 | BU2: =+SUM(BS2:BT2) -> 15034.8 | BW2: =MAX(0,MIN(IF($Y2<>"",$Y2,$S2),BW$1)-MAX($R2,EOMONTH(BW$1,-1)+1)+1) -> 2 | BX2: =ROUND(IF($Z2="",$T2,$Z2)*(BW2/IF($W2="",$Q2,$W2)),2) -> 911.2 | BY2: =+ROUND(BX2*0.1,2) -> 91.12 | BZ2: =+SUM(BX2:BY2) -> 1002.32 | CA2: =+AD2+AI2+AN2+AS2+AX2+BC2+BH2+BM2+BR2+BW2 -> 240 | CB2: =+AE2+AJ2+AO2+AT2+AY2+BD2+BI2+BN2+BS2+BX2 -> 109344 | CC2: =+AF2+AK2+AP2+AU2+AZ2+BE2+BJ2+BO2+BT2+BY2 -> 10934.4 | CD2: =+SUM(CB2:CC2) -> 120278.4 | CE2: =ROUND(IF($Y2<>"",$Z2,$T2)-CB2,2) -> 0 | CF2: =ROUND(IF($Y2<>"",$AA2,$U2)-CC2,2) -> 0 | CG2: IVP ACOBAMBA | CH2: Carlos Hinojosa Orejon | CI2: Gerente | CJ2: 956 786 924 | CK2: Nelson Aguilar Ceron | CL2: Resolución Gerencial N° 004-2026/MPA-IVP-A-GG/CHO | CM2: 46092 | CN2: 900 588 416
A3: 52 | B3: 105 | C3: HUANCAVELICA | D3: ACOBAMBA | E3: ROSARIO; ACOBAMBA | F3: HV-757; HV-758 | G3: EMP. HV-751 (CHIRAPACCASA) - CHECCHE - HUAYLLAPATA II; DV.ROSARIO (KM 05+095) - CCARHUACC | H3: 14.086 | I3: AFIRMADO | J3: 798 | K3: 240 | L3: 89926 | M3: 8993 | N3: 98919 | O3: 027-2026-CHO-GG/IVP/A | P3: CONSTRUCTORA Y SERVICIOS MULTIPLES HERMANOS AZORZA SAC | Q3: =+$K3 -> 240 | R3: 46119 | S3: =IF(Q3+R3=0,"",Q3+R3-1) -> 46358 | T3: 89926 | U3: =+ROUND(T3*0.1,2) -> 8992.6 | V3: =+SUM(T3:U3) -> 98918.6 | X3: =+$R3 -> 46119 | Y3: =IF(W3>0,X3+W3-1,"") | AA3: =+ROUND(Z3*0.1,2) -> 0 | AB3: =+SUM(Z3:AA3) -> 0 | AD3: =MAX(0,MIN(IF($Y3<>"",$Y3,$S3),AD$1)-MAX($R3,EOMONTH(AD$1,-1)+1)+1) -> 0 | AE3: =ROUND(IF($Z3="",$T3,$Z3)*(AD3/IF($W3="",$Q3,$W3)),2) -> 0 | AF3: =+ROUND(AE3*0.1,2) -> 0 | AG3: =+SUM(AE3:AF3) -> 0 | AI3: =MAX(0,MIN(IF($Y3<>"",$Y3,$S3),AI$1)-MAX($R3,EOMONTH(AI$1,-1)+1)+1) -> 24 | AJ3: =ROUND(IF($Z3="",$T3,$Z3)*(AI3/IF($W3="",$Q3,$W3)),2) -> 8992.6 | AK3: =+ROUND(AJ3*0.1,2) -> 899.26 | AL3: =+SUM(AJ3:AK3) -> 9891.86 | AN3: =MAX(0,MIN(IF($Y3<>"",$Y3,$S3),AN$1)-MAX($R3,EOMONTH(AN$1,-1)+1)+1) -> 31 | AO3: =ROUND(IF($Z3="",$T3,$Z3)*(AN3/IF($W3="",$Q3,$W3)),2) -> 11615.44 | AP3: =+ROUND(AO3*0.1,2) -> 1161.54 | AQ3: =+SUM(AO3:AP3) -> 12776.98 | AS3: =MAX(0,MIN(IF($Y3<>"",$Y3,$S3),AS$1)-MAX($R3,EOMONTH(AS$1,-1)+1)+1) -> 30 | AT3: =ROUND(IF($Z3="",$T3,$Z3)*(AS3/IF($W3="",$Q3,$W3)),2) -> 11240.75 | AU3: =+ROUND(AT3*0.1,2) -> 1124.08 | AV3: =+SUM(AT3:AU3) -> 12364.83 | AX3: =MAX(0,MIN(IF($Y3<>"",$Y3,$S3),AX$1)-MAX($R3,EOMONTH(AX$1,-1)+1)+1) -> 31 | AY3: =ROUND(IF($Z3="",$T3,$Z3)*(AX3/IF($W3="",$Q3,$W3)),2) -> 11615.44 | AZ3: =+ROUND(AY3*0.1,2) -> 1161.54 | BA3: =+SUM(AY3:AZ3) -> 12776.98 | BC3: =MAX(0,MIN(IF($Y3<>"",$Y3,$S3),BC$1)-MAX($R3,EOMONTH(BC$1,-1)+1)+1) -> 31 | BD3: =ROUND(IF($Z3="",$T3,$Z3)*(BC3/IF($W3="",$Q3,$W3)),2) -> 11615.44 | BE3: =+ROUND(BD3*0.1,2) -> 1161.54 | BF3: =+SUM(BD3:BE3) -> 12776.98 | BH3: =MAX(0,MIN(IF($Y3<>"",$Y3,$S3),BH$1)-MAX($R3,EOMONTH(BH$1,-1)+1)+1) -> 30 | BI3: =ROUND(IF($Z3="",$T3,$Z3)*(BH3/IF($W3="",$Q3,$W3)),2) -> 11240.75 | BJ3: =+ROUND(BI3*0.1,2) -> 1124.08 | BK3: =+SUM(BI3:BJ3) -> 12364.83 | BM3: =MAX(0,MIN(IF($Y3<>"",$Y3,$S3),BM$1)-MAX($R3,EOMONTH(BM$1,-1)+1)+1) -> 31 | BN3: =ROUND(IF($Z3="",$T3,$Z3)*(BM3/IF($W3="",$Q3,$W3)),2) -> 11615.44 | BO3: =+ROUND(BN3*0.1,2) -> 1161.54 | BP3: =+SUM(BN3:BO3) -> 12776.98 | BR3: =MAX(0,MIN(IF($Y3<>"",$Y3,$S3),BR$1)-MAX($R3,EOMONTH(BR$1,-1)+1)+1) -> 30 | BS3: =ROUND(IF($Z3="",$T3,$Z3)*(BR3/IF($W3="",$Q3,$W3)),2) -> 11240.75 | BT3: =+ROUND(BS3*0.1,2) -> 1124.08 | BU3: =+SUM(BS3:BT3) -> 12364.83 | BW3: =MAX(0,MIN(IF($Y3<>"",$Y3,$S3),BW$1)-MAX($R3,EOMONTH(BW$1,-1)+1)+1) -> 2 | BX3: =ROUND(IF($Z3="",$T3,$Z3)*(BW3/IF($W3="",$Q3,$W3)),2) -> 749.38 | BY3: =+ROUND(BX3*0.1,2) -> 74.94 | BZ3: =+SUM(BX3:BY3) -> 824.32 | CA3: =+AD3+AI3+AN3+AS3+AX3+BC3+BH3+BM3+BR3+BW3 -> 240 | CB3: =+AE3+AJ3+AO3+AT3+AY3+BD3+BI3+BN3+BS3+BX3 -> 89925.99 | CC3: =+AF3+AK3+AP3+AU3+AZ3+BE3+BJ3+BO3+BT3+BY3 -> 8992.6 | CD3: =+SUM(CB3:CC3) -> 98918.59 | CE3: =ROUND(IF($Y3<>"",$Z3,$T3)-CB3,2) -> 0.01 | CF3: =ROUND(IF($Y3<>"",$AA3,$U3)-CC3,2) -> 0 | CG3: IVP ACOBAMBA | CH3: Carlos Hinojosa Orejon | CI3: Gerente | CJ3: 956 786 924 | CK3: Nelson Aguilar Ceron | CL3: Resolución Gerencial N° 004-2026/MPA-IVP-A-GG/CHO | CM3: 46092 | CN3: 900 588 416
A4: 53 | B4: 105 | C4: HUANCAVELICA | D4: ACOBAMBA | E4: ACOBAMBA | F4: HV-837 | G4: ACOBAMBA (KM 00+430) - BELLAVISTA - CASAVI - EMP. HV-839 | H4: 14.829 | I4: AFIRMADO | J4: 808 | K4: 240 | L4: 95855 | M4: 9586 | N4: 105441 | O4: 035-2026-CHO-GG/IVP/A | P4: CONSTRUCTORA Y SERVICIOS MULTIPLES HERMANOS AZORZA SAC | Q4: =+$K4 -> 240 | R4: 46127 | S4: =IF(Q4+R4=0,"",Q4+R4-1) -> 46366 | T4: 95855 | U4: =+ROUND(T4*0.1,2) -> 9585.5 | V4: =+SUM(T4:U4) -> 105440.5 | X4: =+$R4 -> 46127 | Y4: =IF(W4>0,X4+W4-1,"") | AA4: =+ROUND(Z4*0.1,2) -> 0 | AB4: =+SUM(Z4:AA4) -> 0 | AD4: =MAX(0,MIN(IF($Y4<>"",$Y4,$S4),AD$1)-MAX($R4,EOMONTH(AD$1,-1)+1)+1) -> 0 | AE4: =ROUND(IF($Z4="",$T4,$Z4)*(AD4/IF($W4="",$Q4,$W4)),2) -> 0 | AF4: =+ROUND(AE4*0.1,2) -> 0 | AG4: =+SUM(AE4:AF4) -> 0 | AI4: =MAX(0,MIN(IF($Y4<>"",$Y4,$S4),AI$1)-MAX($R4,EOMONTH(AI$1,-1)+1)+1) -> 16 | AJ4: =ROUND(IF($Z4="",$T4,$Z4)*(AI4/IF($W4="",$Q4,$W4)),2) -> 6390.33 | AK4: =+ROUND(AJ4*0.1,2) -> 639.03 | AL4: =+SUM(AJ4:AK4) -> 7029.36 | AN4: =MAX(0,MIN(IF($Y4<>"",$Y4,$S4),AN$1)-MAX($R4,EOMONTH(AN$1,-1)+1)+1) -> 31 | AO4: =ROUND(IF($Z4="",$T4,$Z4)*(AN4/IF($W4="",$Q4,$W4)),2) -> 12381.27 | AP4: =+ROUND(AO4*0.1,2) -> 1238.13 | AQ4: =+SUM(AO4:AP4) -> 13619.4 | AS4: =MAX(0,MIN(IF($Y4<>"",$Y4,$S4),AS$1)-MAX($R4,EOMONTH(AS$1,-1)+1)+1) -> 30 | AT4: =ROUND(IF($Z4="",$T4,$Z4)*(AS4/IF($W4="",$Q4,$W4)),2) -> 11981.88 | AU4: =+ROUND(AT4*0.1,2) -> 1198.19 | AV4: =+SUM(AT4:AU4) -> 13180.07 | AX4: =MAX(0,MIN(IF($Y4<>"",$Y4,$S4),AX$1)-MAX($R4,EOMONTH(AX$1,-1)+1)+1) -> 31 | AY4: =ROUND(IF($Z4="",$T4,$Z4)*(AX4/IF($W4="",$Q4,$W4)),2) -> 12381.27 | AZ4: =+ROUND(AY4*0.1,2) -> 1238.13 | BA4: =+SUM(AY4:AZ4) -> 13619.4 | BC4: =MAX(0,MIN(IF($Y4<>"",$Y4,$S4),BC$1)-MAX($R4,EOMONTH(BC$1,-1)+1)+1) -> 31 | BD4: =ROUND(IF($Z4="",$T4,$Z4)*(BC4/IF($W4="",$Q4,$W4)),2) -> 12381.27 | BE4: =+ROUND(BD4*0.1,2) -> 1238.13 | BF4: =+SUM(BD4:BE4) -> 13619.4 | BH4: =MAX(0,MIN(IF($Y4<>"",$Y4,$S4),BH$1)-MAX($R4,EOMONTH(BH$1,-1)+1)+1) -> 30 | BI4: =ROUND(IF($Z4="",$T4,$Z4)*(BH4/IF($W4="",$Q4,$W4)),2) -> 11981.88 | BJ4: =+ROUND(BI4*0.1,2) -> 1198.19 | BK4: =+SUM(BI4:BJ4) -> 13180.07 | BM4: =MAX(0,MIN(IF($Y4<>"",$Y4,$S4),BM$1)-MAX($R4,EOMONTH(BM$1,-1)+1)+1) -> 31 | BN4: =ROUND(IF($Z4="",$T4,$Z4)*(BM4/IF($W4="",$Q4,$W4)),2) -> 12381.27 | BO4: =+ROUND(BN4*0.1,2) -> 1238.13 | BP4: =+SUM(BN4:BO4) -> 13619.4 | BR4: =MAX(0,MIN(IF($Y4<>"",$Y4,$S4),BR$1)-MAX($R4,EOMONTH(BR$1,-1)+1)+1) -> 30 | BS4: =ROUND(IF($Z4="",$T4,$Z4)*(BR4/IF($W4="",$Q4,$W4)),2) -> 11981.88 | BT4: =+ROUND(BS4*0.1,2) -> 1198.19 | BU4: =+SUM(BS4:BT4) -> 13180.07 | BW4: =MAX(0,MIN(IF($Y4<>"",$Y4,$S4),BW$1)-MAX($R4,EOMONTH(BW$1,-1)+1)+1) -> 10 | BX4: =ROUND(IF($Z4="",$T4,$Z4)*(BW4/IF($W4="",$Q4,$W4)),2) -> 3993.96 | BY4: =+ROUND(BX4*0.1,2) -> 399.4 | BZ4: =+SUM(BX4:BY4) -> 4393.36 | CA4: =+AD4+AI4+AN4+AS4+AX4+BC4+BH4+BM4+BR4+BW4 -> 240 | CB4: =+AE4+AJ4+AO4+AT4+AY4+BD4+BI4+BN4+BS4+BX4 -> 95855.01 | CC4: =+AF4+AK4+AP4+AU4+AZ4+BE4+BJ4+BO4+BT4+BY4 -> 9585.52 | CD4: =+SUM(CB4:CC4) -> 105440.53 | CE4: =ROUND(IF($Y4<>"",$Z4,$T4)-CB4,2) -> -0.01 | CF4: =ROUND(IF($Y4<>"",$AA4,$U4)-CC4,2) -> -0.02 | CG4: IVP ACOBAMBA | CH4: Carlos Hinojosa Orejon | CI4: Gerente | CJ4: 956 786 924 | CK4: Nelson Aguilar Ceron | CL4: Resolución Gerencial N° 004-2026/MPA-IVP-A-GG/CHO | CM4: 46092 | CN4: 900 588 416
A5: 54 | B5: 105 | C5: HUANCAVELICA | D5: ACOBAMBA | E5: ACOBAMBA | F5: HV-836; HV-838 | G5: EMP. PE-3SM (CCELCCAYA) - HUAYLLAPATA I - JUAN VELASCO ALVARADO - EMP. HV-837 (ACCOCCASA); EMP. HV-837 - PUTACCA - EMP. HV-837 | H5: 7.471 | I5: AFIRMADO | J5: 824 | K5: 240 | L5: 49249 | M5: 4925 | N5: 54174 | O5: 033-2026-CHO-GG/IVP/A | P5: GRUPO ESCOBAR SERVICIOS GENERALES SOCIEDAD ANONIMA CERRADA - GRUGEN S.A.C | Q5: =+$K5 -> 240 | R5: 46127 | S5: =IF(Q5+R5=0,"",Q5+R5-1) -> 46366 | T5: 49249 | U5: =+ROUND(T5*0.1,2) -> 4924.9 | V5: =+SUM(T5:U5) -> 54173.9 | X5: =+$R5 -> 46127 | Y5: =IF(W5>0,X5+W5-1,"") | AA5: =+ROUND(Z5*0.1,2) -> 0 | AB5: =+SUM(Z5:AA5) -> 0 | AD5: =MAX(0,MIN(IF($Y5<>"",$Y5,$S5),AD$1)-MAX($R5,EOMONTH(AD$1,-1)+1)+1) -> 0 | AE5: =ROUND(IF($Z5="",$T5,$Z5)*(AD5/IF($W5="",$Q5,$W5)),2) -> 0 | AF5: =+ROUND(AE5*0.1,2) -> 0 | AG5: =+SUM(AE5:AF5) -> 0 | AI5: =MAX(0,MIN(IF($Y5<>"",$Y5,$S5),AI$1)-MAX($R5,EOMONTH(AI$1,-1)+1)+1) -> 16 | AJ5: =ROUND(IF($Z5="",$T5,$Z5)*(AI5/IF($W5="",$Q5,$W5)),2) -> 3283.27 | AK5: =+ROUND(AJ5*0.1,2) -> 328.33 | AL5: =+SUM(AJ5:AK5) -> 3611.6 | AN5: =MAX(0,MIN(IF($Y5<>"",$Y5,$S5),AN$1)-MAX($R5,EOMONTH(AN$1,-1)+1)+1) -> 31 | AO5: =ROUND(IF($Z5="",$T5,$Z5)*(AN5/IF($W5="",$Q5,$W5)),2) -> 6361.33 | AP5: =+ROUND(AO5*0.1,2) -> 636.13 | AQ5: =+SUM(AO5:AP5) -> 6997.46 | AS5: =MAX(0,MIN(IF($Y5<>"",$Y5,$S5),AS$1)-MAX($R5,EOMONTH(AS$1,-1)+1)+1) -> 30 | AT5: =ROUND(IF($Z5="",$T5,$Z5)*(AS5/IF($W5="",$Q5,$W5)),2) -> 6156.13 | AU5: =+ROUND(AT5*0.1,2) -> 615.61 | AV5: =+SUM(AT5:AU5) -> 6771.74 | AX5: =MAX(0,MIN(IF($Y5<>"",$Y5,$S5),AX$1)-MAX($R5,EOMONTH(AX$1,-1)+1)+1) -> 31 | AY5: =ROUND(IF($Z5="",$T5,$Z5)*(AX5/IF($W5="",$Q5,$W5)),2) -> 6361.33 | AZ5: =+ROUND(AY5*0.1,2) -> 636.13 | BA5: =+SUM(AY5:AZ5) -> 6997.46 | BC5: =MAX(0,MIN(IF($Y5<>"",$Y5,$S5),BC$1)-MAX($R5,EOMONTH(BC$1,-1)+1)+1) -> 31 | BD5: =ROUND(IF($Z5="",$T5,$Z5)*(BC5/IF($W5="",$Q5,$W5)),2) -> 6361.33 | BE5: =+ROUND(BD5*0.1,2) -> 636.13 | BF5: =+SUM(BD5:BE5) -> 6997.46 | BH5: =MAX(0,MIN(IF($Y5<>"",$Y5,$S5),BH$1)-MAX($R5,EOMONTH(BH$1,-1)+1)+1) -> 30 | BI5: =ROUND(IF($Z5="",$T5,$Z5)*(BH5/IF($W5="",$Q5,$W5)),2) -> 6156.13 | BJ5: =+ROUND(BI5*0.1,2) -> 615.61 | BK5: =+SUM(BI5:BJ5) -> 6771.74 | BM5: =MAX(0,MIN(IF($Y5<>"",$Y5,$S5),BM$1)-MAX($R5,EOMONTH(BM$1,-1)+1)+1) -> 31 | BN5: =ROUND(IF($Z5="",$T5,$Z5)*(BM5/IF($W5="",$Q5,$W5)),2) -> 6361.33 | BO5: =+ROUND(BN5*0.1,2) -> 636.13 | BP5: =+SUM(BN5:BO5) -> 6997.46 | BR5: =MAX(0,MIN(IF($Y5<>"",$Y5,$S5),BR$1)-MAX($R5,EOMONTH(BR$1,-1)+1)+1) -> 30 | BS5: =ROUND(IF($Z5="",$T5,$Z5)*(BR5/IF($W5="",$Q5,$W5)),2) -> 6156.13 | BT5: =+ROUND(BS5*0.1,2) -> 615.61 | BU5: =+SUM(BS5:BT5) -> 6771.74 | BW5: =MAX(0,MIN(IF($Y5<>"",$Y5,$S5),BW$1)-MAX($R5,EOMONTH(BW$1,-1)+1)+1) -> 10 | BX5: =ROUND(IF($Z5="",$T5,$Z5)*(BW5/IF($W5="",$Q5,$W5)),2) -> 2052.04 | BY5: =+ROUND(BX5*0.1,2) -> 205.2 | BZ5: =+SUM(BX5:BY5) -> 2257.24 | CA5: =+AD5+AI5+AN5+AS5+AX5+BC5+BH5+BM5+BR5+BW5 -> 240 | CB5: =+AE5+AJ5+AO5+AT5+AY5+BD5+BI5+BN5+BS5+BX5 -> 49249.02 | CC5: =+AF5+AK5+AP5+AU5+AZ5+BE5+BJ5+BO5+BT5+BY5 -> 4924.88 | CD5: =+SUM(CB5:CC5) -> 54173.9 | CE5: =ROUND(IF($Y5<>"",$Z5,$T5)-CB5,2) -> -0.02 | CF5: =ROUND(IF($Y5<>"",$AA5,$U5)-CC5,2) -> 0.02 | CG5: IVP ACOBAMBA | CH5: Carlos Hinojosa Orejon | CI5: Gerente | CJ5: 956 786 924 | CK5: Nelson Aguilar Ceron | CL5: Resolución Gerencial N° 004-2026/MPA-IVP-A-GG/CHO | CM5: 46092 | CN5: 900 588 416
A6: 55 | B6: 105 | C6: HUANCAVELICA | D6: ACOBAMBA | E6: ACOBAMBA | F6: HV-834; HV-835 | G6: EMP. PE-3S M (CCOCHCCACCASA) - OCCOROPAMPA - MITO; EMP. HV-834 (OCCOROPAMPA) -TRES DE OCTUBRE - EMP. HV-837 (ACCOCCASA) | H6: 11.487 | I6: AFIRMADO | J6: 806 | K6: 240 | L6: 74069 | M6: 7407 | N6: 81476 | O6: 030-2026-CHO-GG/IVP/A | P6: CONSTRUCTORA Y SERVICIOS MULTIPLES HERMANOS AZORZA SAC | Q6: =+$K6 -> 240 | R6: 46122 | S6: =IF(Q6+R6=0,"",Q6+R6-1) -> 46361 | T6: 74069 | U6: =+ROUND(T6*0.1,2) -> 7406.9 | V6: =+SUM(T6:U6) -> 81475.9 | X6: =+$R6 -> 46122 | Y6: =IF(W6>0,X6+W6-1,"") | AA6: =+ROUND(Z6*0.1,2) -> 0 | AB6: =+SUM(Z6:AA6) -> 0 | AD6: =MAX(0,MIN(IF($Y6<>"",$Y6,$S6),AD$1)-MAX($R6,EOMONTH(AD$1,-1)+1)+1) -> 0 | AE6: =ROUND(IF($Z6="",$T6,$Z6)*(AD6/IF($W6="",$Q6,$W6)),2) -> 0 | AF6: =+ROUND(AE6*0.1,2) -> 0 | AG6: =+SUM(AE6:AF6) -> 0 | AI6: =MAX(0,MIN(IF($Y6<>"",$Y6,$S6),AI$1)-MAX($R6,EOMONTH(AI$1,-1)+1)+1) -> 21 | AJ6: =ROUND(IF($Z6="",$T6,$Z6)*(AI6/IF($W6="",$Q6,$W6)),2) -> 6481.04 | AK6: =+ROUND(AJ6*0.1,2) -> 648.1 | AL6: =+SUM(AJ6:AK6) -> 7129.14 | AN6: =MAX(0,MIN(IF($Y6<>"",$Y6,$S6),AN$1)-MAX($R6,EOMONTH(AN$1,-1)+1)+1) -> 31 | AO6: =ROUND(IF($Z6="",$T6,$Z6)*(AN6/IF($W6="",$Q6,$W6)),2) -> 9567.25 | AP6: =+ROUND(AO6*0.1,2) -> 956.73 | AQ6: =+SUM(AO6:AP6) -> 10523.98 | AS6: =MAX(0,MIN(IF($Y6<>"",$Y6,$S6),AS$1)-MAX($R6,EOMONTH(AS$1,-1)+1)+1) -> 30 | AT6: =ROUND(IF($Z6="",$T6,$Z6)*(AS6/IF($W6="",$Q6,$W6)),2) -> 9258.63 | AU6: =+ROUND(AT6*0.1,2) -> 925.86 | AV6: =+SUM(AT6:AU6) -> 10184.49 | AX6: =MAX(0,MIN(IF($Y6<>"",$Y6,$S6),AX$1)-MAX($R6,EOMONTH(AX$1,-1)+1)+1) -> 31 | AY6: =ROUND(IF($Z6="",$T6,$Z6)*(AX6/IF($W6="",$Q6,$W6)),2) -> 9567.25 | AZ6: =+ROUND(AY6*0.1,2) -> 956.73 | BA6: =+SUM(AY6:AZ6) -> 10523.98 | BC6: =MAX(0,MIN(IF($Y6<>"",$Y6,$S6),BC$1)-MAX($R6,EOMONTH(BC$1,-1)+1)+1) -> 31 | BD6: =ROUND(IF($Z6="",$T6,$Z6)*(BC6/IF($W6="",$Q6,$W6)),2) -> 9567.25 | BE6: =+ROUND(BD6*0.1,2) -> 956.73 | BF6: =+SUM(BD6:BE6) -> 10523.98 | BH6: =MAX(0,MIN(IF($Y6<>"",$Y6,$S6),BH$1)-MAX($R6,EOMONTH(BH$1,-1)+1)+1) -> 30 | BI6: =ROUND(IF($Z6="",$T6,$Z6)*(BH6/IF($W6="",$Q6,$W6)),2) -> 9258.63 | BJ6: =+ROUND(BI6*0.1,2) -> 925.86 | BK6: =+SUM(BI6:BJ6) -> 10184.49 | BM6: =MAX(0,MIN(IF($Y6<>"",$Y6,$S6),BM$1)-MAX($R6,EOMONTH(BM$1,-1)+1)+1) -> 31 | BN6: =ROUND(IF($Z6="",$T6,$Z6)*(BM6/IF($W6="",$Q6,$W6)),2) -> 9567.25 | BO6: =+ROUND(BN6*0.1,2) -> 956.73 | BP6: =+SUM(BN6:BO6) -> 10523.98 | BR6: =MAX(0,MIN(IF($Y6<>"",$Y6,$S6),BR$1)-MAX($R6,EOMONTH(BR$1,-1)+1)+1) -> 30 | BS6: =ROUND(IF($Z6="",$T6,$Z6)*(BR6/IF($W6="",$Q6,$W6)),2) -> 9258.63 | BT6: =+ROUND(BS6*0.1,2) -> 925.86 | BU6: =+SUM(BS6:BT6) -> 10184.49 | BW6: =MAX(0,MIN(IF($Y6<>"",$Y6,$S6),BW$1)-MAX($R6,EOMONTH(BW$1,-1)+1)+1) -> 5 | BX6: =ROUND(IF($Z6="",$T6,$Z6)*(BW6/IF($W6="",$Q6,$W6)),2) -> 1543.1 | BY6: =+ROUND(BX6*0.1,2) -> 154.31 | BZ6: =+SUM(BX6:BY6) -> 1697.41 | CA6: =+AD6+AI6+AN6+AS6+AX6+BC6+BH6+BM6+BR6+BW6 -> 240 | CB6: =+AE6+AJ6+AO6+AT6+AY6+BD6+BI6+BN6+BS6+BX6 -> 74069.03 | CC6: =+AF6+AK6+AP6+AU6+AZ6+BE6+BJ6+BO6+BT6+BY6 -> 7406.91 | CD6: =+SUM(CB6:CC6) -> 81475.94 | CE6: =ROUND(IF($Y6<>"",$Z6,$T6)-CB6,2) -> -0.03 | CF6: =ROUND(IF($Y6<>"",$AA6,$U6)-CC6,2) -> -0.01 | CG6: IVP ACOBAMBA | CH6: Carlos Hinojosa Orejon | CI6: Gerente | CJ6: 956 786 924 | CK6: Nelson Aguilar Ceron | CL6: Resolución Gerencial N° 004-2026/MPA-IVP-A-GG/CHO | CM6: 46092 | CN6: 900 588 416
A7: 56 | B7: 105 | C7: HUANCAVELICA | D7: ACOBAMBA | E7: ROSARIO | F7: R0902215; HV-761 | G7: EMP. PE-3SM (CHACAHUAYCCO) - PUNCHAYPAMPA; EMP. HV-106 (DV. ANDABAMBA) - PUNCHAYPAMPA (KM 07+020 | H7: 9.263 | I7: AFIRMADO | J7: 842 | K7: 240 | L7: 62396 | M7: 6240 | N7: 68636 | O7: 034-2026-CHO-GG/IVP/A | P7: CONSTRUCTORA Y SERVICIOS MULTIPLES HERMANOS AZORZA SAC | Q7: =+$K7 -> 240 | R7: 46129 | S7: =IF(Q7+R7=0,"",Q7+R7-1) -> 46368 | T7: 62396 | U7: =+ROUND(T7*0.1,2) -> 6239.6 | V7: =+SUM(T7:U7) -> 68635.6 | X7: =+$R7 -> 46129 | Y7: =IF(W7>0,X7+W7-1,"") | AA7: =+ROUND(Z7*0.1,2) -> 0 | AB7: =+SUM(Z7:AA7) -> 0 | AD7: =MAX(0,MIN(IF($Y7<>"",$Y7,$S7),AD$1)-MAX($R7,EOMONTH(AD$1,-1)+1)+1) -> 0 | AE7: =ROUND(IF($Z7="",$T7,$Z7)*(AD7/IF($W7="",$Q7,$W7)),2) -> 0 | AF7: =+ROUND(AE7*0.1,2) -> 0 | AG7: =+SUM(AE7:AF7) -> 0 | AI7: =MAX(0,MIN(IF($Y7<>"",$Y7,$S7),AI$1)-MAX($R7,EOMONTH(AI$1,-1)+1)+1) -> 14 | AJ7: =ROUND(IF($Z7="",$T7,$Z7)*(AI7/IF($W7="",$Q7,$W7)),2) -> 3639.77 | AK7: =+ROUND(AJ7*0.1,2) -> 363.98 | AL7: =+SUM(AJ7:AK7) -> 4003.75 | AN7: =MAX(0,MIN(IF($Y7<>"",$Y7,$S7),AN$1)-MAX($R7,EOMONTH(AN$1,-1)+1)+1) -> 31 | AO7: =ROUND(IF($Z7="",$T7,$Z7)*(AN7/IF($W7="",$Q7,$W7)),2) -> 8059.48 | AP7: =+ROUND(AO7*0.1,2) -> 805.95 | AQ7: =+SUM(AO7:AP7) -> 8865.43 | AS7: =MAX(0,MIN(IF($Y7<>"",$Y7,$S7),AS$1)-MAX($R7,EOMONTH(AS$1,-1)+1)+1) -> 30 | AT7: =ROUND(IF($Z7="",$T7,$Z7)*(AS7/IF($W7="",$Q7,$W7)),2) -> 7799.5 | AU7: =+ROUND(AT7*0.1,2) -> 779.95 | AV7: =+SUM(AT7:AU7) -> 8579.45 | AX7: =MAX(0,MIN(IF($Y7<>"",$Y7,$S7),AX$1)-MAX($R7,EOMONTH(AX$1,-1)+1)+1) -> 31 | AY7: =ROUND(IF($Z7="",$T7,$Z7)*(AX7/IF($W7="",$Q7,$W7)),2) -> 8059.48 | AZ7: =+ROUND(AY7*0.1,2) -> 805.95 | BA7: =+SUM(AY7:AZ7) -> 8865.43 | BC7: =MAX(0,MIN(IF($Y7<>"",$Y7,$S7),BC$1)-MAX($R7,EOMONTH(BC$1,-1)+1)+1) -> 31 | BD7: =ROUND(IF($Z7="",$T7,$Z7)*(BC7/IF($W7="",$Q7,$W7)),2) -> 8059.48 | BE7: =+ROUND(BD7*0.1,2) -> 805.95 | BF7: =+SUM(BD7:BE7) -> 8865.43 | BH7: =MAX(0,MIN(IF($Y7<>"",$Y7,$S7),BH$1)-MAX($R7,EOMONTH(BH$1,-1)+1)+1) -> 30 | BI7: =ROUND(IF($Z7="",$T7,$Z7)*(BH7/IF($W7="",$Q7,$W7)),2) -> 7799.5 | BJ7: =+ROUND(BI7*0.1,2) -> 779.95 | BK7: =+SUM(BI7:BJ7) -> 8579.45 | BM7: =MAX(0,MIN(IF($Y7<>"",$Y7,$S7),BM$1)-MAX($R7,EOMONTH(BM$1,-1)+1)+1) -> 31 | BN7: =ROUND(IF($Z7="",$T7,$Z7)*(BM7/IF($W7="",$Q7,$W7)),2) -> 8059.48 | BO7: =+ROUND(BN7*0.1,2) -> 805.95 | BP7: =+SUM(BN7:BO7) -> 8865.43 | BR7: =MAX(0,MIN(IF($Y7<>"",$Y7,$S7),BR$1)-MAX($R7,EOMONTH(BR$1,-1)+1)+1) -> 30 | BS7: =ROUND(IF($Z7="",$T7,$Z7)*(BR7/IF($W7="",$Q7,$W7)),2) -> 7799.5 | BT7: =+ROUND(BS7*0.1,2) -> 779.95 | BU7: =+SUM(BS7:BT7) -> 8579.45 | BW7: =MAX(0,MIN(IF($Y7<>"",$Y7,$S7),BW$1)-MAX($R7,EOMONTH(BW$1,-1)+1)+1) -> 12 | BX7: =ROUND(IF($Z7="",$T7,$Z7)*(BW7/IF($W7="",$Q7,$W7)),2) -> 3119.8 | BY7: =+ROUND(BX7*0.1,2) -> 311.98 | BZ7: =+SUM(BX7:BY7) -> 3431.78 | CA7: =+AD7+AI7+AN7+AS7+AX7+BC7+BH7+BM7+BR7+BW7 -> 240 | CB7: =+AE7+AJ7+AO7+AT7+AY7+BD7+BI7+BN7+BS7+BX7 -> 62395.99 | CC7: =+AF7+AK7+AP7+AU7+AZ7+BE7+BJ7+BO7+BT7+BY7 -> 6239.61 | CD7: =+SUM(CB7:CC7) -> 68635.6 | CE7: =ROUND(IF($Y7<>"",$Z7,$T7)-CB7,2) -> 0.01 | CF7: =ROUND(IF($Y7<>"",$AA7,$U7)-CC7,2) -> -0.01 | CG7: IVP ACOBAMBA | CH7: Carlos Hinojosa Orejon | CI7: Gerente | CJ7: 956 786 924 | CK7: Nelson Aguilar Ceron | CL7: Resolución Gerencial N° 004-2026/MPA-IVP-A-GG/CHO | CM7: 46092 | CN7: 900 588 416
A8: 57 | B8: 105 | C8: HUANCAVELICA | D8: ACOBAMBA | E8: PAUCARÁ; ANDABAMBA | F8: R0902227 | G8: EMP. PE-3SM (PAUCARÁ) - INCA PERCCAN - CHILLHUAPAMPA - SANTA CRUZ DE PACCHO - EMP. PE-3SM | H8: 12.122 | I8: AFIRMADO | J8: 796 | K8: 240 | L8: 77193 | M8: 7719 | N8: 84912 | O8: 038-2026-CHO-GG/IVP/A | P8: CONSTRUCTORA & CONSULTORA BYN S.A.C | Q8: =+$K8 -> 240 | R8: 46136 | S8: =IF(Q8+R8=0,"",Q8+R8-1) -> 46375 | T8: 77193 | U8: =+ROUND(T8*0.1,2) -> 7719.3 | V8: =+SUM(T8:U8) -> 84912.3 | X8: =+$R8 -> 46136 | Y8: =IF(W8>0,X8+W8-1,"") | AA8: =+ROUND(Z8*0.1,2) -> 0 | AB8: =+SUM(Z8:AA8) -> 0 | AD8: =MAX(0,MIN(IF($Y8<>"",$Y8,$S8),AD$1)-MAX($R8,EOMONTH(AD$1,-1)+1)+1) -> 0 | AE8: =ROUND(IF($Z8="",$T8,$Z8)*(AD8/IF($W8="",$Q8,$W8)),2) -> 0 | AF8: =+ROUND(AE8*0.1,2) -> 0 | AG8: =+SUM(AE8:AF8) -> 0 | AI8: =MAX(0,MIN(IF($Y8<>"",$Y8,$S8),AI$1)-MAX($R8,EOMONTH(AI$1,-1)+1)+1) -> 7 | AJ8: =ROUND(IF($Z8="",$T8,$Z8)*(AI8/IF($W8="",$Q8,$W8)),2) -> 2251.46 | AK8: =+ROUND(AJ8*0.1,2) -> 225.15 | AL8: =+SUM(AJ8:AK8) -> 2476.61 | AN8: =MAX(0,MIN(IF($Y8<>"",$Y8,$S8),AN$1)-MAX($R8,EOMONTH(AN$1,-1)+1)+1) -> 31 | AO8: =ROUND(IF($Z8="",$T8,$Z8)*(AN8/IF($W8="",$Q8,$W8)),2) -> 9970.76 | AP8: =+ROUND(AO8*0.1,2) -> 997.08 | AQ8: =+SUM(AO8:AP8) -> 10967.84 | AS8: =MAX(0,MIN(IF($Y8<>"",$Y8,$S8),AS$1)-MAX($R8,EOMONTH(AS$1,-1)+1)+1) -> 30 | AT8: =ROUND(IF($Z8="",$T8,$Z8)*(AS8/IF($W8="",$Q8,$W8)),2) -> 9649.13 | AU8: =+ROUND(AT8*0.1,2) -> 964.91 | AV8: =+SUM(AT8:AU8) -> 10614.04 | AX8: =MAX(0,MIN(IF($Y8<>"",$Y8,$S8),AX$1)-MAX($R8,EOMONTH(AX$1,-1)+1)+1) -> 31 | AY8: =ROUND(IF($Z8="",$T8,$Z8)*(AX8/IF($W8="",$Q8,$W8)),2) -> 9970.76 | AZ8: =+ROUND(AY8*0.1,2) -> 997.08 | BA8: =+SUM(AY8:AZ8) -> 10967.84 | BC8: =MAX(0,MIN(IF($Y8<>"",$Y8,$S8),BC$1)-MAX($R8,EOMONTH(BC$1,-1)+1)+1) -> 31 | BD8: =ROUND(IF($Z8="",$T8,$Z8)*(BC8/IF($W8="",$Q8,$W8)),2) -> 9970.76 | BE8: =+ROUND(BD8*0.1,2) -> 997.08 | BF8: =+SUM(BD8:BE8) -> 10967.84 | BH8: =MAX(0,MIN(IF($Y8<>"",$Y8,$S8),BH$1)-MAX($R8,EOMONTH(BH$1,-1)+1)+1) -> 30 | BI8: =ROUND(IF($Z8="",$T8,$Z8)*(BH8/IF($W8="",$Q8,$W8)),2) -> 9649.13 | BJ8: =+ROUND(BI8*0.1,2) -> 964.91 | BK8: =+SUM(BI8:BJ8) -> 10614.04 | BM8: =MAX(0,MIN(IF($Y8<>"",$Y8,$S8),BM$1)-MAX($R8,EOMONTH(BM$1,-1)+1)+1) -> 31 | BN8: =ROUND(IF($Z8="",$T8,$Z8)*(BM8/IF($W8="",$Q8,$W8)),2) -> 9970.76 | BO8: =+ROUND(BN8*0.1,2) -> 997.08 | BP8: =+SUM(BN8:BO8) -> 10967.84 | BR8: =MAX(0,MIN(IF($Y8<>"",$Y8,$S8),BR$1)-MAX($R8,EOMONTH(BR$1,-1)+1)+1) -> 30 | BS8: =ROUND(IF($Z8="",$T8,$Z8)*(BR8/IF($W8="",$Q8,$W8)),2) -> 9649.13 | BT8: =+ROUND(BS8*0.1,2) -> 964.91 | BU8: =+SUM(BS8:BT8) -> 10614.04 | BW8: =MAX(0,MIN(IF($Y8<>"",$Y8,$S8),BW$1)-MAX($R8,EOMONTH(BW$1,-1)+1)+1) -> 19 | BX8: =ROUND(IF($Z8="",$T8,$Z8)*(BW8/IF($W8="",$Q8,$W8)),2) -> 6111.11 | BY8: =+ROUND(BX8*0.1,2) -> 611.11 | BZ8: =+SUM(BX8:BY8) -> 6722.22 | CA8: =+AD8+AI8+AN8+AS8+AX8+BC8+BH8+BM8+BR8+BW8 -> 240 | CB8: =+AE8+AJ8+AO8+AT8+AY8+BD8+BI8+BN8+BS8+BX8 -> 77193 | CC8: =+AF8+AK8+AP8+AU8+AZ8+BE8+BJ8+BO8+BT8+BY8 -> 7719.31 | CD8: =+SUM(CB8:CC8) -> 84912.31 | CE8: =ROUND(IF($Y8<>"",$Z8,$T8)-CB8,2) -> 0 | CF8: =ROUND(IF($Y8<>"",$AA8,$U8)-CC8,2) -> -0.01 | CG8: IVP ACOBAMBA | CH8: Carlos Hinojosa Orejon | CI8: Gerente | CJ8: 956 786 924 | CK8: Nelson Aguilar Ceron | CL8: Resolución Gerencial N° 004-2026/MPA-IVP-A-GG/CHO | CM8: 46092 | CN8: 900 588 416
